{
  "timestamp": "2026-04-13T13:58:44.254285+00:00",
  "source": "oddstrader",
  "benchmark": "pinnacle_novig",
  "total_scraped": 421,
  "actionable": 209,
  "props": [
    {
      "sport": "MLB",
      "game": "AZ @ BAL",
      "date_time": "MON 04/13 6:35 PM",
      "player": "Coby Mayo",
      "market": "Total Hits",
      "line": "u\u00bd",
      "ev_pct": 32.5,
      "fair_prob": 0.8,
      "best_odds": "+110",
      "href": "/mlb/players/coby-mayo-630921/props/?eid=4784106&mtid=758&partid=15144&pid=630921&seid=80686&tmid=616",
      "kelly_pct": 2.0,
      "tier": "A",
      "confidence": "HIGH"
    },
    {
      "sport": "MLB",
      "game": "MIA @ ATL",
      "date_time": "MON 04/13 7:15 PM",
      "player": "Drake Baldwin",
      "market": "Player to hit a RBI",
      "line": "",
      "ev_pct": 28.7,
      "fair_prob": 0.66,
      "best_odds": "+170",
      "href": "/mlb/players/drake-baldwin-645757/props/?eid=4783158&mtid=1788&partid=638904&pid=645757&seid=80686&tmid=625",
      "kelly_pct": 2.0,
      "tier": "A",
      "confidence": "HIGH"
    },
    {
      "sport": "MLB",
      "game": "CHC @ PHI",
      "date_time": "MON 04/13 6:40 PM",
      "player": "Brandon Marsh",
      "market": "Total Hits",
      "line": "u\u00bd",
      "ev_pct": 28.6,
      "fair_prob": 0.69,
      "best_odds": "+150",
      "href": "/mlb/players/brandon-marsh-477144/props/?eid=4782392&mtid=758&partid=15144&pid=477144&seid=80686&tmid=621",
      "kelly_pct": 2.0,
      "tier": "A",
      "confidence": "HIGH"
    },
    {
      "sport": "MLB",
      "game": "BOS @ MIN",
      "date_time": "MON 04/13 7:40 PM",
      "player": "Brooks Lee",
      "market": "Player to hit a RBI",
      "line": "",
      "ev_pct": 26.5,
      "fair_prob": 0.53,
      "best_odds": "+280",
      "href": "/mlb/players/brooks-lee-627694/props/?eid=4783063&mtid=1788&partid=619747&pid=627694&seid=80686&tmid=610",
      "kelly_pct": 2.0,
      "tier": "A",
      "confidence": "HIGH"
    },
    {
      "sport": "NHL",
      "game": "DET @ TB",
      "date_time": "MON 04/13 7:00 PM",
      "player": "Moritz Seider",
      "market": "Player to score",
      "line": "",
      "ev_pct": 25.7,
      "fair_prob": 0.39,
      "best_odds": "+650",
      "href": "/nhl/players/moritz-seider-426604/props/?eid=4772363&mtid=1643&partid=386771&pid=426604&seid=70851&tmid=566",
      "kelly_pct": 2.0,
      "tier": "A",
      "confidence": "HIGH"
    },
    {
      "sport": "NHL",
      "game": "NYR @ FLA",
      "date_time": "MON 04/13 7:00 PM",
      "player": "Adam Fox",
      "market": "Player to score",
      "line": "",
      "ev_pct": 23.9,
      "fair_prob": 0.41,
      "best_odds": "+475",
      "href": "/nhl/players/adam-fox-406569/props/?eid=4772366&mtid=1643&partid=360093&pid=406569&seid=70851&tmid=591",
      "kelly_pct": 2.0,
      "tier": "A",
      "confidence": "HIGH"
    },
    {
      "sport": "MLB",
      "game": "CHC @ PHI",
      "date_time": "MON 04/13 6:40 PM",
      "player": "Brandon Marsh",
      "market": "Total Bases",
      "line": "u1\u00bd",
      "ev_pct": 22.8,
      "fair_prob": 0.88,
      "best_odds": "-185",
      "href": "/mlb/players/brandon-marsh-477144/props/?eid=4782392&mtid=596&partid=15144&pid=477144&seid=80686&tmid=621",
      "kelly_pct": 2.0,
      "tier": "A",
      "confidence": "HIGH"
    },
    {
      "sport": "MLB",
      "game": "WSH @ PIT",
      "date_time": "MON 04/13 6:40 PM",
      "player": "CJ Abrams",
      "market": "Player to hit a RBI",
      "line": "",
      "ev_pct": 22.4,
      "fair_prob": 0.52,
      "best_odds": "+240",
      "href": "/mlb/players/cj-abrams-476975/props/?eid=4783576&mtid=1788&partid=450732&pid=476975&seid=80686&tmid=623",
      "kelly_pct": 2.0,
      "tier": "A",
      "confidence": "HIGH"
    },
    {
      "sport": "MLB",
      "game": "LAA @ NYY",
      "date_time": "MON 04/13 7:05 PM",
      "player": "Yo\u00e1n Moncada",
      "market": "Total Hits",
      "line": "u\u00bd",
      "ev_pct": 21.9,
      "fair_prob": 0.68,
      "best_odds": "+115",
      "href": "/mlb/players/yo\u00e1n-moncada-187764/props/?eid=4782217&mtid=758&partid=15144&pid=187764&seid=80686&tmid=614",
      "kelly_pct": 2.0,
      "tier": "A",
      "confidence": "HIGH"
    },
    {
      "sport": "MLB",
      "game": "NYM @ LAD",
      "date_time": "MON 04/13 10:10 PM",
      "player": "Kyle Tucker",
      "market": "Total Hits",
      "line": "u\u00bd",
      "ev_pct": 21.9,
      "fair_prob": 0.58,
      "best_odds": "+175",
      "href": "/mlb/players/kyle-tucker-296641/props/?eid=4784028&mtid=758&partid=15144&pid=296641&seid=80686&tmid=635",
      "kelly_pct": 2.0,
      "tier": "A",
      "confidence": "HIGH"
    },
    {
      "sport": "MLB",
      "game": "AZ @ BAL",
      "date_time": "MON 04/13 6:35 PM",
      "player": "Corbin Carroll",
      "market": "Player to hit a RBI",
      "line": "",
      "ev_pct": 21.4,
      "fair_prob": 0.6,
      "best_odds": "+160",
      "href": "/mlb/players/corbin-carroll-477159/props/?eid=4784106&mtid=1788&partid=450915&pid=477159&seid=80686&tmid=633",
      "kelly_pct": 2.0,
      "tier": "A",
      "confidence": "HIGH"
    },
    {
      "sport": "MLB",
      "game": "LAA @ NYY",
      "date_time": "MON 04/13 7:05 PM",
      "player": "Will Warren",
      "market": "Total Strikeouts",
      "line": "u5\u00bd",
      "ev_pct": 21.1,
      "fair_prob": 0.71,
      "best_odds": "+100",
      "href": "/mlb/players/will-warren-630365/props/?eid=4782217&mtid=766&partid=15144&pid=630365&seid=80686&tmid=618",
      "kelly_pct": 2.0,
      "tier": "A",
      "confidence": "HIGH"
    },
    {
      "sport": "NHL",
      "game": "LA @ SEA",
      "date_time": "MON 04/13 9:30 PM",
      "player": "Chandler Stephenson",
      "market": "Player to score",
      "line": "",
      "ev_pct": 20.5,
      "fair_prob": 0.38,
      "best_odds": "+475",
      "href": "/nhl/players/chandler-stephenson-192264/props/?eid=4772396&mtid=1643&partid=99930&pid=192264&seid=70851&tmid=92570",
      "kelly_pct": 2.0,
      "tier": "A",
      "confidence": "HIGH"
    },
    {
      "sport": "MLB",
      "game": "HOU @ SEA",
      "date_time": "MON 04/13 4:10 PM",
      "player": "Christian Walker",
      "market": "Player to hit a RBI",
      "line": "",
      "ev_pct": 20.5,
      "fair_prob": 0.54,
      "best_odds": "+195",
      "href": "/mlb/players/christian-walker-146805/props/?eid=4783290&mtid=1788&partid=76631&pid=146805&seid=80686&tmid=630",
      "kelly_pct": 2.0,
      "tier": "A",
      "confidence": "HIGH"
    },
    {
      "sport": "MLB",
      "game": "LAA @ NYY",
      "date_time": "MON 04/13 7:05 PM",
      "player": "Travis d'Arnaud",
      "market": "Total Hits",
      "line": "u\u00bd",
      "ev_pct": 20.2,
      "fair_prob": 0.66,
      "best_odds": "+120",
      "href": "/mlb/players/travis-darnaud-147066/props/?eid=4782217&mtid=758&partid=15144&pid=147066&seid=80686&tmid=614",
      "kelly_pct": 2.0,
      "tier": "A",
      "confidence": "HIGH"
    },
    {
      "sport": "MLB",
      "game": "WSH @ PIT",
      "date_time": "MON 04/13 6:40 PM",
      "player": "Brandon Lowe",
      "market": "Player to hit a RBI",
      "line": "",
      "ev_pct": 20.0,
      "fair_prob": 0.56,
      "best_odds": "+175",
      "href": "/mlb/players/brandon-lowe-322700/props/?eid=4783576&mtid=1788&partid=261840&pid=322700&seid=80686&tmid=628",
      "kelly_pct": 2.0,
      "tier": "A",
      "confidence": "HIGH"
    },
    {
      "sport": "MLB",
      "game": "CHC @ PHI",
      "date_time": "MON 04/13 6:40 PM",
      "player": "Seiya Suzuki",
      "market": "Total Hits",
      "line": "u\u00bd",
      "ev_pct": 20.0,
      "fair_prob": 0.56,
      "best_odds": "+175",
      "href": "/mlb/players/seiya-suzuki-571899/props/?eid=4782392&mtid=758&partid=15144&pid=571899&seid=80686&tmid=626",
      "kelly_pct": 2.0,
      "tier": "A",
      "confidence": "HIGH"
    },
    {
      "sport": "NHL",
      "game": "SJ @ NSH",
      "date_time": "MON 04/13 8:00 PM",
      "player": "Alexander Wennberg",
      "market": "Player to score",
      "line": "",
      "ev_pct": 19.7,
      "fair_prob": 0.41,
      "best_odds": "+365",
      "href": "/nhl/players/alexander-wennberg-132244/props/?eid=4772384&mtid=1643&partid=78344&pid=132244&seid=70851&tmid=571",
      "kelly_pct": 2.0,
      "tier": "A",
      "confidence": "HIGH"
    },
    {
      "sport": "MLB",
      "game": "LAA @ NYY",
      "date_time": "MON 04/13 7:05 PM",
      "player": "Giancarlo Stanton",
      "market": "Player to hit a RBI",
      "line": "",
      "ev_pct": 19.2,
      "fair_prob": 0.66,
      "best_odds": "+115",
      "href": "/mlb/players/giancarlo-stanton-146769/props/?eid=4782217&mtid=1788&partid=76580&pid=146769&seid=80686&tmid=618",
      "kelly_pct": 2.0,
      "tier": "A",
      "confidence": "HIGH"
    },
    {
      "sport": "MLB",
      "game": "CLE @ STL",
      "date_time": "MON 04/13 7:45 PM",
      "player": "Alec Burleson",
      "market": "Player to hit a RBI",
      "line": "",
      "ev_pct": 19.2,
      "fair_prob": 0.56,
      "best_odds": "+170",
      "href": "/mlb/players/alec-burleson-586077/props/?eid=4782129&mtid=1788&partid=575671&pid=586077&seid=80686&tmid=627",
      "kelly_pct": 2.0,
      "tier": "A",
      "confidence": "HIGH"
    },
    {
      "sport": "MLB",
      "game": "LAA @ NYY",
      "date_time": "MON 04/13 7:05 PM",
      "player": "Randal Grichuk",
      "market": "Player to hit a RBI",
      "line": "",
      "ev_pct": 18.9,
      "fair_prob": 0.57,
      "best_odds": "+160",
      "href": "/mlb/players/randal-grichuk-147487/props/?eid=4782217&mtid=1788&partid=76715&pid=147487&seid=80686&tmid=618",
      "kelly_pct": 2.0,
      "tier": "A",
      "confidence": "HIGH"
    },
    {
      "sport": "MLB",
      "game": "WSH @ PIT",
      "date_time": "MON 04/13 6:40 PM",
      "player": "James Wood",
      "market": "Player to hit a RBI",
      "line": "",
      "ev_pct": 18.6,
      "fair_prob": 0.5,
      "best_odds": "+220",
      "href": "/mlb/players/james-wood-627329/props/?eid=4783576&mtid=1788&partid=619335&pid=627329&seid=80686&tmid=623",
      "kelly_pct": 2.0,
      "tier": "A",
      "confidence": "HIGH"
    },
    {
      "sport": "MLB",
      "game": "TEX @ ATH",
      "date_time": "MON 04/13 9:40 PM",
      "player": "Jake Burger",
      "market": "Total Hits",
      "line": "u\u00bd",
      "ev_pct": 18.4,
      "fair_prob": 0.54,
      "best_odds": "+185",
      "href": "/mlb/players/jake-burger-504554/props/?eid=4782384&mtid=758&partid=15144&pid=504554&seid=80686&tmid=613",
      "kelly_pct": 2.0,
      "tier": "A",
      "confidence": "HIGH"
    },
    {
      "sport": "MLB",
      "game": "HOU @ SEA",
      "date_time": "MON 04/13 4:10 PM",
      "player": "Cal Raleigh",
      "market": "Player to hit a RBI",
      "line": "",
      "ev_pct": 18.1,
      "fair_prob": 0.57,
      "best_odds": "+160",
      "href": "/mlb/players/cal-raleigh-477082/props/?eid=4783290&mtid=1788&partid=450839&pid=477082&seid=80686&tmid=615",
      "kelly_pct": 2.0,
      "tier": "A",
      "confidence": "HIGH"
    },
    {
      "sport": "NHL",
      "game": "CAR @ PHI",
      "date_time": "MON 04/13 7:00 PM",
      "player": "Porter Martone",
      "market": "Player to score",
      "line": "",
      "ev_pct": 17.8,
      "fair_prob": 0.45,
      "best_odds": "+275",
      "href": "/nhl/players/porter-martone-651775/props/?eid=4772370&mtid=1643&partid=645318&pid=651775&seid=70851&tmid=590",
      "kelly_pct": 2.0,
      "tier": "A",
      "confidence": "HIGH"
    },
    {
      "sport": "MLB",
      "game": "TEX @ ATH",
      "date_time": "MON 04/13 9:40 PM",
      "player": "Tyler Soderstrom",
      "market": "Player to hit a RBI",
      "line": "",
      "ev_pct": 17.8,
      "fair_prob": 0.54,
      "best_odds": "+175",
      "href": "/mlb/players/tyler-soderstrom-478016/props/?eid=4782384&mtid=1788&partid=451780&pid=478016&seid=80686&tmid=612",
      "kelly_pct": 2.0,
      "tier": "A",
      "confidence": "HIGH"
    },
    {
      "sport": "NHL",
      "game": "BUF @ CHI",
      "date_time": "MON 04/13 8:30 PM",
      "player": "Teuvo Teravainen",
      "market": "Player to score",
      "line": "",
      "ev_pct": 17.4,
      "fair_prob": 0.36,
      "best_odds": "+425",
      "href": "/nhl/players/teuvo-teravainen-112674/props/?eid=4772389&mtid=1643&partid=78181&pid=112674&seid=70851&tmid=565",
      "kelly_pct": 2.0,
      "tier": "A",
      "confidence": "HIGH"
    },
    {
      "sport": "MLB",
      "game": "WSH @ PIT",
      "date_time": "MON 04/13 6:40 PM",
      "player": "Konnor Griffin",
      "market": "Total Hits",
      "line": "u\u00bd",
      "ev_pct": 17.4,
      "fair_prob": 0.58,
      "best_odds": "+145",
      "href": "/mlb/players/konnor-griffin-676513/props/?eid=4783576&mtid=758&partid=15144&pid=676513&seid=80686&tmid=628",
      "kelly_pct": 2.0,
      "tier": "A",
      "confidence": "HIGH"
    },
    {
      "sport": "MLB",
      "game": "WSH @ PIT",
      "date_time": "MON 04/13 6:40 PM",
      "player": "Marcell Ozuna",
      "market": "Total Hits",
      "line": "u\u00bd",
      "ev_pct": 17.2,
      "fair_prob": 0.57,
      "best_odds": "+150",
      "href": "/mlb/players/marcell-ozuna-146758/props/?eid=4783576&mtid=758&partid=15144&pid=146758&seid=80686&tmid=628",
      "kelly_pct": 2.0,
      "tier": "A",
      "confidence": "HIGH"
    },
    {
      "sport": "MLB",
      "game": "CHC @ PHI",
      "date_time": "MON 04/13 6:40 PM",
      "player": "Javier Assad",
      "market": "Total Strikeouts",
      "line": "u3\u00bd",
      "ev_pct": 16.8,
      "fair_prob": 0.6,
      "best_odds": "+130",
      "href": "/mlb/players/javier-assad-584713/props/?eid=4782392&mtid=766&partid=15144&pid=584713&seid=80686&tmid=626",
      "kelly_pct": 2.0,
      "tier": "A",
      "confidence": "HIGH"
    },
    {
      "sport": "MLB",
      "game": "BOS @ MIN",
      "date_time": "MON 04/13 7:40 PM",
      "player": "Caleb Durbin",
      "market": "Total Hits",
      "line": "u\u00bd",
      "ev_pct": 16.5,
      "fair_prob": 0.54,
      "best_odds": "+170",
      "href": "/mlb/players/caleb-durbin-642140/props/?eid=4783063&mtid=758&partid=15144&pid=642140&seid=80686&tmid=617",
      "kelly_pct": 2.0,
      "tier": "A",
      "confidence": "HIGH"
    },
    {
      "sport": "NHL",
      "game": "CAR @ PHI",
      "date_time": "MON 04/13 7:00 PM",
      "player": "Shayne Gostisbehere",
      "market": "Player to score",
      "line": "",
      "ev_pct": 16.3,
      "fair_prob": 0.32,
      "best_odds": "+525",
      "href": "/nhl/players/shayne-gostisbehere-132892/props/?eid=4772370&mtid=1643&partid=77882&pid=132892&seid=70851&tmid=589",
      "kelly_pct": 1.92,
      "tier": "A",
      "confidence": "HIGH"
    },
    {
      "sport": "NHL",
      "game": "WPG @ VGK",
      "date_time": "MON 04/13 10:00 PM",
      "player": "Jonathan Toews",
      "market": "Player to score",
      "line": "",
      "ev_pct": 16.1,
      "fair_prob": 0.33,
      "best_odds": "+500",
      "href": "/nhl/players/jonathan-toews-6540/props/?eid=4772398&mtid=1643&partid=78178&pid=6540&seid=70851&tmid=588",
      "kelly_pct": 1.98,
      "tier": "A",
      "confidence": "HIGH"
    },
    {
      "sport": "MLB",
      "game": "TEX @ ATH",
      "date_time": "MON 04/13 9:40 PM",
      "player": "Nathan Eovaldi",
      "market": "Total Pitching Hits Allowed",
      "line": "u5\u00bd",
      "ev_pct": 15.9,
      "fair_prob": 0.69,
      "best_odds": "-115",
      "href": "/mlb/players/nathan-eovaldi-257938/props/?eid=4782384&mtid=765&partid=15144&pid=257938&seid=80686&tmid=613",
      "kelly_pct": 2.0,
      "tier": "A",
      "confidence": "HIGH"
    },
    {
      "sport": "MLB",
      "game": "CHC @ PHI",
      "date_time": "MON 04/13 6:40 PM",
      "player": "Alec Bohm",
      "market": "Player to hit a RBI",
      "line": "",
      "ev_pct": 15.7,
      "fair_prob": 0.5,
      "best_odds": "+195",
      "href": "/mlb/players/alec-bohm-477106/props/?eid=4782392&mtid=1788&partid=450863&pid=477106&seid=80686&tmid=621",
      "kelly_pct": 2.0,
      "tier": "A",
      "confidence": "HIGH"
    },
    {
      "sport": "MLB",
      "game": "CHC @ PHI",
      "date_time": "MON 04/13 6:40 PM",
      "player": "Adolis Garc\u00eda",
      "market": "Total Bases",
      "line": "u1\u00bd",
      "ev_pct": 15.7,
      "fair_prob": 0.8,
      "best_odds": "-180",
      "href": "/mlb/players/adolis-garc\u00eda-323754/props/?eid=4782392&mtid=596&partid=15144&pid=323754&seid=80686&tmid=621",
      "kelly_pct": 2.0,
      "tier": "A",
      "confidence": "HIGH"
    },
    {
      "sport": "MLB",
      "game": "BOS @ MIN",
      "date_time": "MON 04/13 7:40 PM",
      "player": "Austin Martin",
      "market": "Total Hits",
      "line": "u\u00bd",
      "ev_pct": 15.6,
      "fair_prob": 0.57,
      "best_odds": "+140",
      "href": "/mlb/players/austin-martin-476936/props/?eid=4783063&mtid=758&partid=15144&pid=476936&seid=80686&tmid=610",
      "kelly_pct": 2.0,
      "tier": "A",
      "confidence": "HIGH"
    },
    {
      "sport": "MLB",
      "game": "WSH @ PIT",
      "date_time": "MON 04/13 6:40 PM",
      "player": "Daylen Lile",
      "market": "Player to hit a RBI",
      "line": "",
      "ev_pct": 15.6,
      "fair_prob": 0.47,
      "best_odds": "+200",
      "href": "/mlb/players/daylen-lile-645489/props/?eid=4783576&mtid=1788&partid=638627&pid=645489&seid=80686&tmid=623",
      "kelly_pct": 2.0,
      "tier": "A",
      "confidence": "HIGH"
    },
    {
      "sport": "NHL",
      "game": "CAR @ PHI",
      "date_time": "MON 04/13 7:00 PM",
      "player": "Trevor Zegras",
      "market": "Player to score",
      "line": "",
      "ev_pct": 15.2,
      "fair_prob": 0.42,
      "best_odds": "+275",
      "href": "/nhl/players/trevor-zegras-508903/props/?eid=4772370&mtid=1643&partid=485535&pid=508903&seid=70851&tmid=590",
      "kelly_pct": 2.0,
      "tier": "A",
      "confidence": "HIGH"
    },
    {
      "sport": "NHL",
      "game": "WPG @ VGK",
      "date_time": "MON 04/13 10:00 PM",
      "player": "Josh Morrissey",
      "market": "Player to score",
      "line": "",
      "ev_pct": 15.1,
      "fair_prob": 0.28,
      "best_odds": "+675",
      "href": "/nhl/players/josh-morrissey-192316/props/?eid=4772398&mtid=1643&partid=77947&pid=192316&seid=70851&tmid=588",
      "kelly_pct": 1.47,
      "tier": "A",
      "confidence": "HIGH"
    },
    {
      "sport": "MLB",
      "game": "NYM @ LAD",
      "date_time": "MON 04/13 10:10 PM",
      "player": "Will Smith",
      "market": "Total Bases",
      "line": "u1\u00bd",
      "ev_pct": 14.9,
      "fair_prob": 0.76,
      "best_odds": "-160",
      "href": "/mlb/players/will-smith-398255/props/?eid=4784028&mtid=596&partid=15144&pid=398255&seid=80686&tmid=635",
      "kelly_pct": 2.0,
      "tier": "B",
      "confidence": "HIGH"
    },
    {
      "sport": "NHL",
      "game": "COL @ EDM",
      "date_time": "MON 04/13 9:30 PM",
      "player": "Devon Toews",
      "market": "Player to score",
      "line": "",
      "ev_pct": 14.8,
      "fair_prob": 0.28,
      "best_odds": "+650",
      "href": "/nhl/players/devon-toews-192830/props/?eid=4772392&mtid=1643&partid=153442&pid=192830&seid=70851&tmid=575",
      "kelly_pct": 1.44,
      "tier": "B",
      "confidence": "HIGH"
    },
    {
      "sport": "MLB",
      "game": "BOS @ MIN",
      "date_time": "MON 04/13 7:40 PM",
      "player": "Josh Bell",
      "market": "Player to hit a RBI",
      "line": "",
      "ev_pct": 14.8,
      "fair_prob": 0.47,
      "best_odds": "+210",
      "href": "/mlb/players/josh-bell-147343/props/?eid=4783063&mtid=1788&partid=76625&pid=147343&seid=80686&tmid=610",
      "kelly_pct": 2.0,
      "tier": "B",
      "confidence": "HIGH"
    },
    {
      "sport": "MLB",
      "game": "WSH @ PIT",
      "date_time": "MON 04/13 6:40 PM",
      "player": "Marcell Ozuna",
      "market": "Total Bases",
      "line": "u1\u00bd",
      "ev_pct": 14.8,
      "fair_prob": 0.81,
      "best_odds": "-200",
      "href": "/mlb/players/marcell-ozuna-146758/props/?eid=4783576&mtid=596&partid=15144&pid=146758&seid=80686&tmid=628",
      "kelly_pct": 2.0,
      "tier": "B",
      "confidence": "HIGH"
    },
    {
      "sport": "MLB",
      "game": "LAA @ NYY",
      "date_time": "MON 04/13 7:05 PM",
      "player": "Jo Adell",
      "market": "Total Hits",
      "line": "u\u00bd",
      "ev_pct": 14.7,
      "fair_prob": 0.55,
      "best_odds": "+150",
      "href": "/mlb/players/jo-adell-477136/props/?eid=4782217&mtid=758&partid=15144&pid=477136&seid=80686&tmid=614",
      "kelly_pct": 2.0,
      "tier": "B",
      "confidence": "HIGH"
    },
    {
      "sport": "MLB",
      "game": "NYM @ LAD",
      "date_time": "MON 04/13 10:10 PM",
      "player": "Kyle Tucker",
      "market": "Total Bases",
      "line": "u1\u00bd",
      "ev_pct": 14.7,
      "fair_prob": 0.77,
      "best_odds": "-165",
      "href": "/mlb/players/kyle-tucker-296641/props/?eid=4784028&mtid=596&partid=15144&pid=296641&seid=80686&tmid=635",
      "kelly_pct": 2.0,
      "tier": "B",
      "confidence": "HIGH"
    },
    {
      "sport": "MLB",
      "game": "AZ @ BAL",
      "date_time": "MON 04/13 6:35 PM",
      "player": "Jorge Barrosa",
      "market": "Total Hits",
      "line": "u\u00bd",
      "ev_pct": 14.6,
      "fair_prob": 0.6,
      "best_odds": "+120",
      "href": "/mlb/players/jorge-barrosa-592944/props/?eid=4784106&mtid=758&partid=15144&pid=592944&seid=80686&tmid=633",
      "kelly_pct": 2.0,
      "tier": "B",
      "confidence": "HIGH"
    },
    {
      "sport": "MLB",
      "game": "LAA @ NYY",
      "date_time": "MON 04/13 7:05 PM",
      "player": "Mike Trout",
      "market": "Player to hit a RBI",
      "line": "",
      "ev_pct": 14.5,
      "fair_prob": 0.5,
      "best_odds": "+180",
      "href": "/mlb/players/mike-trout-146672/props/?eid=4782217&mtid=1788&partid=76807&pid=146672&seid=80686&tmid=614",
      "kelly_pct": 2.0,
      "tier": "B",
      "confidence": "HIGH"
    },
    {
      "sport": "NHL",
      "game": "SJ @ NSH",
      "date_time": "MON 04/13 8:00 PM",
      "player": "Erik Haula",
      "market": "Player to score",
      "line": "",
      "ev_pct": 14.4,
      "fair_prob": 0.35,
      "best_odds": "+390",
      "href": "/nhl/players/erik-haula-112974/props/?eid=4772384&mtid=1643&partid=78087&pid=112974&seid=70851&tmid=569",
      "kelly_pct": 1.94,
      "tier": "B",
      "confidence": "HIGH"
    },
    {
      "sport": "MLB",
      "game": "BOS @ MIN",
      "date_time": "MON 04/13 7:40 PM",
      "player": "Victor Caratini",
      "market": "Total Hits",
      "line": "u\u00bd",
      "ev_pct": 14.4,
      "fair_prob": 0.64,
      "best_odds": "+100",
      "href": "/mlb/players/victor-caratini-147785/props/?eid=4783063&mtid=758&partid=15144&pid=147785&seid=80686&tmid=610",
      "kelly_pct": 2.0,
      "tier": "B",
      "confidence": "HIGH"
    },
    {
      "sport": "MLB",
      "game": "NYM @ LAD",
      "date_time": "MON 04/13 10:10 PM",
      "player": "Will Smith",
      "market": "Total Hits",
      "line": "u\u00bd",
      "ev_pct": 14.3,
      "fair_prob": 0.51,
      "best_odds": "+175",
      "href": "/mlb/players/will-smith-398255/props/?eid=4784028&mtid=758&partid=15144&pid=398255&seid=80686&tmid=635",
      "kelly_pct": 2.0,
      "tier": "B",
      "confidence": "HIGH"
    },
    {
      "sport": "MLB",
      "game": "MIA @ ATL",
      "date_time": "MON 04/13 7:15 PM",
      "player": "Eury P\u00e9rez",
      "market": "Total Pitching Hits Allowed",
      "line": "u4\u00bd",
      "ev_pct": 14.3,
      "fair_prob": 0.73,
      "best_odds": "-145",
      "href": "/mlb/players/eury-p\u00e9rez-601598/props/?eid=4783158&mtid=765&partid=15144&pid=601598&seid=80686&tmid=624",
      "kelly_pct": 2.0,
      "tier": "B",
      "confidence": "HIGH"
    },
    {
      "sport": "MLB",
      "game": "WSH @ PIT",
      "date_time": "MON 04/13 6:40 PM",
      "player": "Henry Davis",
      "market": "Total Hits",
      "line": "u\u00bd",
      "ev_pct": 14.3,
      "fair_prob": 0.61,
      "best_odds": "+115",
      "href": "/mlb/players/henry-davis-603235/props/?eid=4783576&mtid=758&partid=15144&pid=603235&seid=80686&tmid=628",
      "kelly_pct": 2.0,
      "tier": "B",
      "confidence": "HIGH"
    },
    {
      "sport": "NHL",
      "game": "COL @ EDM",
      "date_time": "MON 04/13 9:30 PM",
      "player": "Mattias Ekholm",
      "market": "Player to score",
      "line": "",
      "ev_pct": 14.1,
      "fair_prob": 0.25,
      "best_odds": "+825",
      "href": "/nhl/players/mattias-ekholm-72493/props/?eid=4772392&mtid=1643&partid=78239&pid=72493&seid=70851&tmid=579",
      "kelly_pct": 1.18,
      "tier": "B",
      "confidence": "HIGH"
    },
    {
      "sport": "MLB",
      "game": "TEX @ ATH",
      "date_time": "MON 04/13 9:40 PM",
      "player": "Jake Burger",
      "market": "Total Bases",
      "line": "u1\u00bd",
      "ev_pct": 14.1,
      "fair_prob": 0.73,
      "best_odds": "-145",
      "href": "/mlb/players/jake-burger-504554/props/?eid=4782384&mtid=596&partid=15144&pid=504554&seid=80686&tmid=613",
      "kelly_pct": 2.0,
      "tier": "B",
      "confidence": "HIGH"
    },
    {
      "sport": "NHL",
      "game": "SJ @ NSH",
      "date_time": "MON 04/13 8:00 PM",
      "player": "Nick Perbix",
      "market": "Player to score",
      "line": "",
      "ev_pct": 14.0,
      "fair_prob": 0.21,
      "best_odds": "+1300",
      "href": "/nhl/players/nick-perbix-587986/props/?eid=4772384&mtid=1643&partid=577689&pid=587986&seid=70851&tmid=569",
      "kelly_pct": 0.93,
      "tier": "B",
      "confidence": "HIGH"
    },
    {
      "sport": "NHL",
      "game": "NYR @ FLA",
      "date_time": "MON 04/13 7:00 PM",
      "player": "J.T. Miller",
      "market": "Player to score",
      "line": "",
      "ev_pct": 13.8,
      "fair_prob": 0.42,
      "best_odds": "+255",
      "href": "/nhl/players/jt-miller-82910/props/?eid=4772366&mtid=1643&partid=78059&pid=82910&seid=70851&tmid=591",
      "kelly_pct": 2.0,
      "tier": "B",
      "confidence": "HIGH"
    },
    {
      "sport": "NHL",
      "game": "COL @ EDM",
      "date_time": "MON 04/13 9:30 PM",
      "player": "Evan Bouchard",
      "market": "Player to score",
      "line": "",
      "ev_pct": 13.8,
      "fair_prob": 0.36,
      "best_odds": "+355",
      "href": "/nhl/players/evan-bouchard-280963/props/?eid=4772392&mtid=1643&partid=216760&pid=280963&seid=70851&tmid=579",
      "kelly_pct": 1.94,
      "tier": "B",
      "confidence": "HIGH"
    },
    {
      "sport": "MLB",
      "game": "AZ @ BAL",
      "date_time": "MON 04/13 6:35 PM",
      "player": "Leody Taveras",
      "market": "Total Hits",
      "line": "u\u00bd",
      "ev_pct": 13.8,
      "fair_prob": 0.55,
      "best_odds": "+145",
      "href": "/mlb/players/leody-taveras-444616/props/?eid=4784106&mtid=758&partid=15144&pid=444616&seid=80686&tmid=616",
      "kelly_pct": 2.0,
      "tier": "B",
      "confidence": "HIGH"
    },
    {
      "sport": "NHL",
      "game": "WPG @ VGK",
      "date_time": "MON 04/13 10:00 PM",
      "player": "Mark Scheifele",
      "market": "Player to score",
      "line": "",
      "ev_pct": 13.4,
      "fair_prob": 0.45,
      "best_odds": "+220",
      "href": "/nhl/players/mark-scheifele-72674/props/?eid=4772398&mtid=1643&partid=77765&pid=72674&seid=70851&tmid=588",
      "kelly_pct": 2.0,
      "tier": "B",
      "confidence": "HIGH"
    },
    {
      "sport": "NHL",
      "game": "LA @ SEA",
      "date_time": "MON 04/13 9:30 PM",
      "player": "Anze Kopitar",
      "market": "Player to score",
      "line": "",
      "ev_pct": 13.2,
      "fair_prob": 0.39,
      "best_odds": "+295",
      "href": "/nhl/players/anze-kopitar-2273/props/?eid=4772396&mtid=1643&partid=78444&pid=2273&seid=70851&tmid=573",
      "kelly_pct": 2.0,
      "tier": "B",
      "confidence": "HIGH"
    },
    {
      "sport": "MLB",
      "game": "AZ @ BAL",
      "date_time": "MON 04/13 6:35 PM",
      "player": "Gunnar Henderson",
      "market": "Player to hit a RBI",
      "line": "",
      "ev_pct": 13.2,
      "fair_prob": 0.5,
      "best_odds": "+175",
      "href": "/mlb/players/gunnar-henderson-481645/props/?eid=4784106&mtid=1788&partid=455575&pid=481645&seid=80686&tmid=616",
      "kelly_pct": 2.0,
      "tier": "B",
      "confidence": "HIGH"
    },
    {
      "sport": "MLB",
      "game": "WSH @ PIT",
      "date_time": "MON 04/13 6:40 PM",
      "player": "Jacob Young",
      "market": "Player to hit a RBI",
      "line": "",
      "ev_pct": 13.1,
      "fair_prob": 0.35,
      "best_odds": "+350",
      "href": "/mlb/players/jacob-young-608996/props/?eid=4783576&mtid=1788&partid=599908&pid=608996&seid=80686&tmid=623",
      "kelly_pct": 1.76,
      "tier": "B",
      "confidence": "HIGH"
    },
    {
      "sport": "MLB",
      "game": "CHC @ PHI",
      "date_time": "MON 04/13 6:40 PM",
      "player": "Miguel Amaya",
      "market": "Player to hit a RBI",
      "line": "",
      "ev_pct": 13.1,
      "fair_prob": 0.4,
      "best_odds": "+270",
      "href": "/mlb/players/miguel-amaya-444765/props/?eid=4782392&mtid=1788&partid=408976&pid=444765&seid=80686&tmid=626",
      "kelly_pct": 2.0,
      "tier": "B",
      "confidence": "HIGH"
    },
    {
      "sport": "NHL",
      "game": "SJ @ NSH",
      "date_time": "MON 04/13 8:00 PM",
      "player": "Ryan O'Reilly",
      "market": "Player to score",
      "line": "",
      "ev_pct": 13.0,
      "fair_prob": 0.45,
      "best_odds": "+210",
      "href": "/nhl/players/ryan-oreilly-32616/props/?eid=4772384&mtid=1643&partid=78071&pid=32616&seid=70851&tmid=569",
      "kelly_pct": 2.0,
      "tier": "B",
      "confidence": "HIGH"
    },
    {
      "sport": "NHL",
      "game": "LA @ SEA",
      "date_time": "MON 04/13 9:30 PM",
      "player": "Vince Dunn",
      "market": "Player to score",
      "line": "",
      "ev_pct": 13.0,
      "fair_prob": 0.27,
      "best_odds": "+600",
      "href": "/nhl/players/vince-dunn-190566/props/?eid=4772396&mtid=1643&partid=149744&pid=190566&seid=70851&tmid=92570",
      "kelly_pct": 1.2,
      "tier": "B",
      "confidence": "HIGH"
    },
    {
      "sport": "MLB",
      "game": "HOU @ SEA",
      "date_time": "MON 04/13 4:10 PM",
      "player": "Cole Young",
      "market": "Total Hits",
      "line": "u\u00bd",
      "ev_pct": 13.0,
      "fair_prob": 0.65,
      "best_odds": "-110",
      "href": "/mlb/players/cole-young-649848/props/?eid=4783290&mtid=758&partid=15144&pid=649848&seid=80686&tmid=615",
      "kelly_pct": 2.0,
      "tier": "B",
      "confidence": "HIGH"
    },
    {
      "sport": "MLB",
      "game": "BOS @ MIN",
      "date_time": "MON 04/13 7:40 PM",
      "player": "Caleb Durbin",
      "market": "Total Bases",
      "line": "u1\u00bd",
      "ev_pct": 12.9,
      "fair_prob": 0.76,
      "best_odds": "-170",
      "href": "/mlb/players/caleb-durbin-642140/props/?eid=4783063&mtid=596&partid=15144&pid=642140&seid=80686&tmid=617",
      "kelly_pct": 2.0,
      "tier": "B",
      "confidence": "HIGH"
    },
    {
      "sport": "MLB",
      "game": "HOU @ SEA",
      "date_time": "MON 04/13 4:10 PM",
      "player": "Cam Smith",
      "market": "Total Hits",
      "line": "u\u00bd",
      "ev_pct": 12.8,
      "fair_prob": 0.56,
      "best_odds": "+130",
      "href": "/mlb/players/cam-smith-645855/props/?eid=4783290&mtid=758&partid=15144&pid=645855&seid=80686&tmid=630",
      "kelly_pct": 2.0,
      "tier": "B",
      "confidence": "HIGH"
    },
    {
      "sport": "NHL",
      "game": "COL @ EDM",
      "date_time": "MON 04/13 9:30 PM",
      "player": "Gabriel Landeskog",
      "market": "Player to score",
      "line": "",
      "ev_pct": 12.7,
      "fair_prob": 0.4,
      "best_odds": "+270",
      "href": "/nhl/players/gabriel-landeskog-72505/props/?eid=4772392&mtid=1643&partid=77647&pid=72505&seid=70851&tmid=575",
      "kelly_pct": 2.0,
      "tier": "B",
      "confidence": "HIGH"
    },
    {
      "sport": "MLB",
      "game": "NYM @ LAD",
      "date_time": "MON 04/13 10:10 PM",
      "player": "Luis Robert",
      "market": "Total Hits",
      "line": "u\u00bd",
      "ev_pct": 12.5,
      "fair_prob": 0.53,
      "best_odds": "+145",
      "href": "/mlb/players/luis-robert-448962/props/?eid=4784028&mtid=758&partid=15144&pid=448962&seid=80686&tmid=622",
      "kelly_pct": 2.0,
      "tier": "B",
      "confidence": "HIGH"
    },
    {
      "sport": "MLB",
      "game": "HOU @ SEA",
      "date_time": "MON 04/13 4:10 PM",
      "player": "Taylor Trammell",
      "market": "Total Hits",
      "line": "u\u00bd",
      "ev_pct": 12.4,
      "fair_prob": 0.7,
      "best_odds": "-135",
      "href": "/mlb/players/taylor-trammell-477017/props/?eid=4783290&mtid=758&partid=15144&pid=477017&seid=80686&tmid=630",
      "kelly_pct": 2.0,
      "tier": "B",
      "confidence": "HIGH"
    },
    {
      "sport": "MLB",
      "game": "LAA @ NYY",
      "date_time": "MON 04/13 7:05 PM",
      "player": "Austin Wells",
      "market": "Total Hits",
      "line": "u\u00bd",
      "ev_pct": 12.3,
      "fair_prob": 0.62,
      "best_odds": "+100",
      "href": "/mlb/players/austin-wells-609890/props/?eid=4782217&mtid=758&partid=15144&pid=609890&seid=80686&tmid=618",
      "kelly_pct": 2.0,
      "tier": "B",
      "confidence": "HIGH"
    },
    {
      "sport": "MLB",
      "game": "CLE @ STL",
      "date_time": "MON 04/13 7:45 PM",
      "player": "Gavin Williams",
      "market": "Total Pitching Hits Allowed",
      "line": "u4\u00bd",
      "ev_pct": 12.2,
      "fair_prob": 0.68,
      "best_odds": "-125",
      "href": "/mlb/players/gavin-williams-603745/props/?eid=4782129&mtid=765&partid=15144&pid=603745&seid=80686&tmid=607",
      "kelly_pct": 2.0,
      "tier": "B",
      "confidence": "HIGH"
    },
    {
      "sport": "NHL",
      "game": "COL @ EDM",
      "date_time": "MON 04/13 9:30 PM",
      "player": "Sam Malinski",
      "market": "Player to score",
      "line": "",
      "ev_pct": 11.8,
      "fair_prob": 0.21,
      "best_odds": "+1000",
      "href": "/nhl/players/sam-malinski-611925/props/?eid=4772392&mtid=1643&partid=603023&pid=611925&seid=70851&tmid=575",
      "kelly_pct": 0.78,
      "tier": "B",
      "confidence": "HIGH"
    },
    {
      "sport": "MLB",
      "game": "CHC @ PHI",
      "date_time": "MON 04/13 6:40 PM",
      "player": "Adolis Garc\u00eda",
      "market": "Total Hits",
      "line": "u\u00bd",
      "ev_pct": 11.8,
      "fair_prob": 0.53,
      "best_odds": "+140",
      "href": "/mlb/players/adolis-garc\u00eda-323754/props/?eid=4782392&mtid=758&partid=15144&pid=323754&seid=80686&tmid=621",
      "kelly_pct": 2.0,
      "tier": "B",
      "confidence": "HIGH"
    },
    {
      "sport": "NHL",
      "game": "CAR @ PHI",
      "date_time": "MON 04/13 7:00 PM",
      "player": "Jamie Drysdale",
      "market": "Player to score",
      "line": "",
      "ev_pct": 11.7,
      "fair_prob": 0.23,
      "best_odds": "+825",
      "href": "/nhl/players/jamie-drysdale-495019/props/?eid=4772370&mtid=1643&partid=470362&pid=495019&seid=70851&tmid=590",
      "kelly_pct": 0.87,
      "tier": "B",
      "confidence": "HIGH"
    },
    {
      "sport": "MLB",
      "game": "BOS @ MIN",
      "date_time": "MON 04/13 7:40 PM",
      "player": "Ryan Jeffers",
      "market": "Player to hit a RBI",
      "line": "",
      "ev_pct": 11.6,
      "fair_prob": 0.44,
      "best_odds": "+210",
      "href": "/mlb/players/ryan-jeffers-476976/props/?eid=4783063&mtid=1788&partid=450733&pid=476976&seid=80686&tmid=610",
      "kelly_pct": 2.0,
      "tier": "B",
      "confidence": "HIGH"
    },
    {
      "sport": "MLB",
      "game": "AZ @ BAL",
      "date_time": "MON 04/13 6:35 PM",
      "player": "Leody Taveras",
      "market": "Total Bases",
      "line": "u1\u00bd",
      "ev_pct": 11.5,
      "fair_prob": 0.77,
      "best_odds": "-190",
      "href": "/mlb/players/leody-taveras-444616/props/?eid=4784106&mtid=596&partid=15144&pid=444616&seid=80686&tmid=616",
      "kelly_pct": 2.0,
      "tier": "B",
      "confidence": "HIGH"
    },
    {
      "sport": "MLB",
      "game": "CLE @ STL",
      "date_time": "MON 04/13 7:45 PM",
      "player": "Jordan Walker",
      "market": "Player to hit a RBI",
      "line": "",
      "ev_pct": 11.5,
      "fair_prob": 0.52,
      "best_odds": "+150",
      "href": "/mlb/players/jordan-walker-477169/props/?eid=4782129&mtid=1788&partid=450926&pid=477169&seid=80686&tmid=627",
      "kelly_pct": 2.0,
      "tier": "B",
      "confidence": "HIGH"
    },
    {
      "sport": "MLB",
      "game": "LAA @ NYY",
      "date_time": "MON 04/13 7:05 PM",
      "player": "Mike Trout",
      "market": "Total Hits",
      "line": "u\u00bd",
      "ev_pct": 11.4,
      "fair_prob": 0.55,
      "best_odds": "+130",
      "href": "/mlb/players/mike-trout-146672/props/?eid=4782217&mtid=758&partid=15144&pid=146672&seid=80686&tmid=614",
      "kelly_pct": 2.0,
      "tier": "B",
      "confidence": "HIGH"
    },
    {
      "sport": "NHL",
      "game": "DET @ TB",
      "date_time": "MON 04/13 7:00 PM",
      "player": "Dylan Larkin",
      "market": "Player to score",
      "line": "",
      "ev_pct": 11.3,
      "fair_prob": 0.48,
      "best_odds": "+176",
      "href": "/nhl/players/dylan-larkin-136108/props/?eid=4772363&mtid=1643&partid=78294&pid=136108&seid=70851&tmid=566",
      "kelly_pct": 2.0,
      "tier": "B",
      "confidence": "HIGH"
    },
    {
      "sport": "MLB",
      "game": "AZ @ BAL",
      "date_time": "MON 04/13 6:35 PM",
      "player": "Ryne Nelson",
      "market": "Total Earned Runs",
      "line": "u2\u00bd",
      "ev_pct": 11.3,
      "fair_prob": 0.65,
      "best_odds": "-115",
      "href": "/mlb/players/ryne-nelson-585941/props/?eid=4784106&mtid=767&partid=15144&pid=585941&seid=80686&tmid=633",
      "kelly_pct": 2.0,
      "tier": "B",
      "confidence": "HIGH"
    },
    {
      "sport": "NHL",
      "game": "WPG @ VGK",
      "date_time": "MON 04/13 10:00 PM",
      "player": "Tomas Hertl",
      "market": "Player to score",
      "line": "",
      "ev_pct": 11.2,
      "fair_prob": 0.42,
      "best_odds": "+225",
      "href": "/nhl/players/tomas-hertl-112805/props/?eid=4772398&mtid=1643&partid=78549&pid=112805&seid=70851&tmid=76787",
      "kelly_pct": 2.0,
      "tier": "B",
      "confidence": "HIGH"
    },
    {
      "sport": "MLB",
      "game": "CHC @ PHI",
      "date_time": "MON 04/13 6:40 PM",
      "player": "Seiya Suzuki",
      "market": "Total Bases",
      "line": "u1\u00bd",
      "ev_pct": 11.2,
      "fair_prob": 0.73,
      "best_odds": "-165",
      "href": "/mlb/players/seiya-suzuki-571899/props/?eid=4782392&mtid=596&partid=15144&pid=571899&seid=80686&tmid=626",
      "kelly_pct": 2.0,
      "tier": "B",
      "confidence": "HIGH"
    },
    {
      "sport": "MLB",
      "game": "TEX @ ATH",
      "date_time": "MON 04/13 9:40 PM",
      "player": "Joc Pederson",
      "market": "Total Hits",
      "line": "u\u00bd",
      "ev_pct": 11.1,
      "fair_prob": 0.58,
      "best_odds": "+115",
      "href": "/mlb/players/joc-pederson-147117/props/?eid=4782384&mtid=758&partid=15144&pid=147117&seid=80686&tmid=613",
      "kelly_pct": 2.0,
      "tier": "B",
      "confidence": "HIGH"
    },
    {
      "sport": "NHL",
      "game": "CAR @ PHI",
      "date_time": "MON 04/13 7:00 PM",
      "player": "Christian Dvorak",
      "market": "Player to score",
      "line": "",
      "ev_pct": 10.9,
      "fair_prob": 0.34,
      "best_odds": "+340",
      "href": "/nhl/players/christian-dvorak-170137/props/?eid=4772370&mtid=1643&partid=78541&pid=170137&seid=70851&tmid=590",
      "kelly_pct": 1.4,
      "tier": "B",
      "confidence": "HIGH"
    },
    {
      "sport": "MLB",
      "game": "CHC @ PHI",
      "date_time": "MON 04/13 6:40 PM",
      "player": "Ian Happ",
      "market": "Player to hit a RBI",
      "line": "",
      "ev_pct": 10.8,
      "fair_prob": 0.42,
      "best_odds": "+220",
      "href": "/mlb/players/ian-happ-224154/props/?eid=4782392&mtid=1788&partid=104556&pid=224154&seid=80686&tmid=626",
      "kelly_pct": 1.96,
      "tier": "B",
      "confidence": "HIGH"
    },
    {
      "sport": "MLB",
      "game": "HOU @ SEA",
      "date_time": "MON 04/13 4:10 PM",
      "player": "Julio Rodr\u00edguez",
      "market": "Total Hits",
      "line": "u\u00bd",
      "ev_pct": 10.7,
      "fair_prob": 0.46,
      "best_odds": "+185",
      "href": "/mlb/players/julio-rodr\u00edguez-477189/props/?eid=4783290&mtid=758&partid=15144&pid=477189&seid=80686&tmid=615",
      "kelly_pct": 2.0,
      "tier": "B",
      "confidence": "HIGH"
    },
    {
      "sport": "MLB",
      "game": "BOS @ MIN",
      "date_time": "MON 04/13 7:40 PM",
      "player": "Ryan Kreidler",
      "market": "Total Hits",
      "line": "u\u00bd",
      "ev_pct": 10.6,
      "fair_prob": 0.66,
      "best_odds": "-125",
      "href": "/mlb/players/ryan-kreidler-585576/props/?eid=4783063&mtid=758&partid=15144&pid=585576&seid=80686&tmid=610",
      "kelly_pct": 2.0,
      "tier": "B",
      "confidence": "HIGH"
    },
    {
      "sport": "MLB",
      "game": "HOU @ SEA",
      "date_time": "MON 04/13 4:10 PM",
      "player": "Brendan Donovan",
      "market": "Total Hits",
      "line": "u\u00bd",
      "ev_pct": 10.5,
      "fair_prob": 0.46,
      "best_odds": "+185",
      "href": "/mlb/players/brendan-donovan-564269/props/?eid=4783290&mtid=758&partid=15144&pid=564269&seid=80686&tmid=615",
      "kelly_pct": 2.0,
      "tier": "B",
      "confidence": "HIGH"
    },
    {
      "sport": "MLB",
      "game": "WSH @ PIT",
      "date_time": "MON 04/13 6:40 PM",
      "player": "Nick Yorke",
      "market": "Total Hits",
      "line": "u\u00bd",
      "ev_pct": 10.5,
      "fair_prob": 0.46,
      "best_odds": "+185",
      "href": "/mlb/players/nick-yorke-491001/props/?eid=4783576&mtid=758&partid=15144&pid=491001&seid=80686&tmid=628",
      "kelly_pct": 2.0,
      "tier": "B",
      "confidence": "HIGH"
    },
    {
      "sport": "MLB",
      "game": "NYM @ LAD",
      "date_time": "MON 04/13 10:10 PM",
      "player": "Bo Bichette",
      "market": "Total Hits",
      "line": "u\u00bd",
      "ev_pct": 10.5,
      "fair_prob": 0.46,
      "best_odds": "+185",
      "href": "/mlb/players/bo-bichette-412843/props/?eid=4784028&mtid=758&partid=15144&pid=412843&seid=80686&tmid=622",
      "kelly_pct": 2.0,
      "tier": "B",
      "confidence": "HIGH"
    },
    {
      "sport": "NHL",
      "game": "CAR @ PHI",
      "date_time": "MON 04/13 7:00 PM",
      "player": "Jaccob Slavin",
      "market": "Player to score",
      "line": "",
      "ev_pct": 10.4,
      "fair_prob": 0.17,
      "best_odds": "+1500",
      "href": "/nhl/players/jaccob-slavin-143940/props/?eid=4772370&mtid=1643&partid=78000&pid=143940&seid=70851&tmid=589",
      "kelly_pct": 0.53,
      "tier": "B",
      "confidence": "HIGH"
    },
    {
      "sport": "MLB",
      "game": "NYM @ LAD",
      "date_time": "MON 04/13 10:10 PM",
      "player": "Justin Wrobleski",
      "market": "Total Strikeouts",
      "line": "u3\u00bd",
      "ev_pct": 10.4,
      "fair_prob": 0.55,
      "best_odds": "+125",
      "href": "/mlb/players/justin-wrobleski-627810/props/?eid=4784028&mtid=766&partid=15144&pid=627810&seid=80686&tmid=635",
      "kelly_pct": 2.0,
      "tier": "B",
      "confidence": "HIGH"
    },
    {
      "sport": "MLB",
      "game": "CLE @ STL",
      "date_time": "MON 04/13 7:45 PM",
      "player": "Steven Kwan",
      "market": "Total Hits",
      "line": "u1\u00bd",
      "ev_pct": 10.4,
      "fair_prob": 0.81,
      "best_odds": "-245",
      "href": "/mlb/players/steven-kwan-564301/props/?eid=4782129&mtid=758&partid=15144&pid=564301&seid=80686&tmid=607",
      "kelly_pct": 2.0,
      "tier": "B",
      "confidence": "HIGH"
    },
    {
      "sport": "NHL",
      "game": "COL @ EDM",
      "date_time": "MON 04/13 9:30 PM",
      "player": "Jack Roslovic",
      "market": "Player to score",
      "line": "",
      "ev_pct": 10.3,
      "fair_prob": 0.32,
      "best_odds": "+370",
      "href": "/nhl/players/jack-roslovic-192290/props/?eid=4772392&mtid=1643&partid=98064&pid=192290&seid=70851&tmid=579",
      "kelly_pct": 1.21,
      "tier": "B",
      "confidence": "HIGH"
    },
    {
      "sport": "NHL",
      "game": "CAR @ PHI",
      "date_time": "MON 04/13 7:00 PM",
      "player": "Jordan Staal",
      "market": "Player to score",
      "line": "",
      "ev_pct": 10.2,
      "fair_prob": 0.32,
      "best_odds": "+370",
      "href": "/nhl/players/jordan-staal-13423/props/?eid=4772370&mtid=1643&partid=78053&pid=13423&seid=70851&tmid=589",
      "kelly_pct": 1.2,
      "tier": "B",
      "confidence": "HIGH"
    },
    {
      "sport": "NHL",
      "game": "COL @ EDM",
      "date_time": "MON 04/13 9:30 PM",
      "player": "Brent Burns",
      "market": "Player to score",
      "line": "",
      "ev_pct": 10.2,
      "fair_prob": 0.21,
      "best_odds": "+800",
      "href": "/nhl/players/brent-burns-10728/props/?eid=4772392&mtid=1643&partid=78509&pid=10728&seid=70851&tmid=575",
      "kelly_pct": 0.68,
      "tier": "B",
      "confidence": "HIGH"
    },
    {
      "sport": "NHL",
      "game": "SJ @ NSH",
      "date_time": "MON 04/13 8:00 PM",
      "player": "Roman Josi",
      "market": "Player to score",
      "line": "",
      "ev_pct": 10.1,
      "fair_prob": 0.31,
      "best_odds": "+370",
      "href": "/nhl/players/roman-josi-72662/props/?eid=4772384&mtid=1643&partid=78260&pid=72662&seid=70851&tmid=569",
      "kelly_pct": 1.13,
      "tier": "B",
      "confidence": "HIGH"
    },
    {
      "sport": "NHL",
      "game": "SJ @ NSH",
      "date_time": "MON 04/13 8:00 PM",
      "player": "Adam Wilsby",
      "market": "Player to score",
      "line": "",
      "ev_pct": 10.1,
      "fair_prob": 0.16,
      "best_odds": "+1600",
      "href": "/nhl/players/adam-wilsby-495308/props/?eid=4772384&mtid=1643&partid=470649&pid=495308&seid=70851&tmid=569",
      "kelly_pct": 0.48,
      "tier": "B",
      "confidence": "HIGH"
    },
    {
      "sport": "NHL",
      "game": "BUF @ CHI",
      "date_time": "MON 04/13 8:30 PM",
      "player": "Wyatt Kaiser",
      "market": "Player to score",
      "line": "",
      "ev_pct": 10.0,
      "fair_prob": 0.18,
      "best_odds": "+1200",
      "href": "/nhl/players/wyatt-kaiser-495323/props/?eid=4772389&mtid=1643&partid=470666&pid=495323&seid=70851&tmid=565",
      "kelly_pct": 0.55,
      "tier": "B",
      "confidence": "HIGH"
    },
    {
      "sport": "MLB",
      "game": "TEX @ ATH",
      "date_time": "MON 04/13 9:40 PM",
      "player": "Brandon Nimmo",
      "market": "Total Hits",
      "line": "u1\u00bd",
      "ev_pct": 10.0,
      "fair_prob": 0.81,
      "best_odds": "-250",
      "href": "/mlb/players/brandon-nimmo-147144/props/?eid=4782384&mtid=758&partid=15144&pid=147144&seid=80686&tmid=613",
      "kelly_pct": 2.0,
      "tier": "B",
      "confidence": "HIGH"
    },
    {
      "sport": "MLB",
      "game": "NYM @ LAD",
      "date_time": "MON 04/13 10:10 PM",
      "player": "Teoscar Hern\u00e1ndez",
      "market": "Player to hit a RBI",
      "line": "",
      "ev_pct": 9.9,
      "fair_prob": 0.53,
      "best_odds": "+135",
      "href": "/mlb/players/teoscar-hern\u00e1ndez-178692/props/?eid=4784028&mtid=1788&partid=77254&pid=178692&seid=80686&tmid=635",
      "kelly_pct": 2.0,
      "tier": "C",
      "confidence": "MEDIUM"
    },
    {
      "sport": "MLB",
      "game": "BOS @ MIN",
      "date_time": "MON 04/13 7:40 PM",
      "player": "Jarren Duran",
      "market": "Total Hits",
      "line": "u\u00bd",
      "ev_pct": 9.9,
      "fair_prob": 0.46,
      "best_odds": "+180",
      "href": "/mlb/players/jarren-duran-477700/props/?eid=4783063&mtid=758&partid=15144&pid=477700&seid=80686&tmid=617",
      "kelly_pct": 2.0,
      "tier": "C",
      "confidence": "MEDIUM"
    },
    {
      "sport": "NHL",
      "game": "NYR @ FLA",
      "date_time": "MON 04/13 7:00 PM",
      "player": "Vincent Trocheck",
      "market": "Player to score",
      "line": "",
      "ev_pct": 9.8,
      "fair_prob": 0.39,
      "best_odds": "+240",
      "href": "/nhl/players/vincent-trocheck-112622/props/?eid=4772366&mtid=1643&partid=77716&pid=112622&seid=70851&tmid=591",
      "kelly_pct": 1.57,
      "tier": "C",
      "confidence": "MEDIUM"
    },
    {
      "sport": "MLB",
      "game": "HOU @ SEA",
      "date_time": "MON 04/13 4:10 PM",
      "player": "Yainer Diaz",
      "market": "Player to hit a RBI",
      "line": "",
      "ev_pct": 9.8,
      "fair_prob": 0.42,
      "best_odds": "+210",
      "href": "/mlb/players/yainer-diaz-585564/props/?eid=4783290&mtid=1788&partid=574976&pid=585564&seid=80686&tmid=630",
      "kelly_pct": 1.77,
      "tier": "C",
      "confidence": "MEDIUM"
    },
    {
      "sport": "MLB",
      "game": "LAA @ NYY",
      "date_time": "MON 04/13 7:05 PM",
      "player": "Nolan Schanuel",
      "market": "Player to hit a RBI",
      "line": "",
      "ev_pct": 9.7,
      "fair_prob": 0.42,
      "best_odds": "+210",
      "href": "/mlb/players/nolan-schanuel-607846/props/?eid=4782217&mtid=1788&partid=598730&pid=607846&seid=80686&tmid=614",
      "kelly_pct": 1.76,
      "tier": "C",
      "confidence": "MEDIUM"
    },
    {
      "sport": "NHL",
      "game": "COL @ EDM",
      "date_time": "MON 04/13 9:30 PM",
      "player": "Brock Nelson",
      "market": "Player to score",
      "line": "",
      "ev_pct": 9.6,
      "fair_prob": 0.43,
      "best_odds": "+200",
      "href": "/nhl/players/brock-nelson-98832/props/?eid=4772392&mtid=1643&partid=77918&pid=98832&seid=70851&tmid=575",
      "kelly_pct": 1.81,
      "tier": "C",
      "confidence": "MEDIUM"
    },
    {
      "sport": "NHL",
      "game": "SJ @ NSH",
      "date_time": "MON 04/13 8:00 PM",
      "player": "Adam Gaudette",
      "market": "Player to score",
      "line": "",
      "ev_pct": 9.5,
      "fair_prob": 0.2,
      "best_odds": "+850",
      "href": "/nhl/players/adam-gaudette-271594/props/?eid=4772384&mtid=1643&partid=202794&pid=271594&seid=70851&tmid=571",
      "kelly_pct": 0.59,
      "tier": "C",
      "confidence": "MEDIUM"
    },
    {
      "sport": "NHL",
      "game": "WPG @ VGK",
      "date_time": "MON 04/13 10:00 PM",
      "player": "Gabriel Vilardi",
      "market": "Player to score",
      "line": "",
      "ev_pct": 9.4,
      "fair_prob": 0.33,
      "best_odds": "+320",
      "href": "/nhl/players/gabriel-vilardi-246850/props/?eid=4772398&mtid=1643&partid=152519&pid=246850&seid=70851&tmid=588",
      "kelly_pct": 1.16,
      "tier": "C",
      "confidence": "MEDIUM"
    },
    {
      "sport": "MLB",
      "game": "CLE @ STL",
      "date_time": "MON 04/13 7:45 PM",
      "player": "Victor Scott",
      "market": "Total Hits",
      "line": "u\u00bd",
      "ev_pct": 9.4,
      "fair_prob": 0.61,
      "best_odds": "-105",
      "href": "/mlb/players/victor-scott-622551/props/?eid=4782129&mtid=758&partid=15144&pid=622551&seid=80686&tmid=627",
      "kelly_pct": 2.0,
      "tier": "C",
      "confidence": "MEDIUM"
    },
    {
      "sport": "MLB",
      "game": "AZ @ BAL",
      "date_time": "MON 04/13 6:35 PM",
      "player": "Alek Thomas",
      "market": "Total Hits",
      "line": "u\u00bd",
      "ev_pct": 9.3,
      "fair_prob": 0.52,
      "best_odds": "+135",
      "href": "/mlb/players/alek-thomas-477184/props/?eid=4784106&mtid=758&partid=15144&pid=477184&seid=80686&tmid=633",
      "kelly_pct": 2.0,
      "tier": "C",
      "confidence": "MEDIUM"
    },
    {
      "sport": "MLB",
      "game": "MIA @ ATL",
      "date_time": "MON 04/13 7:15 PM",
      "player": "Heriberto Hern\u00e1ndez",
      "market": "Total Hits",
      "line": "u\u00bd",
      "ev_pct": 9.3,
      "fair_prob": 0.59,
      "best_odds": "+100",
      "href": "/mlb/players/heriberto-hern\u00e1ndez-649772/props/?eid=4783158&mtid=758&partid=15144&pid=649772&seid=80686&tmid=624",
      "kelly_pct": 2.0,
      "tier": "C",
      "confidence": "MEDIUM"
    },
    {
      "sport": "MLB",
      "game": "AZ @ BAL",
      "date_time": "MON 04/13 6:35 PM",
      "player": "Nolan Arenado",
      "market": "Total Hits",
      "line": "u\u00bd",
      "ev_pct": 9.2,
      "fair_prob": 0.47,
      "best_odds": "+165",
      "href": "/mlb/players/nolan-arenado-146725/props/?eid=4784106&mtid=758&partid=15144&pid=146725&seid=80686&tmid=633",
      "kelly_pct": 2.0,
      "tier": "C",
      "confidence": "MEDIUM"
    },
    {
      "sport": "MLB",
      "game": "LAA @ NYY",
      "date_time": "MON 04/13 7:05 PM",
      "player": "Zach Neto",
      "market": "Total Hits",
      "line": "u\u00bd",
      "ev_pct": 9.2,
      "fair_prob": 0.46,
      "best_odds": "+170",
      "href": "/mlb/players/zach-neto-600617/props/?eid=4782217&mtid=758&partid=15144&pid=600617&seid=80686&tmid=614",
      "kelly_pct": 1.96,
      "tier": "C",
      "confidence": "MEDIUM"
    },
    {
      "sport": "MLB",
      "game": "TEX @ ATH",
      "date_time": "MON 04/13 9:40 PM",
      "player": "Lawrence Butler",
      "market": "Player to hit a RBI",
      "line": "",
      "ev_pct": 9.1,
      "fair_prob": 0.41,
      "best_odds": "+210",
      "href": "/mlb/players/lawrence-butler-592714/props/?eid=4782384&mtid=1788&partid=582581&pid=592714&seid=80686&tmid=612",
      "kelly_pct": 1.58,
      "tier": "C",
      "confidence": "MEDIUM"
    },
    {
      "sport": "MLB",
      "game": "BOS @ MIN",
      "date_time": "MON 04/13 7:40 PM",
      "player": "Luke Keaschall",
      "market": "Player to hit a RBI",
      "line": "",
      "ev_pct": 9.0,
      "fair_prob": 0.37,
      "best_odds": "+260",
      "href": "/mlb/players/luke-keaschall-646694/props/?eid=4783063&mtid=1788&partid=639914&pid=646694&seid=80686&tmid=610",
      "kelly_pct": 1.32,
      "tier": "C",
      "confidence": "MEDIUM"
    },
    {
      "sport": "MLB",
      "game": "WSH @ PIT",
      "date_time": "MON 04/13 6:40 PM",
      "player": "Bryan Reynolds",
      "market": "Total Hits",
      "line": "u\u00bd",
      "ev_pct": 8.8,
      "fair_prob": 0.46,
      "best_odds": "+170",
      "href": "/mlb/players/bryan-reynolds-388179/props/?eid=4783576&mtid=758&partid=15144&pid=388179&seid=80686&tmid=628",
      "kelly_pct": 1.87,
      "tier": "C",
      "confidence": "MEDIUM"
    },
    {
      "sport": "MLB",
      "game": "WSH @ PIT",
      "date_time": "MON 04/13 6:40 PM",
      "player": "Nasim Nu\u00f1ez",
      "market": "Player to hit a RBI",
      "line": "",
      "ev_pct": 8.8,
      "fair_prob": 0.33,
      "best_odds": "+310",
      "href": "/mlb/players/nasim-nu\u00f1ez-616102/props/?eid=4783576&mtid=1788&partid=607381&pid=616102&seid=80686&tmid=623",
      "kelly_pct": 1.08,
      "tier": "C",
      "confidence": "MEDIUM"
    },
    {
      "sport": "MLB",
      "game": "HOU @ SEA",
      "date_time": "MON 04/13 4:10 PM",
      "player": "Joey Loperfido",
      "market": "Player to hit a RBI",
      "line": "",
      "ev_pct": 8.8,
      "fair_prob": 0.35,
      "best_odds": "+280",
      "href": "/mlb/players/joey-loperfido-623735/props/?eid=4783290&mtid=1788&partid=615473&pid=623735&seid=80686&tmid=630",
      "kelly_pct": 1.18,
      "tier": "C",
      "confidence": "MEDIUM"
    },
    {
      "sport": "MLB",
      "game": "MIA @ ATL",
      "date_time": "MON 04/13 7:15 PM",
      "player": "Otto Lopez",
      "market": "Total Hits",
      "line": "u\u00bd",
      "ev_pct": 8.6,
      "fair_prob": 0.46,
      "best_odds": "+170",
      "href": "/mlb/players/otto-lopez-378490/props/?eid=4783158&mtid=758&partid=15144&pid=378490&seid=80686&tmid=624",
      "kelly_pct": 1.83,
      "tier": "C",
      "confidence": "MEDIUM"
    },
    {
      "sport": "NHL",
      "game": "DET @ TB",
      "date_time": "MON 04/13 7:00 PM",
      "player": "Patrick Kane",
      "market": "Player to score",
      "line": "",
      "ev_pct": 8.5,
      "fair_prob": 0.33,
      "best_odds": "+305",
      "href": "/nhl/players/patrick-kane-6527/props/?eid=4772363&mtid=1643&partid=78211&pid=6527&seid=70851&tmid=566",
      "kelly_pct": 1.05,
      "tier": "C",
      "confidence": "MEDIUM"
    },
    {
      "sport": "MLB",
      "game": "TEX @ ATH",
      "date_time": "MON 04/13 9:40 PM",
      "player": "Luis Severino",
      "market": "Total Strikeouts",
      "line": "u4\u00bd",
      "ev_pct": 8.5,
      "fair_prob": 0.56,
      "best_odds": "+110",
      "href": "/mlb/players/luis-severino-147724/props/?eid=4782384&mtid=766&partid=15144&pid=147724&seid=80686&tmid=612",
      "kelly_pct": 2.0,
      "tier": "C",
      "confidence": "MEDIUM"
    },
    {
      "sport": "MLB",
      "game": "LAA @ NYY",
      "date_time": "MON 04/13 7:05 PM",
      "player": "Nolan Schanuel",
      "market": "Total Hits",
      "line": "u\u00bd",
      "ev_pct": 8.3,
      "fair_prob": 0.48,
      "best_odds": "+150",
      "href": "/mlb/players/nolan-schanuel-607846/props/?eid=4782217&mtid=758&partid=15144&pid=607846&seid=80686&tmid=614",
      "kelly_pct": 1.92,
      "tier": "C",
      "confidence": "MEDIUM"
    },
    {
      "sport": "MLB",
      "game": "WSH @ PIT",
      "date_time": "MON 04/13 6:40 PM",
      "player": "Jos\u00e9 Tena",
      "market": "Player to hit a RBI",
      "line": "",
      "ev_pct": 8.2,
      "fair_prob": 0.33,
      "best_odds": "+300",
      "href": "/mlb/players/jos\u00e9-tena-564290/props/?eid=4783576&mtid=1788&partid=551030&pid=564290&seid=80686&tmid=623",
      "kelly_pct": 1.01,
      "tier": "C",
      "confidence": "MEDIUM"
    },
    {
      "sport": "MLB",
      "game": "MIA @ ATL",
      "date_time": "MON 04/13 7:15 PM",
      "player": "Xavier Edwards",
      "market": "Total Hits",
      "line": "u1\u00bd",
      "ev_pct": 8.1,
      "fair_prob": 0.81,
      "best_odds": "-275",
      "href": "/mlb/players/xavier-edwards-483011/props/?eid=4783158&mtid=758&partid=15144&pid=483011&seid=80686&tmid=624",
      "kelly_pct": 2.0,
      "tier": "C",
      "confidence": "MEDIUM"
    },
    {
      "sport": "MLB",
      "game": "CHC @ PHI",
      "date_time": "MON 04/13 6:40 PM",
      "player": "Trea Turner",
      "market": "Player to hit a RBI",
      "line": "",
      "ev_pct": 8.1,
      "fair_prob": 0.42,
      "best_odds": "+195",
      "href": "/mlb/players/trea-turner-147329/props/?eid=4782392&mtid=1788&partid=77190&pid=147329&seid=80686&tmid=621",
      "kelly_pct": 1.47,
      "tier": "C",
      "confidence": "MEDIUM"
    },
    {
      "sport": "NHL",
      "game": "DET @ TB",
      "date_time": "MON 04/13 7:00 PM",
      "player": "James van Riemsdyk",
      "market": "Player to score",
      "line": "",
      "ev_pct": 7.9,
      "fair_prob": 0.21,
      "best_odds": "+675",
      "href": "/nhl/players/james-van-riemsdyk-32369/props/?eid=4772363&mtid=1643&partid=78160&pid=32369&seid=70851&tmid=566",
      "kelly_pct": 0.52,
      "tier": "C",
      "confidence": "MEDIUM"
    },
    {
      "sport": "NHL",
      "game": "CAR @ PHI",
      "date_time": "MON 04/13 7:00 PM",
      "player": "Sean Couturier",
      "market": "Player to score",
      "line": "",
      "ev_pct": 7.9,
      "fair_prob": 0.26,
      "best_odds": "+440",
      "href": "/nhl/players/sean-couturier-72581/props/?eid=4772370&mtid=1643&partid=77751&pid=72581&seid=70851&tmid=590",
      "kelly_pct": 0.69,
      "tier": "C",
      "confidence": "MEDIUM"
    },
    {
      "sport": "MLB",
      "game": "CLE @ STL",
      "date_time": "MON 04/13 7:45 PM",
      "player": "Ivan Herrera",
      "market": "Total Hits",
      "line": "u\u00bd",
      "ev_pct": 7.9,
      "fair_prob": 0.46,
      "best_odds": "+165",
      "href": "/mlb/players/ivan-herrera-477062/props/?eid=4782129&mtid=758&partid=15144&pid=477062&seid=80686&tmid=627",
      "kelly_pct": 1.68,
      "tier": "C",
      "confidence": "MEDIUM"
    },
    {
      "sport": "MLB",
      "game": "WSH @ PIT",
      "date_time": "MON 04/13 6:40 PM",
      "player": "Ryan O'Hearn",
      "market": "Total Hits",
      "line": "u\u00bd",
      "ev_pct": 7.9,
      "fair_prob": 0.46,
      "best_odds": "+165",
      "href": "/mlb/players/ryan-ohearn-319525/props/?eid=4783576&mtid=758&partid=15144&pid=319525&seid=80686&tmid=628",
      "kelly_pct": 1.68,
      "tier": "C",
      "confidence": "MEDIUM"
    },
    {
      "sport": "NHL",
      "game": "NYR @ FLA",
      "date_time": "MON 04/13 7:00 PM",
      "player": "Adam Fox",
      "market": "Player to score 2+ Goals",
      "line": "",
      "ev_pct": 7.8,
      "fair_prob": 0.1,
      "best_odds": "+4500",
      "href": "/nhl/players/adam-fox-406569/props/?eid=4772366&mtid=1648&partid=360093&pid=406569&seid=70851&tmid=591",
      "kelly_pct": 0.22,
      "tier": "C",
      "confidence": "MEDIUM"
    },
    {
      "sport": "NHL",
      "game": "WPG @ VGK",
      "date_time": "MON 04/13 10:00 PM",
      "player": "Neal Pionk",
      "market": "Player to score",
      "line": "",
      "ev_pct": 7.8,
      "fair_prob": 0.17,
      "best_odds": "+1000",
      "href": "/nhl/players/neal-pionk-247758/props/?eid=4772398&mtid=1643&partid=154547&pid=247758&seid=70851&tmid=588",
      "kelly_pct": 0.4,
      "tier": "C",
      "confidence": "MEDIUM"
    },
    {
      "sport": "MLB",
      "game": "LAA @ NYY",
      "date_time": "MON 04/13 7:05 PM",
      "player": "Jos\u00e9 Caballero",
      "market": "Total Hits",
      "line": "u\u00bd",
      "ev_pct": 7.7,
      "fair_prob": 0.55,
      "best_odds": "+110",
      "href": "/mlb/players/jos\u00e9-caballero-600616/props/?eid=4782217&mtid=758&partid=15144&pid=600616&seid=80686&tmid=618",
      "kelly_pct": 2.0,
      "tier": "C",
      "confidence": "MEDIUM"
    },
    {
      "sport": "NHL",
      "game": "CAR @ PHI",
      "date_time": "MON 04/13 7:00 PM",
      "player": "Porter Martone",
      "market": "Player to score 2+ Goals",
      "line": "",
      "ev_pct": 7.6,
      "fair_prob": 0.12,
      "best_odds": "+2300",
      "href": "/nhl/players/porter-martone-651775/props/?eid=4772370&mtid=1648&partid=645318&pid=651775&seid=70851&tmid=590",
      "kelly_pct": 0.26,
      "tier": "C",
      "confidence": "MEDIUM"
    },
    {
      "sport": "NHL",
      "game": "DET @ TB",
      "date_time": "MON 04/13 7:00 PM",
      "player": "Moritz Seider",
      "market": "Player to score 2+ Goals",
      "line": "",
      "ev_pct": 7.6,
      "fair_prob": 0.09,
      "best_odds": "+8000",
      "href": "/nhl/players/moritz-seider-426604/props/?eid=4772363&mtid=1648&partid=386771&pid=426604&seid=70851&tmid=566",
      "kelly_pct": 0.19,
      "tier": "C",
      "confidence": "MEDIUM"
    },
    {
      "sport": "MLB",
      "game": "LAA @ NYY",
      "date_time": "MON 04/13 7:05 PM",
      "player": "Oswald Peraza",
      "market": "Player to hit a RBI",
      "line": "",
      "ev_pct": 7.6,
      "fair_prob": 0.33,
      "best_odds": "+290",
      "href": "/mlb/players/oswald-peraza-504561/props/?eid=4782217&mtid=1788&partid=480702&pid=504561&seid=80686&tmid=614",
      "kelly_pct": 0.94,
      "tier": "C",
      "confidence": "MEDIUM"
    },
    {
      "sport": "NHL",
      "game": "CAR @ PHI",
      "date_time": "MON 04/13 7:00 PM",
      "player": "Sean Walker",
      "market": "Player to score",
      "line": "",
      "ev_pct": 7.5,
      "fair_prob": 0.2,
      "best_odds": "+700",
      "href": "/nhl/players/sean-walker-246861/props/?eid=4772370&mtid=1643&partid=152545&pid=246861&seid=70851&tmid=589",
      "kelly_pct": 0.47,
      "tier": "C",
      "confidence": "MEDIUM"
    },
    {
      "sport": "NHL",
      "game": "SJ @ NSH",
      "date_time": "MON 04/13 8:00 PM",
      "player": "Dmitry Orlov",
      "market": "Player to score",
      "line": "",
      "ev_pct": 7.5,
      "fair_prob": 0.19,
      "best_odds": "+800",
      "href": "/nhl/players/dmitry-orlov-122270/props/?eid=4772384&mtid=1643&partid=78140&pid=122270&seid=70851&tmid=571",
      "kelly_pct": 0.44,
      "tier": "C",
      "confidence": "MEDIUM"
    },
    {
      "sport": "MLB",
      "game": "MIA @ ATL",
      "date_time": "MON 04/13 7:15 PM",
      "player": "Graham Pauley",
      "market": "Total Hits",
      "line": "u\u00bd",
      "ev_pct": 7.5,
      "fair_prob": 0.55,
      "best_odds": "+110",
      "href": "/mlb/players/graham-pauley-621205/props/?eid=4783158&mtid=758&partid=15144&pid=621205&seid=80686&tmid=624",
      "kelly_pct": 2.0,
      "tier": "C",
      "confidence": "MEDIUM"
    },
    {
      "sport": "MLB",
      "game": "WSH @ PIT",
      "date_time": "MON 04/13 6:40 PM",
      "player": "Oneil Cruz",
      "market": "Player to hit a RBI",
      "line": "",
      "ev_pct": 7.5,
      "fair_prob": 0.45,
      "best_odds": "+170",
      "href": "/mlb/players/oneil-cruz-444764/props/?eid=4783576&mtid=1788&partid=408975&pid=444764&seid=80686&tmid=628",
      "kelly_pct": 1.53,
      "tier": "C",
      "confidence": "MEDIUM"
    },
    {
      "sport": "NHL",
      "game": "BUF @ CHI",
      "date_time": "MON 04/13 8:30 PM",
      "player": "Anton Frondell",
      "market": "Player to score",
      "line": "",
      "ev_pct": 7.3,
      "fair_prob": 0.33,
      "best_odds": "+290",
      "href": "/nhl/players/anton-frondell-651781/props/?eid=4772389&mtid=1643&partid=645324&pid=651781&seid=70851&tmid=565",
      "kelly_pct": 0.9,
      "tier": "C",
      "confidence": "MEDIUM"
    },
    {
      "sport": "NHL",
      "game": "SJ @ NSH",
      "date_time": "MON 04/13 8:00 PM",
      "player": "Alexander Wennberg",
      "market": "Player to score 2+ Goals",
      "line": "",
      "ev_pct": 7.2,
      "fair_prob": 0.1,
      "best_odds": "+3500",
      "href": "/nhl/players/alexander-wennberg-132244/props/?eid=4772384&mtid=1648&partid=78344&pid=132244&seid=70851&tmid=571",
      "kelly_pct": 0.2,
      "tier": "C",
      "confidence": "MEDIUM"
    },
    {
      "sport": "NHL",
      "game": "WPG @ VGK",
      "date_time": "MON 04/13 10:00 PM",
      "player": "Noah Hanifin",
      "market": "Player to score",
      "line": "",
      "ev_pct": 7.2,
      "fair_prob": 0.15,
      "best_odds": "+1200",
      "href": "/nhl/players/noah-hanifin-135290/props/?eid=4772398&mtid=1643&partid=77967&pid=135290&seid=70851&tmid=76787",
      "kelly_pct": 0.32,
      "tier": "C",
      "confidence": "MEDIUM"
    },
    {
      "sport": "MLB",
      "game": "MIA @ ATL",
      "date_time": "MON 04/13 7:15 PM",
      "player": "Heriberto Hern\u00e1ndez",
      "market": "Player to hit a RBI",
      "line": "",
      "ev_pct": 7.2,
      "fair_prob": 0.37,
      "best_odds": "+240",
      "href": "/mlb/players/heriberto-hern\u00e1ndez-649772/props/?eid=4783158&mtid=1788&partid=643141&pid=649772&seid=80686&tmid=624",
      "kelly_pct": 1.06,
      "tier": "C",
      "confidence": "MEDIUM"
    },
    {
      "sport": "MLB",
      "game": "HOU @ SEA",
      "date_time": "MON 04/13 4:10 PM",
      "player": "Yordan Alvarez",
      "market": "Total Hits",
      "line": "u\u00bd",
      "ev_pct": 7.2,
      "fair_prob": 0.46,
      "best_odds": "+160",
      "href": "/mlb/players/yordan-alvarez-401945/props/?eid=4783290&mtid=758&partid=15144&pid=401945&seid=80686&tmid=630",
      "kelly_pct": 1.53,
      "tier": "C",
      "confidence": "MEDIUM"
    },
    {
      "sport": "MLB",
      "game": "BOS @ MIN",
      "date_time": "MON 04/13 7:40 PM",
      "player": "Roman Anthony",
      "market": "Total Hits",
      "line": "u\u00bd",
      "ev_pct": 7.2,
      "fair_prob": 0.46,
      "best_odds": "+160",
      "href": "/mlb/players/roman-anthony-650455/props/?eid=4783063&mtid=758&partid=15144&pid=650455&seid=80686&tmid=617",
      "kelly_pct": 1.53,
      "tier": "C",
      "confidence": "MEDIUM"
    },
    {
      "sport": "MLB",
      "game": "AZ @ BAL",
      "date_time": "MON 04/13 6:35 PM",
      "player": "Ketel Marte",
      "market": "Player to hit a RBI",
      "line": "",
      "ev_pct": 7.2,
      "fair_prob": 0.45,
      "best_odds": "+165",
      "href": "/mlb/players/ketel-marte-147412/props/?eid=4784106&mtid=1788&partid=76589&pid=147412&seid=80686&tmid=633",
      "kelly_pct": 1.47,
      "tier": "C",
      "confidence": "MEDIUM"
    },
    {
      "sport": "MLB",
      "game": "CLE @ STL",
      "date_time": "MON 04/13 7:45 PM",
      "player": "Angel Mart\u00ednez",
      "market": "Total Hits",
      "line": "u\u00bd",
      "ev_pct": 7.1,
      "fair_prob": 0.42,
      "best_odds": "+190",
      "href": "/mlb/players/angel-mart\u00ednez-592952/props/?eid=4782129&mtid=758&partid=15144&pid=592952&seid=80686&tmid=607",
      "kelly_pct": 1.29,
      "tier": "C",
      "confidence": "MEDIUM"
    },
    {
      "sport": "NHL",
      "game": "WPG @ VGK",
      "date_time": "MON 04/13 10:00 PM",
      "player": "Mark Stone",
      "market": "Player to score",
      "line": "",
      "ev_pct": 7.0,
      "fair_prob": 0.42,
      "best_odds": "+190",
      "href": "/nhl/players/mark-stone-72517/props/?eid=4772398&mtid=1643&partid=78413&pid=72517&seid=70851&tmid=76787",
      "kelly_pct": 1.27,
      "tier": "C",
      "confidence": "MEDIUM"
    },
    {
      "sport": "MLB",
      "game": "NYM @ LAD",
      "date_time": "MON 04/13 10:10 PM",
      "player": "Shohei Ohtani",
      "market": "Player to hit a RBI",
      "line": "",
      "ev_pct": 7.0,
      "fair_prob": 0.53,
      "best_odds": "+120",
      "href": "/mlb/players/shohei-ohtani-262535/props/?eid=4784028&mtid=1788&partid=189683&pid=262535&seid=80686&tmid=635",
      "kelly_pct": 1.97,
      "tier": "C",
      "confidence": "MEDIUM"
    },
    {
      "sport": "NHL",
      "game": "BUF @ CHI",
      "date_time": "MON 04/13 8:30 PM",
      "player": "Josh Norris",
      "market": "Player to score",
      "line": "",
      "ev_pct": 6.9,
      "fair_prob": 0.33,
      "best_odds": "+280",
      "href": "/nhl/players/josh-norris-457937/props/?eid=4772389&mtid=1643&partid=430003&pid=457937&seid=70851&tmid=583",
      "kelly_pct": 0.85,
      "tier": "C",
      "confidence": "MEDIUM"
    },
    {
      "sport": "MLB",
      "game": "CLE @ STL",
      "date_time": "MON 04/13 7:45 PM",
      "player": "Brayan Rocchio",
      "market": "Total Hits",
      "line": "u\u00bd",
      "ev_pct": 6.9,
      "fair_prob": 0.49,
      "best_odds": "+135",
      "href": "/mlb/players/brayan-rocchio-564284/props/?eid=4782129&mtid=758&partid=15144&pid=564284&seid=80686&tmid=607",
      "kelly_pct": 1.66,
      "tier": "C",
      "confidence": "MEDIUM"
    },
    {
      "sport": "MLB",
      "game": "WSH @ PIT",
      "date_time": "MON 04/13 6:40 PM",
      "player": "Keibert Ruiz",
      "market": "Player to hit a RBI",
      "line": "",
      "ev_pct": 6.8,
      "fair_prob": 0.36,
      "best_odds": "+240",
      "href": "/mlb/players/keibert-ruiz-355516/props/?eid=4783576&mtid=1788&partid=300527&pid=355516&seid=80686&tmid=623",
      "kelly_pct": 0.96,
      "tier": "C",
      "confidence": "MEDIUM"
    },
    {
      "sport": "MLB",
      "game": "NYM @ LAD",
      "date_time": "MON 04/13 10:10 PM",
      "player": "Shohei Ohtani",
      "market": "Total Hits",
      "line": "u\u00bd",
      "ev_pct": 6.8,
      "fair_prob": 0.4,
      "best_odds": "+200",
      "href": "/mlb/players/shohei-ohtani-262535/props/?eid=4784028&mtid=758&partid=15144&pid=262535&seid=80686&tmid=635",
      "kelly_pct": 1.13,
      "tier": "C",
      "confidence": "MEDIUM"
    },
    {
      "sport": "NHL",
      "game": "CAR @ PHI",
      "date_time": "MON 04/13 7:00 PM",
      "player": "Cam York",
      "market": "Player to score",
      "line": "",
      "ev_pct": 6.5,
      "fair_prob": 0.16,
      "best_odds": "+1000",
      "href": "/nhl/players/cam-york-528208/props/?eid=4772370&mtid=1643&partid=507575&pid=528208&seid=70851&tmid=590",
      "kelly_pct": 0.31,
      "tier": "C",
      "confidence": "MEDIUM"
    },
    {
      "sport": "NHL",
      "game": "BUF @ CHI",
      "date_time": "MON 04/13 8:30 PM",
      "player": "Louis Crevier",
      "market": "Player to score",
      "line": "",
      "ev_pct": 6.5,
      "fair_prob": 0.16,
      "best_odds": "+1000",
      "href": "/nhl/players/louis-crevier-495939/props/?eid=4772389&mtid=1643&partid=471298&pid=495939&seid=70851&tmid=565",
      "kelly_pct": 0.31,
      "tier": "C",
      "confidence": "MEDIUM"
    },
    {
      "sport": "NHL",
      "game": "DET @ TB",
      "date_time": "MON 04/13 7:00 PM",
      "player": "Lucas Raymond",
      "market": "Player to score",
      "line": "",
      "ev_pct": 6.5,
      "fair_prob": 0.33,
      "best_odds": "+280",
      "href": "/nhl/players/lucas-raymond-495029/props/?eid=4772363&mtid=1643&partid=470372&pid=495029&seid=70851&tmid=566",
      "kelly_pct": 0.8,
      "tier": "C",
      "confidence": "MEDIUM"
    },
    {
      "sport": "MLB",
      "game": "MIA @ ATL",
      "date_time": "MON 04/13 7:15 PM",
      "player": "Austin Riley",
      "market": "Total Hits",
      "line": "u\u00bd",
      "ev_pct": 6.5,
      "fair_prob": 0.48,
      "best_odds": "+140",
      "href": "/mlb/players/austin-riley-395010/props/?eid=4783158&mtid=758&partid=15144&pid=395010&seid=80686&tmid=625",
      "kelly_pct": 1.5,
      "tier": "C",
      "confidence": "MEDIUM"
    },
    {
      "sport": "MLB",
      "game": "TEX @ ATH",
      "date_time": "MON 04/13 9:40 PM",
      "player": "Brandon Nimmo",
      "market": "Total Bases",
      "line": "u1\u00bd",
      "ev_pct": 6.5,
      "fair_prob": 0.63,
      "best_odds": "-130",
      "href": "/mlb/players/brandon-nimmo-147144/props/?eid=4782384&mtid=596&partid=15144&pid=147144&seid=80686&tmid=613",
      "kelly_pct": 2.0,
      "tier": "C",
      "confidence": "MEDIUM"
    },
    {
      "sport": "MLB",
      "game": "CHC @ PHI",
      "date_time": "MON 04/13 6:40 PM",
      "player": "Nico Hoerner",
      "market": "Player to hit a RBI",
      "line": "",
      "ev_pct": 6.5,
      "fair_prob": 0.36,
      "best_odds": "+240",
      "href": "/mlb/players/nico-hoerner-425118/props/?eid=4782392&mtid=1788&partid=382547&pid=425118&seid=80686&tmid=626",
      "kelly_pct": 0.91,
      "tier": "C",
      "confidence": "MEDIUM"
    },
    {
      "sport": "NHL",
      "game": "DET @ TB",
      "date_time": "MON 04/13 7:00 PM",
      "player": "Andrew Copp",
      "market": "Player to score",
      "line": "",
      "ev_pct": 6.4,
      "fair_prob": 0.25,
      "best_odds": "+450",
      "href": "/nhl/players/andrew-copp-134321/props/?eid=4772363&mtid=1643&partid=77940&pid=134321&seid=70851&tmid=566",
      "kelly_pct": 0.53,
      "tier": "C",
      "confidence": "MEDIUM"
    },
    {
      "sport": "NHL",
      "game": "SJ @ NSH",
      "date_time": "MON 04/13 8:00 PM",
      "player": "Ryan O'Reilly",
      "market": "Player to score 2+ Goals",
      "line": "",
      "ev_pct": 6.4,
      "fair_prob": 0.12,
      "best_odds": "+1600",
      "href": "/nhl/players/ryan-oreilly-32616/props/?eid=4772384&mtid=1648&partid=78071&pid=32616&seid=70851&tmid=569",
      "kelly_pct": 0.22,
      "tier": "C",
      "confidence": "MEDIUM"
    },
    {
      "sport": "NHL",
      "game": "CAR @ PHI",
      "date_time": "MON 04/13 7:00 PM",
      "player": "Trevor Zegras",
      "market": "Player to score 2+ Goals",
      "line": "",
      "ev_pct": 6.4,
      "fair_prob": 0.1,
      "best_odds": "+2400",
      "href": "/nhl/players/trevor-zegras-508903/props/?eid=4772370&mtid=1648&partid=485535&pid=508903&seid=70851&tmid=590",
      "kelly_pct": 0.18,
      "tier": "C",
      "confidence": "MEDIUM"
    },
    {
      "sport": "NHL",
      "game": "LA @ SEA",
      "date_time": "MON 04/13 9:30 PM",
      "player": "Brandon Montour",
      "market": "Player to score",
      "line": "",
      "ev_pct": 6.4,
      "fair_prob": 0.22,
      "best_odds": "+525",
      "href": "/nhl/players/brandon-montour-191856/props/?eid=4772396&mtid=1643&partid=77750&pid=191856&seid=70851&tmid=92570",
      "kelly_pct": 0.45,
      "tier": "C",
      "confidence": "MEDIUM"
    },
    {
      "sport": "NHL",
      "game": "CAR @ PHI",
      "date_time": "MON 04/13 7:00 PM",
      "player": "Nikolaj Ehlers",
      "market": "Player to score",
      "line": "",
      "ev_pct": 6.3,
      "fair_prob": 0.35,
      "best_odds": "+255",
      "href": "/nhl/players/nikolaj-ehlers-132289/props/?eid=4772370&mtid=1643&partid=77951&pid=132289&seid=70851&tmid=589",
      "kelly_pct": 0.85,
      "tier": "C",
      "confidence": "MEDIUM"
    },
    {
      "sport": "MLB",
      "game": "AZ @ BAL",
      "date_time": "MON 04/13 6:35 PM",
      "player": "Dylan Beavers",
      "market": "Total Hits",
      "line": "u\u00bd",
      "ev_pct": 6.3,
      "fair_prob": 0.52,
      "best_odds": "+120",
      "href": "/mlb/players/dylan-beavers-658028/props/?eid=4784106&mtid=758&partid=15144&pid=658028&seid=80686&tmid=616",
      "kelly_pct": 1.71,
      "tier": "C",
      "confidence": "MEDIUM"
    },
    {
      "sport": "NHL",
      "game": "WPG @ VGK",
      "date_time": "MON 04/13 10:00 PM",
      "player": "Brayden McNabb",
      "market": "Player to score",
      "line": "",
      "ev_pct": 6.2,
      "fair_prob": 0.14,
      "best_odds": "+1200",
      "href": "/nhl/players/brayden-mcnabb-72472/props/?eid=4772398&mtid=1643&partid=78557&pid=72472&seid=70851&tmid=76787",
      "kelly_pct": 0.25,
      "tier": "C",
      "confidence": "MEDIUM"
    },
    {
      "sport": "MLB",
      "game": "NYM @ LAD",
      "date_time": "MON 04/13 10:10 PM",
      "player": "Carson Benge",
      "market": "Player to hit a RBI",
      "line": "",
      "ev_pct": 6.2,
      "fair_prob": 0.33,
      "best_odds": "+270",
      "href": "/mlb/players/carson-benge-676281/props/?eid=4784028&mtid=1788&partid=671170&pid=676281&seid=80686&tmid=622",
      "kelly_pct": 0.76,
      "tier": "C",
      "confidence": "MEDIUM"
    },
    {
      "sport": "NHL",
      "game": "LA @ SEA",
      "date_time": "MON 04/13 9:30 PM",
      "player": "Chandler Stephenson",
      "market": "Player to score 2+ Goals",
      "line": "",
      "ev_pct": 6.1,
      "fair_prob": 0.08,
      "best_odds": "+4500",
      "href": "/nhl/players/chandler-stephenson-192264/props/?eid=4772396&mtid=1648&partid=99930&pid=192264&seid=70851&tmid=92570",
      "kelly_pct": 0.13,
      "tier": "C",
      "confidence": "MEDIUM"
    },
    {
      "sport": "NHL",
      "game": "WPG @ VGK",
      "date_time": "MON 04/13 10:00 PM",
      "player": "Mark Scheifele",
      "market": "Player to score 2+ Goals",
      "line": "",
      "ev_pct": 6.0,
      "fair_prob": 0.12,
      "best_odds": "+1600",
      "href": "/nhl/players/mark-scheifele-72674/props/?eid=4772398&mtid=1648&partid=77765&pid=72674&seid=70851&tmid=588",
      "kelly_pct": 0.2,
      "tier": "C",
      "confidence": "MEDIUM"
    },
    {
      "sport": "NHL",
      "game": "COL @ EDM",
      "date_time": "MON 04/13 9:30 PM",
      "player": "Jack Drury",
      "market": "Player to score",
      "line": "",
      "ev_pct": 6.0,
      "fair_prob": 0.15,
      "best_odds": "+1000",
      "href": "/nhl/players/jack-drury-280971/props/?eid=4772392&mtid=1643&partid=216768&pid=280971&seid=70851&tmid=575",
      "kelly_pct": 0.26,
      "tier": "C",
      "confidence": "MEDIUM"
    },
    {
      "sport": "NHL",
      "game": "DET @ TB",
      "date_time": "MON 04/13 7:00 PM",
      "player": "Dylan Larkin",
      "market": "Player to score 2+ Goals",
      "line": "",
      "ev_pct": 6.0,
      "fair_prob": 0.14,
      "best_odds": "+1200",
      "href": "/nhl/players/dylan-larkin-136108/props/?eid=4772363&mtid=1648&partid=78294&pid=136108&seid=70851&tmid=566",
      "kelly_pct": 0.24,
      "tier": "C",
      "confidence": "MEDIUM"
    },
    {
      "sport": "MLB",
      "game": "CHC @ PHI",
      "date_time": "MON 04/13 6:40 PM",
      "player": "Alex Bregman",
      "market": "Total Hits",
      "line": "u\u00bd",
      "ev_pct": 5.9,
      "fair_prob": 0.44,
      "best_odds": "+160",
      "href": "/mlb/players/alex-bregman-172785/props/?eid=4782392&mtid=758&partid=15144&pid=172785&seid=80686&tmid=626",
      "kelly_pct": 1.16,
      "tier": "C",
      "confidence": "MEDIUM"
    },
    {
      "sport": "NHL",
      "game": "CAR @ PHI",
      "date_time": "MON 04/13 7:00 PM",
      "player": "Rasmus Ristolainen",
      "market": "Player to score",
      "line": "",
      "ev_pct": 5.8,
      "fair_prob": 0.16,
      "best_odds": "+850",
      "href": "/nhl/players/rasmus-ristolainen-112728/props/?eid=4772370&mtid=1643&partid=78030&pid=112728&seid=70851&tmid=590",
      "kelly_pct": 0.28,
      "tier": "C",
      "confidence": "MEDIUM"
    },
    {
      "sport": "MLB",
      "game": "BOS @ MIN",
      "date_time": "MON 04/13 7:40 PM",
      "player": "Byron Buxton",
      "market": "Player to hit a RBI",
      "line": "",
      "ev_pct": 5.8,
      "fair_prob": 0.37,
      "best_odds": "+220",
      "href": "/mlb/players/byron-buxton-147426/props/?eid=4783063&mtid=1788&partid=78688&pid=147426&seid=80686&tmid=610",
      "kelly_pct": 0.85,
      "tier": "C",
      "confidence": "MEDIUM"
    },
    {
      "sport": "NHL",
      "game": "BUF @ CHI",
      "date_time": "MON 04/13 8:30 PM",
      "player": "Alex Vlasic",
      "market": "Player to score",
      "line": "",
      "ev_pct": 5.7,
      "fair_prob": 0.13,
      "best_odds": "+1200",
      "href": "/nhl/players/alex-vlasic-571996/props/?eid=4772389&mtid=1643&partid=560554&pid=571996&seid=70851&tmid=565",
      "kelly_pct": 0.21,
      "tier": "C",
      "confidence": "MEDIUM"
    },
    {
      "sport": "NHL",
      "game": "LA @ SEA",
      "date_time": "MON 04/13 9:30 PM",
      "player": "Ryker Evans",
      "market": "Player to score",
      "line": "",
      "ev_pct": 5.6,
      "fair_prob": 0.13,
      "best_odds": "+1200",
      "href": "/nhl/players/ryker-evans-543621/props/?eid=4772396&mtid=1643&partid=525699&pid=543621&seid=70851&tmid=92570",
      "kelly_pct": 0.21,
      "tier": "C",
      "confidence": "MEDIUM"
    },
    {
      "sport": "NHL",
      "game": "CAR @ PHI",
      "date_time": "MON 04/13 7:00 PM",
      "player": "Tyson Foerster",
      "market": "Player to score 2+ Goals",
      "line": "",
      "ev_pct": 5.6,
      "fair_prob": 0.11,
      "best_odds": "+1900",
      "href": "/nhl/players/tyson-foerster-495315/props/?eid=4772370&mtid=1648&partid=470658&pid=495315&seid=70851&tmid=590",
      "kelly_pct": 0.17,
      "tier": "C",
      "confidence": "MEDIUM"
    },
    {
      "sport": "NHL",
      "game": "COL @ EDM",
      "date_time": "MON 04/13 9:30 PM",
      "player": "Jake Walman",
      "market": "Player to score",
      "line": "",
      "ev_pct": 5.6,
      "fair_prob": 0.17,
      "best_odds": "+800",
      "href": "/nhl/players/jake-walman-245903/props/?eid=4772392&mtid=1643&partid=149741&pid=245903&seid=70851&tmid=579",
      "kelly_pct": 0.29,
      "tier": "C",
      "confidence": "MEDIUM"
    },
    {
      "sport": "MLB",
      "game": "CLE @ STL",
      "date_time": "MON 04/13 7:45 PM",
      "player": "Juan Brito",
      "market": "Total Hits",
      "line": "u\u00bd",
      "ev_pct": 5.6,
      "fair_prob": 0.46,
      "best_odds": "+150",
      "href": "/mlb/players/juan-brito-599914/props/?eid=4782129&mtid=758&partid=15144&pid=599914&seid=80686&tmid=607",
      "kelly_pct": 1.19,
      "tier": "C",
      "confidence": "MEDIUM"
    },
    {
      "sport": "MLB",
      "game": "CLE @ STL",
      "date_time": "MON 04/13 7:45 PM",
      "player": "JJ Wetherholt",
      "market": "Total Hits",
      "line": "u\u00bd",
      "ev_pct": 5.6,
      "fair_prob": 0.46,
      "best_odds": "+150",
      "href": "/mlb/players/jj-wetherholt-676279/props/?eid=4782129&mtid=758&partid=15144&pid=676279&seid=80686&tmid=627",
      "kelly_pct": 1.19,
      "tier": "C",
      "confidence": "MEDIUM"
    },
    {
      "sport": "MLB",
      "game": "MIA @ ATL",
      "date_time": "MON 04/13 7:15 PM",
      "player": "Liam Hicks",
      "market": "Total Hits",
      "line": "u\u00bd",
      "ev_pct": 5.6,
      "fair_prob": 0.46,
      "best_odds": "+150",
      "href": "/mlb/players/liam-hicks-643272/props/?eid=4783158&mtid=758&partid=15144&pid=643272&seid=80686&tmid=624",
      "kelly_pct": 1.19,
      "tier": "C",
      "confidence": "MEDIUM"
    },
    {
      "sport": "MLB",
      "game": "WSH @ PIT",
      "date_time": "MON 04/13 6:40 PM",
      "player": "Luis Garc\u00eda",
      "market": "Total Hits",
      "line": "u\u00bd",
      "ev_pct": 5.6,
      "fair_prob": 0.46,
      "best_odds": "+150",
      "href": "/mlb/players/luis-garc\u00eda-476971/props/?eid=4783576&mtid=758&partid=15144&pid=476971&seid=80686&tmid=623",
      "kelly_pct": 1.19,
      "tier": "C",
      "confidence": "MEDIUM"
    },
    {
      "sport": "NHL",
      "game": "NYR @ FLA",
      "date_time": "MON 04/13 7:00 PM",
      "player": "J.T. Miller",
      "market": "Player to score 2+ Goals",
      "line": "",
      "ev_pct": 5.4,
      "fair_prob": 0.1,
      "best_odds": "+1900",
      "href": "/nhl/players/jt-miller-82910/props/?eid=4772366&mtid=1648&partid=78059&pid=82910&seid=70851&tmid=591",
      "kelly_pct": 0.15,
      "tier": "C",
      "confidence": "MEDIUM"
    },
    {
      "sport": "NHL",
      "game": "SJ @ NSH",
      "date_time": "MON 04/13 8:00 PM",
      "player": "Nick Leddy",
      "market": "Player to score first goal",
      "line": "",
      "ev_pct": 5.4,
      "fair_prob": 0.07,
      "best_odds": "+7000",
      "href": "/nhl/players/nick-leddy-32959/props/?eid=4772384&mtid=1641&partid=77723&pid=32959&seid=70851&tmid=571",
      "kelly_pct": 0.1,
      "tier": "C",
      "confidence": "MEDIUM"
    },
    {
      "sport": "NHL",
      "game": "NYR @ FLA",
      "date_time": "MON 04/13 7:00 PM",
      "player": "Tobias Bjornfot",
      "market": "Player to score",
      "line": "",
      "ev_pct": 5.4,
      "fair_prob": 0.13,
      "best_odds": "+1300",
      "href": "/nhl/players/tobias-bjornfot-426607/props/?eid=4772366&mtid=1643&partid=386774&pid=426607&seid=70851&tmid=586",
      "kelly_pct": 0.2,
      "tier": "C",
      "confidence": "MEDIUM"
    },
    {
      "sport": "NHL",
      "game": "WPG @ VGK",
      "date_time": "MON 04/13 10:00 PM",
      "player": "Dylan Samberg",
      "market": "Player to score first goal",
      "line": "",
      "ev_pct": 5.3,
      "fair_prob": 0.07,
      "best_odds": "+7000",
      "href": "/nhl/players/dylan-samberg-510088/props/?eid=4772398&mtid=1641&partid=486845&pid=510088&seid=70851&tmid=588",
      "kelly_pct": 0.1,
      "tier": "C",
      "confidence": "MEDIUM"
    },
    {
      "sport": "NHL",
      "game": "LA @ SEA",
      "date_time": "MON 04/13 9:30 PM",
      "player": "Brian Dumoulin",
      "market": "Player to score first goal",
      "line": "",
      "ev_pct": 5.3,
      "fair_prob": 0.07,
      "best_odds": "+7500",
      "href": "/nhl/players/brian-dumoulin-112826/props/?eid=4772396&mtid=1641&partid=78326&pid=112826&seid=70851&tmid=573",
      "kelly_pct": 0.1,
      "tier": "C",
      "confidence": "MEDIUM"
    },
    {
      "sport": "NHL",
      "game": "CAR @ PHI",
      "date_time": "MON 04/13 7:00 PM",
      "player": "Alexander Nikishin",
      "market": "Player to score",
      "line": "",
      "ev_pct": 5.3,
      "fair_prob": 0.17,
      "best_odds": "+725",
      "href": "/nhl/players/alexander-nikishin-495333/props/?eid=4772370&mtid=1643&partid=470676&pid=495333&seid=70851&tmid=589",
      "kelly_pct": 0.27,
      "tier": "C",
      "confidence": "MEDIUM"
    },
    {
      "sport": "NHL",
      "game": "BUF @ CHI",
      "date_time": "MON 04/13 8:30 PM",
      "player": "Connor Bedard",
      "market": "Player to score",
      "line": "",
      "ev_pct": 5.3,
      "fair_prob": 0.42,
      "best_odds": "+170",
      "href": "/nhl/players/connor-bedard-604222/props/?eid=4772389&mtid=1643&partid=594864&pid=604222&seid=70851&tmid=565",
      "kelly_pct": 0.96,
      "tier": "C",
      "confidence": "MEDIUM"
    },
    {
      "sport": "NHL",
      "game": "SJ @ NSH",
      "date_time": "MON 04/13 8:00 PM",
      "player": "Mario Ferraro",
      "market": "Player to score first goal",
      "line": "",
      "ev_pct": 5.3,
      "fair_prob": 0.07,
      "best_odds": "+6000",
      "href": "/nhl/players/mario-ferraro-426236/props/?eid=4772384&mtid=1641&partid=386134&pid=426236&seid=70851&tmid=571",
      "kelly_pct": 0.1,
      "tier": "C",
      "confidence": "MEDIUM"
    },
    {
      "sport": "MLB",
      "game": "TEX @ ATH",
      "date_time": "MON 04/13 9:40 PM",
      "player": "Lawrence Butler",
      "market": "Total Hits",
      "line": "u\u00bd",
      "ev_pct": 5.3,
      "fair_prob": 0.45,
      "best_odds": "+150",
      "href": "/mlb/players/lawrence-butler-592714/props/?eid=4782384&mtid=758&partid=15144&pid=592714&seid=80686&tmid=612",
      "kelly_pct": 1.08,
      "tier": "C",
      "confidence": "MEDIUM"
    },
    {
      "sport": "MLB",
      "game": "TEX @ ATH",
      "date_time": "MON 04/13 9:40 PM",
      "player": "Nick Kurtz",
      "market": "Total Hits",
      "line": "u\u00bd",
      "ev_pct": 5.3,
      "fair_prob": 0.48,
      "best_odds": "+135",
      "href": "/mlb/players/nick-kurtz-646970/props/?eid=4782384&mtid=758&partid=15144&pid=646970&seid=80686&tmid=612",
      "kelly_pct": 1.22,
      "tier": "C",
      "confidence": "MEDIUM"
    },
    {
      "sport": "NHL",
      "game": "LA @ SEA",
      "date_time": "MON 04/13 9:30 PM",
      "player": "Kaapo Kakko",
      "market": "Player to score",
      "line": "",
      "ev_pct": 5.2,
      "fair_prob": 0.24,
      "best_odds": "+430",
      "href": "/nhl/players/kaapo-kakko-406567/props/?eid=4772396&mtid=1643&partid=360091&pid=406567&seid=70851&tmid=92570",
      "kelly_pct": 0.41,
      "tier": "C",
      "confidence": "MEDIUM"
    },
    {
      "sport": "NHL",
      "game": "COL @ EDM",
      "date_time": "MON 04/13 9:30 PM",
      "player": "Gabriel Landeskog",
      "market": "Player to score 2+ Goals",
      "line": "",
      "ev_pct": 5.2,
      "fair_prob": 0.09,
      "best_odds": "+2400",
      "href": "/nhl/players/gabriel-landeskog-72505/props/?eid=4772392&mtid=1648&partid=77647&pid=72505&seid=70851&tmid=575",
      "kelly_pct": 0.13,
      "tier": "C",
      "confidence": "MEDIUM"
    },
    {
      "sport": "NHL",
      "game": "LA @ SEA",
      "date_time": "MON 04/13 9:30 PM",
      "player": "Jaden Schwartz",
      "market": "Player to score",
      "line": "",
      "ev_pct": 5.2,
      "fair_prob": 0.27,
      "best_odds": "+365",
      "href": "/nhl/players/jaden-schwartz-81791/props/?eid=4772396&mtid=1643&partid=78222&pid=81791&seid=70851&tmid=92570",
      "kelly_pct": 0.48,
      "tier": "C",
      "confidence": "MEDIUM"
    },
    {
      "sport": "NHL",
      "game": "DET @ TB",
      "date_time": "MON 04/13 7:00 PM",
      "player": "Justin Faulk",
      "market": "Player to score",
      "line": "",
      "ev_pct": 5.2,
      "fair_prob": 0.16,
      "best_odds": "+800",
      "href": "/nhl/players/justin-faulk-72584/props/?eid=4772363&mtid=1643&partid=78082&pid=72584&seid=70851&tmid=566",
      "kelly_pct": 0.25,
      "tier": "C",
      "confidence": "MEDIUM"
    },
    {
      "sport": "NHL",
      "game": "NYR @ FLA",
      "date_time": "MON 04/13 7:00 PM",
      "player": "Urho Vaakanainen",
      "market": "Player to score first goal",
      "line": "",
      "ev_pct": 5.2,
      "fair_prob": 0.07,
      "best_odds": "+7500",
      "href": "/nhl/players/urho-vaakanainen-336773/props/?eid=4772366&mtid=1641&partid=277915&pid=336773&seid=70851&tmid=591",
      "kelly_pct": 0.1,
      "tier": "C",
      "confidence": "MEDIUM"
    },
    {
      "sport": "NHL",
      "game": "LA @ SEA",
      "date_time": "MON 04/13 9:30 PM",
      "player": "Cody Ceci",
      "market": "Player to score first goal",
      "line": "",
      "ev_pct": 5.2,
      "fair_prob": 0.06,
      "best_odds": "+8000",
      "href": "/nhl/players/cody-ceci-103584/props/?eid=4772396&mtid=1641&partid=78020&pid=103584&seid=70851&tmid=573",
      "kelly_pct": 0.08,
      "tier": "C",
      "confidence": "MEDIUM"
    },
    {
      "sport": "NHL",
      "game": "BUF @ CHI",
      "date_time": "MON 04/13 8:30 PM",
      "player": "Teuvo Teravainen",
      "market": "Player to score 2+ Goals",
      "line": "",
      "ev_pct": 5.2,
      "fair_prob": 0.08,
      "best_odds": "+4000",
      "href": "/nhl/players/teuvo-teravainen-112674/props/?eid=4772389&mtid=1648&partid=78181&pid=112674&seid=70851&tmid=565",
      "kelly_pct": 0.11,
      "tier": "C",
      "confidence": "MEDIUM"
    },
    {
      "sport": "NHL",
      "game": "SJ @ NSH",
      "date_time": "MON 04/13 8:00 PM",
      "player": "Vincent Desharnais",
      "market": "Player to score first goal",
      "line": "",
      "ev_pct": 5.1,
      "fair_prob": 0.06,
      "best_odds": "+8000",
      "href": "/nhl/players/vincent-desharnais-426776/props/?eid=4772384&mtid=1641&partid=387036&pid=426776&seid=70851&tmid=571",
      "kelly_pct": 0.08,
      "tier": "C",
      "confidence": "MEDIUM"
    },
    {
      "sport": "MLB",
      "game": "CHC @ PHI",
      "date_time": "MON 04/13 6:40 PM",
      "player": "Pete Crow-Armstrong",
      "market": "Total Hits",
      "line": "u\u00bd",
      "ev_pct": 5.1,
      "fair_prob": 0.54,
      "best_odds": "+105",
      "href": "/mlb/players/pete-crow-armstrong-610950/props/?eid=4782392&mtid=758&partid=15144&pid=610950&seid=80686&tmid=626",
      "kelly_pct": 1.5,
      "tier": "C",
      "confidence": "MEDIUM"
    },
    {
      "sport": "MLB",
      "game": "MIA @ ATL",
      "date_time": "MON 04/13 7:15 PM",
      "player": "Jakob Marsee",
      "market": "Total Hits",
      "line": "u\u00bd",
      "ev_pct": 5.1,
      "fair_prob": 0.42,
      "best_odds": "+170",
      "href": "/mlb/players/jakob-marsee-655204/props/?eid=4783158&mtid=758&partid=15144&pid=655204&seid=80686&tmid=624",
      "kelly_pct": 0.92,
      "tier": "C",
      "confidence": "MEDIUM"
    },
    {
      "sport": "NHL",
      "game": "BUF @ CHI",
      "date_time": "MON 04/13 8:30 PM",
      "player": "Kevin Korchinski",
      "market": "Player to score first goal",
      "line": "",
      "ev_pct": 5.0,
      "fair_prob": 0.06,
      "best_odds": "+8500",
      "href": "/nhl/players/kevin-korchinski-577658/props/?eid=4772389&mtid=1641&partid=566689&pid=577658&seid=70851&tmid=565",
      "kelly_pct": 0.08,
      "tier": "C",
      "confidence": "MEDIUM"
    },
    {
      "sport": "NHL",
      "game": "BUF @ CHI",
      "date_time": "MON 04/13 8:30 PM",
      "player": "Kevin Korchinski",
      "market": "Player to score",
      "line": "",
      "ev_pct": 5.0,
      "fair_prob": 0.09,
      "best_odds": "+2200",
      "href": "/nhl/players/kevin-korchinski-577658/props/?eid=4772389&mtid=1643&partid=566689&pid=577658&seid=70851&tmid=565",
      "kelly_pct": 0.12,
      "tier": "C",
      "confidence": "MEDIUM"
    },
    {
      "sport": "MLB",
      "game": "MIA @ ATL",
      "date_time": "MON 04/13 7:15 PM",
      "player": "Jakob Marsee",
      "market": "Total Bases",
      "line": "u1\u00bd",
      "ev_pct": 5.0,
      "fair_prob": 0.68,
      "best_odds": "-170",
      "href": "/mlb/players/jakob-marsee-655204/props/?eid=4783158&mtid=596&partid=15144&pid=655204&seid=80686&tmid=624",
      "kelly_pct": 2.0,
      "tier": "C",
      "confidence": "MEDIUM"
    },
    {
      "sport": "MLB",
      "game": "TEX @ ATH",
      "date_time": "MON 04/13 9:40 PM",
      "player": "Jacob Wilson",
      "market": "Total Bases",
      "line": "u1\u00bd",
      "ev_pct": 5.0,
      "fair_prob": 0.68,
      "best_odds": "-170",
      "href": "/mlb/players/jacob-wilson-539574/props/?eid=4782384&mtid=596&partid=15144&pid=539574&seid=80686&tmid=612",
      "kelly_pct": 2.0,
      "tier": "C",
      "confidence": "MEDIUM"
    }
  ]
}