{"meta": {"version": 1, "code": 200, "request": "http://nba.cloud/games/0022500289/boxscore?Format=json", "time": "2025-11-25 00:38:50.706562"}, "game": {"gameId": "0022500289", "gameTimeLocal": "2025-11-24T19:00:00-06:00", "gameTimeUTC": "2025-11-25T01:00:00Z", "gameTimeHome": "2025-11-24T19:00:00-06:00", "gameTimeAway": "2025-11-24T19:00:00-06:00", "gameEt": "2025-11-24T20:00:00-05:00", "duration": 140, "gameCode": "20251124/CHINOP", "gameStatusText": "Final", "gameStatus": 3, "regulationPeriods": 4, "period": 4, "gameClock": "PT00M00.00S", "attendance": 16690, "sellout": "0", "arena": {"arenaId": 160, "arenaName": "Smoothie King Center", "arenaCity": "New Orleans", "arenaState": "LA", "arenaCountry": "US", "arenaTimezone": "America/Chicago"}, "officials": [{"personId": 2003, "name": "Pat Fraher", "nameI": "P. Fraher", "firstName": "Pat", "familyName": "Fraher", "jerseyNum": "26", "assignment": "OFFICIAL1"}, {"personId": 201246, "name": "Kevin Cutler", "nameI": "K. Cutler", "firstName": "Kevin", "familyName": "Cutler", "jerseyNum": "34", "assignment": "OFFICIAL2"}, {"personId": 1628480, "name": "Robert Hussey", "nameI": "R. Hussey", "firstName": "Robert", "familyName": "Hussey", "jerseyNum": "85", "assignment": "OFFICIAL3"}], "homeTeam": {"teamId": 1610612740, "teamName": "Pelicans", "teamCity": "New Orleans", "teamTricode": "NOP", "score": 143, "inBonus": "1", "timeoutsRemaining": 0, "periods": [{"period": 1, "periodType": "REGULAR", "score": 37}, {"period": 2, "periodType": "REGULAR", "score": 37}, {"period": 3, "periodType": "REGULAR", "score": 34}, {"period": 4, "periodType": "REGULAR", "score": 35}], "players": [{"status": "ACTIVE", "order": 1, "personId": 1630180, "jerseyNum": "41", "position": "SF", "starter": "1", "oncourt": "1", "played": "1", "statistics": {"assists": 3, "blocks": 0, "blocksReceived": 0, "fieldGoalsAttempted": 16, "fieldGoalsMade": 8, "fieldGoalsPercentage": 0.5, "foulsOffensive": 0, "foulsDrawn": 2, "foulsPersonal": 2, "foulsTechnical": 0, "freeThrowsAttempted": 4, "freeThrowsMade": 1, "freeThrowsPercentage": 0.25, "minus": 98.0, "minutes": "PT34M28.90S", "minutesCalculated": "PT34M", "plus": 102.0, "plusMinusPoints": 4.0, "points": 20, "pointsFastBreak": 0, "pointsInThePaint": 10, "pointsSecondChance": 8, "reboundsDefensive": 9, "reboundsOffensive": 4, "reboundsTotal": 13, "steals": 2, "threePointersAttempted": 8, "threePointersMade": 3, "threePointersPercentage": 0.375, "turnovers": 0, "twoPointersAttempted": 8, "twoPointersMade": 5, "twoPointersPercentage": 0.625}, "name": "Saddiq Bey", "nameI": "S. Bey", "firstName": "Saddiq", "familyName": "Bey"}, {"status": "ACTIVE", "order": 2, "personId": 1629627, "jerseyNum": "1", "position": "PF", "starter": "1", "oncourt": "1", "played": "1", "statistics": {"assists": 2, "blocks": 1, "blocksReceived": 0, "fieldGoalsAttempted": 14, "fieldGoalsMade": 8, "fieldGoalsPercentage": 0.5714285714285711, "foulsOffensive": 0, "foulsDrawn": 8, "foulsPersonal": 2, "foulsTechnical": 0, "freeThrowsAttempted": 16, "freeThrowsMade": 13, "freeThrowsPercentage": 0.8125, "minus": 84.0, "minutes": "PT29M37.00S", "minutesCalculated": "PT30M", "plus": 86.0, "plusMinusPoints": 2.0, "points": 29, "pointsFastBreak": 4, "pointsInThePaint": 16, "pointsSecondChance": 0, "reboundsDefensive": 1, "reboundsOffensive": 0, "reboundsTotal": 1, "steals": 2, "threePointersAttempted": 0, "threePointersMade": 0, "threePointersPercentage": 0.0, "turnovers": 2, "twoPointersAttempted": 14, "twoPointersMade": 8, "twoPointersPercentage": 0.5714285714285711}, "name": "Zion Williamson", "nameI": "Z. Williamson", "firstName": "Zion", "familyName": "Williamson"}, {"status": "ACTIVE", "order": 3, "personId": 1642852, "jerseyNum": "22", "position": "C", "starter": "1", "oncourt": "0", "played": "1", "statistics": {"assists": 4, "blocks": 1, "blocksReceived": 0, "fieldGoalsAttempted": 9, "fieldGoalsMade": 4, "fieldGoalsPercentage": 0.444444444444444, "foulsOffensive": 0, "foulsDrawn": 0, "foulsPersonal": 4, "foulsTechnical": 0, "freeThrowsAttempted": 0, "freeThrowsMade": 0, "freeThrowsPercentage": 0.0, "minus": 55.0, "minutes": "PT16M56.10S", "minutesCalculated": "PT17M", "plus": 50.0, "plusMinusPoints": -5.0, "points": 8, "pointsFastBreak": 0, "pointsInThePaint": 8, "pointsSecondChance": 4, "reboundsDefensive": 3, "reboundsOffensive": 2, "reboundsTotal": 5, "steals": 1, "threePointersAttempted": 0, "threePointersMade": 0, "threePointersPercentage": 0.0, "turnovers": 1, "twoPointersAttempted": 9, "twoPointersMade": 4, "twoPointersPercentage": 0.444444444444444}, "name": "Derik Queen", "nameI": "D. Queen", "firstName": "Derik", "familyName": "Queen"}, {"status": "ACTIVE", "order": 4, "personId": 1630530, "jerseyNum": "25", "position": "SG", "starter": "1", "oncourt": "1", "played": "1", "statistics": {"assists": 4, "blocks": 0, "blocksReceived": 1, "fieldGoalsAttempted": 16, "fieldGoalsMade": 7, "fieldGoalsPercentage": 0.4375, "foulsOffensive": 1, "foulsDrawn": 2, "foulsPersonal": 3, "foulsTechnical": 0, "freeThrowsAttempted": 3, "freeThrowsMade": 2, "freeThrowsPercentage": 0.666666666666666, "minus": 88.0, "minutes": "PT36M08.90S", "minutesCalculated": "PT36M", "plus": 108.0, "plusMinusPoints": 20.0, "points": 20, "pointsFastBreak": 2, "pointsInThePaint": 6, "pointsSecondChance": 3, "reboundsDefensive": 4, "reboundsOffensive": 0, "reboundsTotal": 4, "steals": 2, "threePointersAttempted": 10, "threePointersMade": 4, "threePointersPercentage": 0.4, "turnovers": 1, "twoPointersAttempted": 6, "twoPointersMade": 3, "twoPointersPercentage": 0.5}, "name": "Trey Murphy III", "nameI": "T. Murphy III", "firstName": "Trey", "familyName": "Murphy III"}, {"status": "ACTIVE", "order": 5, "personId": 1642847, "jerseyNum": "0", "position": "PG", "starter": "1", "oncourt": "1", "played": "1", "statistics": {"assists": 3, "blocks": 0, "blocksReceived": 0, "fieldGoalsAttempted": 9, "fieldGoalsMade": 4, "fieldGoalsPercentage": 0.444444444444444, "foulsOffensive": 0, "foulsDrawn": 5, "foulsPersonal": 1, "foulsTechnical": 0, "freeThrowsAttempted": 6, "freeThrowsMade": 5, "freeThrowsPercentage": 0.833333333333334, "minus": 70.0, "minutes": "PT24M17.00S", "minutesCalculated": "PT24M", "plus": 74.0, "plusMinusPoints": 4.0, "points": 15, "pointsFastBreak": 0, "pointsInThePaint": 2, "pointsSecondChance": 3, "reboundsDefensive": 4, "reboundsOffensive": 0, "reboundsTotal": 4, "steals": 0, "threePointersAttempted": 3, "threePointersMade": 2, "threePointersPercentage": 0.666666666666666, "turnovers": 1, "twoPointersAttempted": 6, "twoPointersMade": 2, "twoPointersPercentage": 0.333333333333333}, "name": "Jeremiah Fears", "nameI": "J. Fears", "firstName": "Jeremiah", "familyName": "Fears"}, {"status": "ACTIVE", "order": 6, "personId": 1642877, "jerseyNum": "14", "starter": "0", "oncourt": "0", "played": "1", "statistics": {"assists": 2, "blocks": 0, "blocksReceived": 1, "fieldGoalsAttempted": 9, "fieldGoalsMade": 5, "fieldGoalsPercentage": 0.555555555555556, "foulsOffensive": 0, "foulsDrawn": 1, "foulsPersonal": 1, "foulsTechnical": 0, "freeThrowsAttempted": 2, "freeThrowsMade": 0, "freeThrowsPercentage": 0.0, "minus": 49.0, "minutes": "PT19M50.00S", "minutesCalculated": "PT20M", "plus": 62.0, "plusMinusPoints": 13.0, "points": 10, "pointsFastBreak": 4, "pointsInThePaint": 10, "pointsSecondChance": 2, "reboundsDefensive": 2, "reboundsOffensive": 1, "reboundsTotal": 3, "steals": 4, "threePointersAttempted": 2, "threePointersMade": 0, "threePointersPercentage": 0.0, "turnovers": 0, "twoPointersAttempted": 7, "twoPointersMade": 5, "twoPointersPercentage": 0.714285714285714}, "name": "Micah Peavy", "nameI": "M. Peavy", "firstName": "Micah", "familyName": "Peavy"}, {"status": "ACTIVE", "order": 7, "personId": 1630631, "jerseyNum": "15", "starter": "0", "oncourt": "1", "played": "1", "statistics": {"assists": 8, "blocks": 0, "blocksReceived": 0, "fieldGoalsAttempted": 16, "fieldGoalsMade": 7, "fieldGoalsPercentage": 0.4375, "foulsOffensive": 0, "foulsDrawn": 1, "foulsPersonal": 2, "foulsTechnical": 0, "freeThrowsAttempted": 0, "freeThrowsMade": 0, "freeThrowsPercentage": 0.0, "minus": 80.0, "minutes": "PT31M56.00S", "minutesCalculated": "PT32M", "plus": 94.0, "plusMinusPoints": 14.0, "points": 16, "pointsFastBreak": 4, "pointsInThePaint": 10, "pointsSecondChance": 2, "reboundsDefensive": 7, "reboundsOffensive": 1, "reboundsTotal": 8, "steals": 2, "threePointersAttempted": 9, "threePointersMade": 2, "threePointersPercentage": 0.222222222222222, "turnovers": 2, "twoPointersAttempted": 7, "twoPointersMade": 5, "twoPointersPercentage": 0.714285714285714}, "name": "Jose Alvarado", "nameI": "J. Alvarado", "firstName": "Jose", "familyName": "Alvarado"}, {"status": "ACTIVE", "order": 8, "personId": 1642274, "jerseyNum": "21", "starter": "0", "oncourt": "0", "played": "1", "statistics": {"assists": 0, "blocks": 3, "blocksReceived": 0, "fieldGoalsAttempted": 11, "fieldGoalsMade": 7, "fieldGoalsPercentage": 0.636363636363636, "foulsOffensive": 1, "foulsDrawn": 0, "foulsPersonal": 4, "foulsTechnical": 0, "freeThrowsAttempted": 0, "freeThrowsMade": 0, "freeThrowsPercentage": 0.0, "minus": 71.0, "minutes": "PT29M15.10S", "minutesCalculated": "PT29M", "plus": 85.0, "plusMinusPoints": 14.0, "points": 14, "pointsFastBreak": 2, "pointsInThePaint": 14, "pointsSecondChance": 8, "reboundsDefensive": 4, "reboundsOffensive": 10, "reboundsTotal": 14, "steals": 0, "threePointersAttempted": 0, "threePointersMade": 0, "threePointersPercentage": 0.0, "turnovers": 2, "twoPointersAttempted": 11, "twoPointersMade": 7, "twoPointersPercentage": 0.636363636363636}, "name": "Yves Missi", "nameI": "Y. Missi", "firstName": "Yves", "familyName": "Missi"}, {"status": "ACTIVE", "order": 9, "personId": 1631121, "jerseyNum": "11", "starter": "0", "oncourt": "0", "played": "1", "statistics": {"assists": 2, "blocks": 0, "blocksReceived": 1, "fieldGoalsAttempted": 4, "fieldGoalsMade": 3, "fieldGoalsPercentage": 0.75, "foulsOffensive": 1, "foulsDrawn": 2, "foulsPersonal": 2, "foulsTechnical": 0, "freeThrowsAttempted": 4, "freeThrowsMade": 3, "freeThrowsPercentage": 0.75, "minus": 55.0, "minutes": "PT17M31.00S", "minutesCalculated": "PT18M", "plus": 54.0, "plusMinusPoints": -1.0, "points": 11, "pointsFastBreak": 1, "pointsInThePaint": 2, "pointsSecondChance": 0, "reboundsDefensive": 2, "reboundsOffensive": 1, "reboundsTotal": 3, "steals": 0, "threePointersAttempted": 3, "threePointersMade": 2, "threePointersPercentage": 0.666666666666666, "turnovers": 1, "twoPointersAttempted": 1, "twoPointersMade": 1, "twoPointersPercentage": 1.0}, "name": "Bryce McGowens", "nameI": "B. McGowens", "firstName": "Bryce", "familyName": "McGowens"}, {"status": "ACTIVE", "notPlayingReason": "NWT_PERSONAL", "order": 10, "personId": 1641722, "jerseyNum": "24", "starter": "0", "oncourt": "0", "played": "0", "statistics": {"assists": 0, "blocks": 0, "blocksReceived": 0, "fieldGoalsAttempted": 0, "fieldGoalsMade": 0, "fieldGoalsPercentage": 0.0, "foulsOffensive": 0, "foulsDrawn": 0, "foulsPersonal": 0, "foulsTechnical": 0, "freeThrowsAttempted": 0, "freeThrowsMade": 0, "freeThrowsPercentage": 0.0, "minus": 0.0, "minutes": "PT00M00.00S", "minutesCalculated": "PT00M", "plus": 0.0, "plusMinusPoints": 0.0, "points": 0, "pointsFastBreak": 0, "pointsInThePaint": 0, "pointsSecondChance": 0, "reboundsDefensive": 0, "reboundsOffensive": 0, "reboundsTotal": 0, "steals": 0, "threePointersAttempted": 0, "threePointersMade": 0, "threePointersPercentage": 0.0, "turnovers": 0, "twoPointersAttempted": 0, "twoPointersMade": 0, "twoPointersPercentage": 0.0}, "name": "Jordan Hawkins", "nameI": "J. Hawkins", "firstName": "Jordan", "familyName": "Hawkins"}, {"status": "ACTIVE", "order": 11, "personId": 201599, "jerseyNum": "9", "starter": "0", "oncourt": "0", "played": "0", "statistics": {"assists": 0, "blocks": 0, "blocksReceived": 0, "fieldGoalsAttempted": 0, "fieldGoalsMade": 0, "fieldGoalsPercentage": 0.0, "foulsOffensive": 0, "foulsDrawn": 0, "foulsPersonal": 0, "foulsTechnical": 0, "freeThrowsAttempted": 0, "freeThrowsMade": 0, "freeThrowsPercentage": 0.0, "minus": 0.0, "minutes": "PT00M00.00S", "minutesCalculated": "PT00M", "plus": 0.0, "plusMinusPoints": 0.0, "points": 0, "pointsFastBreak": 0, "pointsInThePaint": 0, "pointsSecondChance": 0, "reboundsDefensive": 0, "reboundsOffensive": 0, "reboundsTotal": 0, "steals": 0, "threePointersAttempted": 0, "threePointersMade": 0, "threePointersPercentage": 0.0, "turnovers": 0, "twoPointersAttempted": 0, "twoPointersMade": 0, "twoPointersPercentage": 0.0}, "name": "DeAndre Jordan", "nameI": "D. Jordan", "firstName": "DeAndre", "familyName": "Jordan"}, {"status": "ACTIVE", "order": 12, "personId": 1626172, "jerseyNum": "55", "starter": "0", "oncourt": "0", "played": "0", "statistics": {"assists": 0, "blocks": 0, "blocksReceived": 0, "fieldGoalsAttempted": 0, "fieldGoalsMade": 0, "fieldGoalsPercentage": 0.0, "foulsOffensive": 0, "foulsDrawn": 0, "foulsPersonal": 0, "foulsTechnical": 0, "freeThrowsAttempted": 0, "freeThrowsMade": 0, "freeThrowsPercentage": 0.0, "minus": 0.0, "minutes": "PT00M00.00S", "minutesCalculated": "PT00M", "plus": 0.0, "plusMinusPoints": 0.0, "points": 0, "pointsFastBreak": 0, "pointsInThePaint": 0, "pointsSecondChance": 0, "reboundsDefensive": 0, "reboundsOffensive": 0, "reboundsTotal": 0, "steals": 0, "threePointersAttempted": 0, "threePointersMade": 0, "threePointersPercentage": 0.0, "turnovers": 0, "twoPointersAttempted": 0, "twoPointersMade": 0, "twoPointersPercentage": 0.0}, "name": "Kevon Looney", "nameI": "K. Looney", "firstName": "Kevon", "familyName": "Looney"}, {"status": "INACTIVE", "notPlayingReason": "INACTIVE_GLEAGUE_TWOWAY", "notPlayingDescription": "G League - Two-Way", "order": 13, "personId": 1641725, "jerseyNum": "23", "starter": "0", "oncourt": "0", "played": "0", "statistics": {"assists": 0, "blocks": 0, "blocksReceived": 0, "fieldGoalsAttempted": 0, "fieldGoalsMade": 0, "fieldGoalsPercentage": 0.0, "foulsOffensive": 0, "foulsDrawn": 0, "foulsPersonal": 0, "foulsTechnical": 0, "freeThrowsAttempted": 0, "freeThrowsMade": 0, "freeThrowsPercentage": 0.0, "minus": 0.0, "minutes": "PT00M00.00S", "minutesCalculated": "PT00M", "plus": 0.0, "plusMinusPoints": 0.0, "points": 0, "pointsFastBreak": 0, "pointsInThePaint": 0, "pointsSecondChance": 0, "reboundsDefensive": 0, "reboundsOffensive": 0, "reboundsTotal": 0, "steals": 0, "threePointersAttempted": 0, "threePointersMade": 0, "threePointersPercentage": 0.0, "turnovers": 0, "twoPointersAttempted": 0, "twoPointersMade": 0, "twoPointersPercentage": 0.0}, "name": "Trey Alexander", "nameI": "T. Alexander", "firstName": "Trey", "familyName": "Alexander"}, {"status": "INACTIVE", "notPlayingReason": "INACTIVE_GLEAGUE_TWOWAY", "notPlayingDescription": "G League - Two-Way", "order": 14, "personId": 1630621, "jerseyNum": "4", "starter": "0", "oncourt": "0", "played": "0", "statistics": {"assists": 0, "blocks": 0, "blocksReceived": 0, "fieldGoalsAttempted": 0, "fieldGoalsMade": 0, "fieldGoalsPercentage": 0.0, "foulsOffensive": 0, "foulsDrawn": 0, "foulsPersonal": 0, "foulsTechnical": 0, "freeThrowsAttempted": 0, "freeThrowsMade": 0, "freeThrowsPercentage": 0.0, "minus": 0.0, "minutes": "PT00M00.00S", "minutesCalculated": "PT00M", "plus": 0.0, "plusMinusPoints": 0.0, "points": 0, "pointsFastBreak": 0, "pointsInThePaint": 0, "pointsSecondChance": 0, "reboundsDefensive": 0, "reboundsOffensive": 0, "reboundsTotal": 0, "steals": 0, "threePointersAttempted": 0, "threePointersMade": 0, "threePointersPercentage": 0.0, "turnovers": 0, "twoPointersAttempted": 0, "twoPointersMade": 0, "twoPointersPercentage": 0.0}, "name": "Hunter Dickinson", "nameI": "H. Dickinson", "firstName": "Hunter", "familyName": "Dickinson"}, {"status": "INACTIVE", "notPlayingReason": "INACTIVE_INJURY", "notPlayingDescription": "Right Calf; Strain", "order": 15, "personId": 1630529, "jerseyNum": "2", "starter": "0", "oncourt": "0", "played": "0", "statistics": {"assists": 0, "blocks": 0, "blocksReceived": 0, "fieldGoalsAttempted": 0, "fieldGoalsMade": 0, "fieldGoalsPercentage": 0.0, "foulsOffensive": 0, "foulsDrawn": 0, "foulsPersonal": 0, "foulsTechnical": 0, "freeThrowsAttempted": 0, "freeThrowsMade": 0, "freeThrowsPercentage": 0.0, "minus": 0.0, "minutes": "PT00M00.00S", "minutesCalculated": "PT00M", "plus": 0.0, "plusMinusPoints": 0.0, "points": 0, "pointsFastBreak": 0, "pointsInThePaint": 0, "pointsSecondChance": 0, "reboundsDefensive": 0, "reboundsOffensive": 0, "reboundsTotal": 0, "steals": 0, "threePointersAttempted": 0, "threePointersMade": 0, "threePointersPercentage": 0.0, "turnovers": 0, "twoPointersAttempted": 0, "twoPointersMade": 0, "twoPointersPercentage": 0.0}, "name": "Herbert Jones", "nameI": "H. Jones", "firstName": "Herbert", "familyName": "Jones"}, {"status": "INACTIVE", "notPlayingReason": "INACTIVE_INJURY", "notPlayingDescription": "Right Calf; Strain", "order": 16, "personId": 1631255, "jerseyNum": "17", "starter": "0", "oncourt": "0", "played": "0", "statistics": {"assists": 0, "blocks": 0, "blocksReceived": 0, "fieldGoalsAttempted": 0, "fieldGoalsMade": 0, "fieldGoalsPercentage": 0.0, "foulsOffensive": 0, "foulsDrawn": 0, "foulsPersonal": 0, "foulsTechnical": 0, "freeThrowsAttempted": 0, "freeThrowsMade": 0, "freeThrowsPercentage": 0.0, "minus": 0.0, "minutes": "PT00M00.00S", "minutesCalculated": "PT00M", "plus": 0.0, "plusMinusPoints": 0.0, "points": 0, "pointsFastBreak": 0, "pointsInThePaint": 0, "pointsSecondChance": 0, "reboundsDefensive": 0, "reboundsOffensive": 0, "reboundsTotal": 0, "steals": 0, "threePointersAttempted": 0, "threePointersMade": 0, "threePointersPercentage": 0.0, "turnovers": 0, "twoPointersAttempted": 0, "twoPointersMade": 0, "twoPointersPercentage": 0.0}, "name": "Karlo Matkovi\u0107", "nameI": "K. Matkovi\u0107", "firstName": "Karlo", "familyName": "Matkovi\u0107"}, {"status": "INACTIVE", "notPlayingReason": "INACTIVE_INJURY", "notPlayingDescription": "Right Achilles; Rupture ", "order": 17, "personId": 1627749, "jerseyNum": "5", "starter": "0", "oncourt": "0", "played": "0", "statistics": {"assists": 0, "blocks": 0, "blocksReceived": 0, "fieldGoalsAttempted": 0, "fieldGoalsMade": 0, "fieldGoalsPercentage": 0.0, "foulsOffensive": 0, "foulsDrawn": 0, "foulsPersonal": 0, "foulsTechnical": 0, "freeThrowsAttempted": 0, "freeThrowsMade": 0, "freeThrowsPercentage": 0.0, "minus": 0.0, "minutes": "PT00M00.00S", "minutesCalculated": "PT00M", "plus": 0.0, "plusMinusPoints": 0.0, "points": 0, "pointsFastBreak": 0, "pointsInThePaint": 0, "pointsSecondChance": 0, "reboundsDefensive": 0, "reboundsOffensive": 0, "reboundsTotal": 0, "steals": 0, "threePointersAttempted": 0, "threePointersMade": 0, "threePointersPercentage": 0.0, "turnovers": 0, "twoPointersAttempted": 0, "twoPointersMade": 0, "twoPointersPercentage": 0.0}, "name": "Dejounte Murray", "nameI": "D. Murray", "firstName": "Dejounte", "familyName": "Murray"}, {"status": "INACTIVE", "notPlayingReason": "INACTIVE_INJURY", "notPlayingDescription": "Left Quad; Strain", "order": 18, "personId": 1629673, "jerseyNum": "3", "starter": "0", "oncourt": "0", "played": "0", "statistics": {"assists": 0, "blocks": 0, "blocksReceived": 0, "fieldGoalsAttempted": 0, "fieldGoalsMade": 0, "fieldGoalsPercentage": 0.0, "foulsOffensive": 0, "foulsDrawn": 0, "foulsPersonal": 0, "foulsTechnical": 0, "freeThrowsAttempted": 0, "freeThrowsMade": 0, "freeThrowsPercentage": 0.0, "minus": 0.0, "minutes": "PT00M00.00S", "minutesCalculated": "PT00M", "plus": 0.0, "plusMinusPoints": 0.0, "points": 0, "pointsFastBreak": 0, "pointsInThePaint": 0, "pointsSecondChance": 0, "reboundsDefensive": 0, "reboundsOffensive": 0, "reboundsTotal": 0, "steals": 0, "threePointersAttempted": 0, "threePointersMade": 0, "threePointersPercentage": 0.0, "turnovers": 0, "twoPointersAttempted": 0, "twoPointersMade": 0, "twoPointersPercentage": 0.0}, "name": "Jordan Poole", "nameI": "J. Poole", "firstName": "Jordan", "familyName": "Poole"}], "statistics": {"assists": 28, "assistsTurnoverRatio": 2.0, "benchPoints": 51, "biggestLead": 22, "biggestLeadScore": "33-55", "biggestScoringRun": 15, "biggestScoringRunScore": "32-52", "blocks": 5, "blocksReceived": 3, "fastBreakPointsAttempted": 12, "fastBreakPointsMade": 8, "fastBreakPointsPercentage": 0.666666666666666, "fieldGoalsAttempted": 104, "fieldGoalsEffectiveAdjusted": 0.572115384615385, "fieldGoalsMade": 53, "fieldGoalsPercentage": 0.509615384615385, "foulsOffensive": 3, "foulsDrawn": 21, "foulsPersonal": 21, "foulsTeam": 18, "foulsTechnical": 0, "foulsTeamTechnical": 0, "freeThrowsAttempted": 35, "freeThrowsMade": 24, "freeThrowsPercentage": 0.6857142857142859, "leadChanges": 6, "minutes": "PT240M00.00S", "minutesCalculated": "PT240M", "points": 143, "pointsAgainst": 130, "pointsFastBreak": 17, "pointsFromTurnovers": 23, "pointsInThePaint": 78, "pointsInThePaintAttempted": 67, "pointsInThePaintMade": 39, "pointsInThePaintPercentage": 0.582089552238806, "pointsSecondChance": 30, "reboundsDefensive": 36, "reboundsOffensive": 19, "reboundsPersonal": 55, "reboundsTeam": 15, "reboundsTeamDefensive": 1, "reboundsTeamOffensive": 14, "reboundsTotal": 70, "secondChancePointsAttempted": 21, "secondChancePointsMade": 13, "secondChancePointsPercentage": 0.619047619047619, "steals": 13, "teamFieldGoalAttempts": 1, "threePointersAttempted": 35, "threePointersMade": 13, "threePointersPercentage": 0.37142857142857105, "timeLeading": "PT42M53.00S", "timesTied": 5, "trueShootingAttempts": 119.4, "trueShootingPercentage": 0.598827470686767, "turnovers": 10, "turnoversTeam": 4, "turnoversTotal": 14, "twoPointersAttempted": 69, "twoPointersMade": 40, "twoPointersPercentage": 0.579710144927536}}, "awayTeam": {"teamId": 1610612741, "teamName": "Bulls", "teamCity": "Chicago", "teamTricode": "CHI", "score": 130, "inBonus": "1", "timeoutsRemaining": 2, "periods": [{"period": 1, "periodType": "REGULAR", "score": 30}, {"period": 2, "periodType": "REGULAR", "score": 28}, {"period": 3, "periodType": "REGULAR", "score": 35}, {"period": 4, "periodType": "REGULAR", "score": 37}], "players": [{"status": "ACTIVE", "order": 1, "personId": 1630245, "jerseyNum": "11", "position": "SF", "starter": "1", "oncourt": "1", "played": "1", "statistics": {"assists": 1, "blocks": 0, "blocksReceived": 2, "fieldGoalsAttempted": 16, "fieldGoalsMade": 11, "fieldGoalsPercentage": 0.6875, "foulsOffensive": 0, "foulsDrawn": 3, "foulsPersonal": 1, "foulsTechnical": 0, "freeThrowsAttempted": 5, "freeThrowsMade": 4, "freeThrowsPercentage": 0.8, "minus": 92.0, "minutes": "PT32M10.00S", "minutesCalculated": "PT32M", "plus": 98.0, "plusMinusPoints": 6.0, "points": 28, "pointsFastBreak": 7, "pointsInThePaint": 18, "pointsSecondChance": 0, "reboundsDefensive": 1, "reboundsOffensive": 1, "reboundsTotal": 2, "steals": 0, "threePointersAttempted": 4, "threePointersMade": 2, "threePointersPercentage": 0.5, "turnovers": 1, "twoPointersAttempted": 12, "twoPointersMade": 9, "twoPointersPercentage": 0.75}, "name": "Ayo Dosunmu", "nameI": "A. Dosunmu", "firstName": "Ayo", "familyName": "Dosunmu"}, {"status": "ACTIVE", "order": 2, "personId": 1641824, "jerseyNum": "14", "position": "PF", "starter": "1", "oncourt": "0", "played": "1", "statistics": {"assists": 0, "blocks": 2, "blocksReceived": 1, "fieldGoalsAttempted": 8, "fieldGoalsMade": 4, "fieldGoalsPercentage": 0.5, "foulsOffensive": 0, "foulsDrawn": 1, "foulsPersonal": 3, "foulsTechnical": 0, "freeThrowsAttempted": 0, "freeThrowsMade": 0, "freeThrowsPercentage": 0.0, "minus": 66.0, "minutes": "PT21M14.10S", "minutesCalculated": "PT21M", "plus": 43.0, "plusMinusPoints": -23.0, "points": 10, "pointsFastBreak": 2, "pointsInThePaint": 4, "pointsSecondChance": 3, "reboundsDefensive": 4, "reboundsOffensive": 0, "reboundsTotal": 4, "steals": 0, "threePointersAttempted": 5, "threePointersMade": 2, "threePointersPercentage": 0.4, "turnovers": 2, "twoPointersAttempted": 3, "twoPointersMade": 2, "twoPointersPercentage": 0.666666666666666}, "name": "Matas Buzelis", "nameI": "M. Buzelis", "firstName": "Matas", "familyName": "Buzelis"}, {"status": "ACTIVE", "order": 3, "personId": 1630172, "jerseyNum": "44", "position": "C", "starter": "1", "oncourt": "1", "played": "1", "statistics": {"assists": 2, "blocks": 0, "blocksReceived": 1, "fieldGoalsAttempted": 9, "fieldGoalsMade": 2, "fieldGoalsPercentage": 0.222222222222222, "foulsOffensive": 0, "foulsDrawn": 1, "foulsPersonal": 3, "foulsTechnical": 0, "freeThrowsAttempted": 0, "freeThrowsMade": 0, "freeThrowsPercentage": 0.0, "minus": 79.0, "minutes": "PT27M26.00S", "minutesCalculated": "PT28M", "plus": 72.0, "plusMinusPoints": -7.0, "points": 6, "pointsFastBreak": 0, "pointsInThePaint": 0, "pointsSecondChance": 0, "reboundsDefensive": 4, "reboundsOffensive": 0, "reboundsTotal": 4, "steals": 0, "threePointersAttempted": 7, "threePointersMade": 2, "threePointersPercentage": 0.28571428571428603, "turnovers": 1, "twoPointersAttempted": 2, "twoPointersMade": 0, "twoPointersPercentage": 0.0}, "name": "Patrick Williams", "nameI": "P. Williams", "firstName": "Patrick", "familyName": "Williams"}, {"status": "ACTIVE", "order": 4, "personId": 1629632, "jerseyNum": "0", "position": "SG", "starter": "1", "oncourt": "1", "played": "1", "statistics": {"assists": 6, "blocks": 0, "blocksReceived": 0, "fieldGoalsAttempted": 15, "fieldGoalsMade": 7, "fieldGoalsPercentage": 0.466666666666667, "foulsOffensive": 1, "foulsDrawn": 6, "foulsPersonal": 1, "foulsTechnical": 0, "freeThrowsAttempted": 10, "freeThrowsMade": 7, "freeThrowsPercentage": 0.7, "minus": 103.0, "minutes": "PT35M16.00S", "minutesCalculated": "PT35M", "plus": 102.0, "plusMinusPoints": -1.0, "points": 24, "pointsFastBreak": 5, "pointsInThePaint": 6, "pointsSecondChance": 0, "reboundsDefensive": 5, "reboundsOffensive": 0, "reboundsTotal": 5, "steals": 1, "threePointersAttempted": 10, "threePointersMade": 3, "threePointersPercentage": 0.3, "turnovers": 5, "twoPointersAttempted": 5, "twoPointersMade": 4, "twoPointersPercentage": 0.8}, "name": "Coby White", "nameI": "C. White", "firstName": "Coby", "familyName": "White"}, {"status": "ACTIVE", "order": 5, "personId": 1630581, "jerseyNum": "3", "position": "PG", "starter": "1", "oncourt": "1", "played": "1", "statistics": {"assists": 6, "blocks": 0, "blocksReceived": 0, "fieldGoalsAttempted": 12, "fieldGoalsMade": 6, "fieldGoalsPercentage": 0.5, "foulsOffensive": 0, "foulsDrawn": 3, "foulsPersonal": 3, "foulsTechnical": 1, "freeThrowsAttempted": 6, "freeThrowsMade": 5, "freeThrowsPercentage": 0.833333333333334, "minus": 104.0, "minutes": "PT35M03.00S", "minutesCalculated": "PT35M", "plus": 91.0, "plusMinusPoints": -13.0, "points": 21, "pointsFastBreak": 0, "pointsInThePaint": 4, "pointsSecondChance": 3, "reboundsDefensive": 7, "reboundsOffensive": 0, "reboundsTotal": 7, "steals": 0, "threePointersAttempted": 10, "threePointersMade": 4, "threePointersPercentage": 0.4, "turnovers": 5, "twoPointersAttempted": 2, "twoPointersMade": 2, "twoPointersPercentage": 1.0}, "name": "Josh Giddey", "nameI": "J. Giddey", "firstName": "Josh", "familyName": "Giddey"}, {"status": "ACTIVE", "order": 6, "personId": 1630200, "jerseyNum": "30", "starter": "0", "oncourt": "1", "played": "1", "statistics": {"assists": 11, "blocks": 0, "blocksReceived": 0, "fieldGoalsAttempted": 4, "fieldGoalsMade": 2, "fieldGoalsPercentage": 0.5, "foulsOffensive": 0, "foulsDrawn": 5, "foulsPersonal": 3, "foulsTechnical": 0, "freeThrowsAttempted": 9, "freeThrowsMade": 6, "freeThrowsPercentage": 0.666666666666666, "minus": 84.0, "minutes": "PT27M39.00S", "minutesCalculated": "PT28M", "plus": 74.0, "plusMinusPoints": -10.0, "points": 10, "pointsFastBreak": 0, "pointsInThePaint": 4, "pointsSecondChance": 2, "reboundsDefensive": 1, "reboundsOffensive": 1, "reboundsTotal": 2, "steals": 0, "threePointersAttempted": 1, "threePointersMade": 0, "threePointersPercentage": 0.0, "turnovers": 0, "twoPointersAttempted": 3, "twoPointersMade": 2, "twoPointersPercentage": 0.666666666666666}, "name": "Tre Jones", "nameI": "T. Jones", "firstName": "Tre", "familyName": "Jones"}, {"status": "ACTIVE", "order": 7, "personId": 1641763, "jerseyNum": "15", "starter": "0", "oncourt": "0", "played": "1", "statistics": {"assists": 1, "blocks": 1, "blocksReceived": 0, "fieldGoalsAttempted": 3, "fieldGoalsMade": 3, "fieldGoalsPercentage": 1.0, "foulsOffensive": 0, "foulsDrawn": 0, "foulsPersonal": 1, "foulsTechnical": 0, "freeThrowsAttempted": 0, "freeThrowsMade": 0, "freeThrowsPercentage": 0.0, "minus": 46.0, "minutes": "PT14M37.00S", "minutesCalculated": "PT15M", "plus": 45.0, "plusMinusPoints": -1.0, "points": 7, "pointsFastBreak": 5, "pointsInThePaint": 4, "pointsSecondChance": 0, "reboundsDefensive": 1, "reboundsOffensive": 1, "reboundsTotal": 2, "steals": 1, "threePointersAttempted": 1, "threePointersMade": 1, "threePointersPercentage": 1.0, "turnovers": 1, "twoPointersAttempted": 2, "twoPointersMade": 2, "twoPointersPercentage": 1.0}, "name": "Julian Phillips", "nameI": "J. Phillips", "firstName": "Julian", "familyName": "Phillips"}, {"status": "ACTIVE", "order": 8, "personId": 1630188, "jerseyNum": "25", "starter": "0", "oncourt": "0", "played": "1", "statistics": {"assists": 1, "blocks": 0, "blocksReceived": 0, "fieldGoalsAttempted": 6, "fieldGoalsMade": 4, "fieldGoalsPercentage": 0.666666666666666, "foulsOffensive": 0, "foulsDrawn": 1, "foulsPersonal": 3, "foulsTechnical": 0, "freeThrowsAttempted": 2, "freeThrowsMade": 2, "freeThrowsPercentage": 1.0, "minus": 78.0, "minutes": "PT26M21.90S", "minutesCalculated": "PT26M", "plus": 81.0, "plusMinusPoints": 3.0, "points": 13, "pointsFastBreak": 0, "pointsInThePaint": 2, "pointsSecondChance": 0, "reboundsDefensive": 5, "reboundsOffensive": 1, "reboundsTotal": 6, "steals": 0, "threePointersAttempted": 5, "threePointersMade": 3, "threePointersPercentage": 0.6, "turnovers": 2, "twoPointersAttempted": 1, "twoPointersMade": 1, "twoPointersPercentage": 1.0}, "name": "Jalen Smith", "nameI": "J. Smith", "firstName": "Jalen", "familyName": "Smith"}, {"status": "ACTIVE", "order": 9, "personId": 1628975, "jerseyNum": "5", "starter": "0", "oncourt": "0", "played": "1", "statistics": {"assists": 1, "blocks": 0, "blocksReceived": 0, "fieldGoalsAttempted": 7, "fieldGoalsMade": 4, "fieldGoalsPercentage": 0.5714285714285711, "foulsOffensive": 0, "foulsDrawn": 1, "foulsPersonal": 2, "foulsTechnical": 0, "freeThrowsAttempted": 0, "freeThrowsMade": 0, "freeThrowsPercentage": 0.0, "minus": 57.0, "minutes": "PT18M04.00S", "minutesCalculated": "PT18M", "plus": 44.0, "plusMinusPoints": -13.0, "points": 11, "pointsFastBreak": 2, "pointsInThePaint": 2, "pointsSecondChance": 0, "reboundsDefensive": 1, "reboundsOffensive": 0, "reboundsTotal": 1, "steals": 1, "threePointersAttempted": 6, "threePointersMade": 3, "threePointersPercentage": 0.5, "turnovers": 0, "twoPointersAttempted": 1, "twoPointersMade": 1, "twoPointersPercentage": 1.0}, "name": "Jevon Carter", "nameI": "J. Carter", "firstName": "Jevon", "familyName": "Carter"}, {"status": "ACTIVE", "order": 10, "personId": 1642855, "jerseyNum": "24", "starter": "0", "oncourt": "0", "played": "1", "statistics": {"assists": 0, "blocks": 0, "blocksReceived": 1, "fieldGoalsAttempted": 2, "fieldGoalsMade": 0, "fieldGoalsPercentage": 0.0, "foulsOffensive": 0, "foulsDrawn": 0, "foulsPersonal": 1, "foulsTechnical": 0, "freeThrowsAttempted": 0, "freeThrowsMade": 0, "freeThrowsPercentage": 0.0, "minus": 6.0, "minutes": "PT02M09.00S", "minutesCalculated": "PT02M", "plus": 0.0, "plusMinusPoints": -6.0, "points": 0, "pointsFastBreak": 0, "pointsInThePaint": 0, "pointsSecondChance": 0, "reboundsDefensive": 0, "reboundsOffensive": 0, "reboundsTotal": 0, "steals": 1, "threePointersAttempted": 1, "threePointersMade": 0, "threePointersPercentage": 0.0, "turnovers": 0, "twoPointersAttempted": 1, "twoPointersMade": 0, "twoPointersPercentage": 0.0}, "name": "Noa Essengue", "nameI": "N. Essengue", "firstName": "Noa", "familyName": "Essengue"}, {"status": "ACTIVE", "order": 11, "personId": 1641801, "jerseyNum": "2", "starter": "0", "oncourt": "0", "played": "0", "statistics": {"assists": 0, "blocks": 0, "blocksReceived": 0, "fieldGoalsAttempted": 0, "fieldGoalsMade": 0, "fieldGoalsPercentage": 0.0, "foulsOffensive": 0, "foulsDrawn": 0, "foulsPersonal": 0, "foulsTechnical": 0, "freeThrowsAttempted": 0, "freeThrowsMade": 0, "freeThrowsPercentage": 0.0, "minus": 0.0, "minutes": "PT00M00.00S", "minutesCalculated": "PT00M", "plus": 0.0, "plusMinusPoints": 0.0, "points": 0, "pointsFastBreak": 0, "pointsInThePaint": 0, "pointsSecondChance": 0, "reboundsDefensive": 0, "reboundsOffensive": 0, "reboundsTotal": 0, "steals": 0, "threePointersAttempted": 0, "threePointersMade": 0, "threePointersPercentage": 0.0, "turnovers": 0, "twoPointersAttempted": 0, "twoPointersMade": 0, "twoPointersPercentage": 0.0}, "name": "Emanuel Miller", "nameI": "E. Miller", "firstName": "Emanuel", "familyName": "Miller"}, {"status": "ACTIVE", "order": 12, "personId": 1642950, "jerseyNum": "47", "starter": "0", "oncourt": "0", "played": "0", "statistics": {"assists": 0, "blocks": 0, "blocksReceived": 0, "fieldGoalsAttempted": 0, "fieldGoalsMade": 0, "fieldGoalsPercentage": 0.0, "foulsOffensive": 0, "foulsDrawn": 0, "foulsPersonal": 0, "foulsTechnical": 0, "freeThrowsAttempted": 0, "freeThrowsMade": 0, "freeThrowsPercentage": 0.0, "minus": 0.0, "minutes": "PT00M00.00S", "minutesCalculated": "PT00M", "plus": 0.0, "plusMinusPoints": 0.0, "points": 0, "pointsFastBreak": 0, "pointsInThePaint": 0, "pointsSecondChance": 0, "reboundsDefensive": 0, "reboundsOffensive": 0, "reboundsTotal": 0, "steals": 0, "threePointersAttempted": 0, "threePointersMade": 0, "threePointersPercentage": 0.0, "turnovers": 0, "twoPointersAttempted": 0, "twoPointersMade": 0, "twoPointersPercentage": 0.0}, "name": "Lachlan Olbrich", "nameI": "L. Olbrich", "firstName": "Lachlan", "familyName": "Olbrich"}, {"status": "INACTIVE", "notPlayingReason": "INACTIVE_INJURY", "notPlayingDescription": "Left Scaphoid; Fracture", "order": 13, "personId": 1628380, "jerseyNum": "12", "starter": "0", "oncourt": "0", "played": "0", "statistics": {"assists": 0, "blocks": 0, "blocksReceived": 0, "fieldGoalsAttempted": 0, "fieldGoalsMade": 0, "fieldGoalsPercentage": 0.0, "foulsOffensive": 0, "foulsDrawn": 0, "foulsPersonal": 0, "foulsTechnical": 0, "freeThrowsAttempted": 0, "freeThrowsMade": 0, "freeThrowsPercentage": 0.0, "minus": 0.0, "minutes": "PT00M00.00S", "minutesCalculated": "PT00M", "plus": 0.0, "plusMinusPoints": 0.0, "points": 0, "pointsFastBreak": 0, "pointsInThePaint": 0, "pointsSecondChance": 0, "reboundsDefensive": 0, "reboundsOffensive": 0, "reboundsTotal": 0, "steals": 0, "threePointersAttempted": 0, "threePointersMade": 0, "threePointersPercentage": 0.0, "turnovers": 0, "twoPointersAttempted": 0, "twoPointersMade": 0, "twoPointersPercentage": 0.0}, "name": "Zach Collins", "nameI": "Z. Collins", "firstName": "Zach", "familyName": "Collins"}, {"status": "INACTIVE", "notPlayingReason": "INACTIVE_INJURY", "notPlayingDescription": "N/a; Illness", "order": 14, "personId": 1642280, "jerseyNum": "00", "starter": "0", "oncourt": "0", "played": "0", "statistics": {"assists": 0, "blocks": 0, "blocksReceived": 0, "fieldGoalsAttempted": 0, "fieldGoalsMade": 0, "fieldGoalsPercentage": 0.0, "foulsOffensive": 0, "foulsDrawn": 0, "foulsPersonal": 0, "foulsTechnical": 0, "freeThrowsAttempted": 0, "freeThrowsMade": 0, "freeThrowsPercentage": 0.0, "minus": 0.0, "minutes": "PT00M00.00S", "minutesCalculated": "PT00M", "plus": 0.0, "plusMinusPoints": 0.0, "points": 0, "pointsFastBreak": 0, "pointsInThePaint": 0, "pointsSecondChance": 0, "reboundsDefensive": 0, "reboundsOffensive": 0, "reboundsTotal": 0, "steals": 0, "threePointersAttempted": 0, "threePointersMade": 0, "threePointersPercentage": 0.0, "turnovers": 0, "twoPointersAttempted": 0, "twoPointersMade": 0, "twoPointersPercentage": 0.0}, "name": "Trentyn Flowers", "nameI": "T. Flowers", "firstName": "Trentyn", "familyName": "Flowers"}, {"status": "INACTIVE", "notPlayingReason": "INACTIVE_INJURY", "notPlayingDescription": "N/a; Illness; Left Pelvis Soreness", "order": 15, "personId": 1628989, "jerseyNum": "13", "starter": "0", "oncourt": "0", "played": "0", "statistics": {"assists": 0, "blocks": 0, "blocksReceived": 0, "fieldGoalsAttempted": 0, "fieldGoalsMade": 0, "fieldGoalsPercentage": 0.0, "foulsOffensive": 0, "foulsDrawn": 0, "foulsPersonal": 0, "foulsTechnical": 0, "freeThrowsAttempted": 0, "freeThrowsMade": 0, "freeThrowsPercentage": 0.0, "minus": 0.0, "minutes": "PT00M00.00S", "minutesCalculated": "PT00M", "plus": 0.0, "plusMinusPoints": 0.0, "points": 0, "pointsFastBreak": 0, "pointsInThePaint": 0, "pointsSecondChance": 0, "reboundsDefensive": 0, "reboundsOffensive": 0, "reboundsTotal": 0, "steals": 0, "threePointersAttempted": 0, "threePointersMade": 0, "threePointersPercentage": 0.0, "turnovers": 0, "twoPointersAttempted": 0, "twoPointersMade": 0, "twoPointersPercentage": 0.0}, "name": "Kevin Huerter", "nameI": "K. Huerter", "firstName": "Kevin", "familyName": "Huerter"}, {"status": "INACTIVE", "notPlayingReason": "INACTIVE_INJURY", "notPlayingDescription": "Left Lumbar; Radiculopathy", "order": 16, "personId": 1630171, "jerseyNum": "35", "starter": "0", "oncourt": "0", "played": "0", "statistics": {"assists": 0, "blocks": 0, "blocksReceived": 0, "fieldGoalsAttempted": 0, "fieldGoalsMade": 0, "fieldGoalsPercentage": 0.0, "foulsOffensive": 0, "foulsDrawn": 0, "foulsPersonal": 0, "foulsTechnical": 0, "freeThrowsAttempted": 0, "freeThrowsMade": 0, "freeThrowsPercentage": 0.0, "minus": 0.0, "minutes": "PT00M00.00S", "minutesCalculated": "PT00M", "plus": 0.0, "plusMinusPoints": 0.0, "points": 0, "pointsFastBreak": 0, "pointsInThePaint": 0, "pointsSecondChance": 0, "reboundsDefensive": 0, "reboundsOffensive": 0, "reboundsTotal": 0, "steals": 0, "threePointersAttempted": 0, "threePointersMade": 0, "threePointersPercentage": 0.0, "turnovers": 0, "twoPointersAttempted": 0, "twoPointersMade": 0, "twoPointersPercentage": 0.0}, "name": "Isaac Okoro", "nameI": "I. Okoro", "firstName": "Isaac", "familyName": "Okoro"}, {"status": "INACTIVE", "notPlayingReason": "INACTIVE_INJURY", "notPlayingDescription": "Left Calf; Strain", "order": 17, "personId": 1631207, "jerseyNum": "7", "starter": "0", "oncourt": "0", "played": "0", "statistics": {"assists": 0, "blocks": 0, "blocksReceived": 0, "fieldGoalsAttempted": 0, "fieldGoalsMade": 0, "fieldGoalsPercentage": 0.0, "foulsOffensive": 0, "foulsDrawn": 0, "foulsPersonal": 0, "foulsTechnical": 0, "freeThrowsAttempted": 0, "freeThrowsMade": 0, "freeThrowsPercentage": 0.0, "minus": 0.0, "minutes": "PT00M00.00S", "minutesCalculated": "PT00M", "plus": 0.0, "plusMinusPoints": 0.0, "points": 0, "pointsFastBreak": 0, "pointsInThePaint": 0, "pointsSecondChance": 0, "reboundsDefensive": 0, "reboundsOffensive": 0, "reboundsTotal": 0, "steals": 0, "threePointersAttempted": 0, "threePointersMade": 0, "threePointersPercentage": 0.0, "turnovers": 0, "twoPointersAttempted": 0, "twoPointersMade": 0, "twoPointersPercentage": 0.0}, "name": "Dalen Terry", "nameI": "D. Terry", "firstName": "Dalen", "familyName": "Terry"}, {"status": "INACTIVE", "notPlayingReason": "INACTIVE_INJURY", "notPlayingDescription": "Right Knee; Soreness", "order": 18, "personId": 202696, "jerseyNum": "9", "starter": "0", "oncourt": "0", "played": "0", "statistics": {"assists": 0, "blocks": 0, "blocksReceived": 0, "fieldGoalsAttempted": 0, "fieldGoalsMade": 0, "fieldGoalsPercentage": 0.0, "foulsOffensive": 0, "foulsDrawn": 0, "foulsPersonal": 0, "foulsTechnical": 0, "freeThrowsAttempted": 0, "freeThrowsMade": 0, "freeThrowsPercentage": 0.0, "minus": 0.0, "minutes": "PT00M00.00S", "minutesCalculated": "PT00M", "plus": 0.0, "plusMinusPoints": 0.0, "points": 0, "pointsFastBreak": 0, "pointsInThePaint": 0, "pointsSecondChance": 0, "reboundsDefensive": 0, "reboundsOffensive": 0, "reboundsTotal": 0, "steals": 0, "threePointersAttempted": 0, "threePointersMade": 0, "threePointersPercentage": 0.0, "turnovers": 0, "twoPointersAttempted": 0, "twoPointersMade": 0, "twoPointersPercentage": 0.0}, "name": "Nikola Vu\u010devi\u0107", "nameI": "N. Vu\u010devi\u0107", "firstName": "Nikola", "familyName": "Vu\u010devi\u0107"}], "statistics": {"assists": 29, "assistsTurnoverRatio": 1.70588235294118, "benchPoints": 41, "biggestLead": 5, "biggestLeadScore": "6-1", "biggestScoringRun": 15, "biggestScoringRunScore": "32-52", "blocks": 3, "blocksReceived": 5, "fastBreakPointsAttempted": 12, "fastBreakPointsMade": 9, "fastBreakPointsPercentage": 0.75, "fieldGoalsAttempted": 82, "fieldGoalsEffectiveAdjusted": 0.646341463414634, "fieldGoalsMade": 43, "fieldGoalsPercentage": 0.524390243902439, "foulsOffensive": 1, "foulsDrawn": 21, "foulsPersonal": 21, "foulsTeam": 20, "foulsTechnical": 1, "foulsTeamTechnical": 1, "freeThrowsAttempted": 32, "freeThrowsMade": 24, "freeThrowsPercentage": 0.75, "leadChanges": 6, "minutes": "PT240M00.00S", "minutesCalculated": "PT240M", "points": 130, "pointsAgainst": 143, "pointsFastBreak": 21, "pointsFromTurnovers": 19, "pointsInThePaint": 44, "pointsInThePaintAttempted": 31, "pointsInThePaintMade": 22, "pointsInThePaintPercentage": 0.709677419354839, "pointsSecondChance": 8, "reboundsDefensive": 29, "reboundsOffensive": 4, "reboundsPersonal": 33, "reboundsTeam": 8, "reboundsTeamDefensive": 1, "reboundsTeamOffensive": 7, "reboundsTotal": 41, "secondChancePointsAttempted": 5, "secondChancePointsMade": 3, "secondChancePointsPercentage": 0.6, "steals": 4, "teamFieldGoalAttempts": 1, "threePointersAttempted": 50, "threePointersMade": 20, "threePointersPercentage": 0.4, "timeLeading": "PT02M22.00S", "timesTied": 5, "trueShootingAttempts": 96.08, "trueShootingPercentage": 0.676519567027477, "turnovers": 17, "turnoversTeam": 0, "turnoversTotal": 17, "twoPointersAttempted": 32, "twoPointersMade": 23, "twoPointersPercentage": 0.71875}}}}