{"meta": {"version": 1, "code": 200, "request": "http://nba.cloud/games/0022500213/boxscore?Format=json", "time": "2025-11-12 23:45:47.081562"}, "game": {"gameId": "0022500213", "gameTimeLocal": "2025-11-12T19:00:00-05:00", "gameTimeUTC": "2025-11-13T00:00:00Z", "gameTimeHome": "2025-11-12T19:00:00-05:00", "gameTimeAway": "2025-11-12T18:00:00-06:00", "gameEt": "2025-11-12T19:00:00-05:00", "duration": 133, "gameCode": "20251112/MILCHA", "gameStatusText": "Final", "gameStatus": 3, "regulationPeriods": 4, "period": 4, "gameClock": "PT00M00.00S", "attendance": 17142, "sellout": "0", "arena": {"arenaId": 9, "arenaName": "Spectrum Center", "arenaCity": "Charlotte", "arenaState": "NC", "arenaCountry": "US", "arenaTimezone": "America/New_York"}, "officials": [{"personId": 202027, "name": "Tre Maddox", "nameI": "T. Maddox", "firstName": "Tre", "familyName": "Maddox", "jerseyNum": "23", "assignment": "OFFICIAL1"}, {"personId": 1627534, "name": "Andy Nagy", "nameI": "A. Nagy", "firstName": "Andy", "familyName": "Nagy", "jerseyNum": "83", "assignment": "OFFICIAL2"}, {"personId": 1627539, "name": "Tyler Ricks", "nameI": "T. Ricks", "firstName": "Tyler", "familyName": "Ricks", "jerseyNum": "95", "assignment": "OFFICIAL3"}], "homeTeam": {"teamId": 1610612766, "teamName": "Hornets", "teamCity": "Charlotte", "teamTricode": "CHA", "score": 111, "inBonus": "1", "timeoutsRemaining": 2, "periods": [{"period": 1, "periodType": "REGULAR", "score": 35}, {"period": 2, "periodType": "REGULAR", "score": 24}, {"period": 3, "periodType": "REGULAR", "score": 24}, {"period": 4, "periodType": "REGULAR", "score": 28}], "players": [{"status": "ACTIVE", "order": 1, "personId": 1642851, "jerseyNum": "7", "position": "SF", "starter": "1", "oncourt": "0", "played": "1", "statistics": {"assists": 1, "blocks": 0, "blocksReceived": 0, "fieldGoalsAttempted": 13, "fieldGoalsMade": 5, "fieldGoalsPercentage": 0.384615384615385, "foulsOffensive": 0, "foulsDrawn": 3, "foulsPersonal": 1, "foulsTechnical": 0, "freeThrowsAttempted": 4, "freeThrowsMade": 3, "freeThrowsPercentage": 0.75, "minus": 72.0, "minutes": "PT34M18.40S", "minutesCalculated": "PT34M", "plus": 78.0, "plusMinusPoints": 6.0, "points": 16, "pointsFastBreak": 3, "pointsInThePaint": 4, "pointsSecondChance": 0, "reboundsDefensive": 6, "reboundsOffensive": 0, "reboundsTotal": 6, "steals": 0, "threePointersAttempted": 8, "threePointersMade": 3, "threePointersPercentage": 0.375, "turnovers": 3, "twoPointersAttempted": 5, "twoPointersMade": 2, "twoPointersPercentage": 0.4}, "name": "Kon Knueppel", "nameI": "K. Knueppel", "firstName": "Kon", "familyName": "Knueppel"}, {"status": "ACTIVE", "order": 2, "personId": 1628970, "jerseyNum": "0", "position": "PF", "starter": "1", "oncourt": "0", "played": "1", "statistics": {"assists": 6, "blocks": 0, "blocksReceived": 1, "fieldGoalsAttempted": 19, "fieldGoalsMade": 7, "fieldGoalsPercentage": 0.368421052631579, "foulsOffensive": 0, "foulsDrawn": 3, "foulsPersonal": 2, "foulsTechnical": 0, "freeThrowsAttempted": 4, "freeThrowsMade": 4, "freeThrowsPercentage": 1.0, "minus": 70.0, "minutes": "PT32M48.00S", "minutesCalculated": "PT33M", "plus": 85.0, "plusMinusPoints": 15.0, "points": 20, "pointsFastBreak": 2, "pointsInThePaint": 10, "pointsSecondChance": 2, "reboundsDefensive": 5, "reboundsOffensive": 1, "reboundsTotal": 6, "steals": 1, "threePointersAttempted": 10, "threePointersMade": 2, "threePointersPercentage": 0.2, "turnovers": 3, "twoPointersAttempted": 9, "twoPointersMade": 5, "twoPointersPercentage": 0.555555555555556}, "name": "Miles Bridges", "nameI": "M. Bridges", "firstName": "Miles", "familyName": "Bridges"}, {"status": "ACTIVE", "order": 3, "personId": 1641750, "jerseyNum": "11", "position": "C", "starter": "1", "oncourt": "0", "played": "1", "statistics": {"assists": 0, "blocks": 3, "blocksReceived": 0, "fieldGoalsAttempted": 8, "fieldGoalsMade": 8, "fieldGoalsPercentage": 1.0, "foulsOffensive": 0, "foulsDrawn": 1, "foulsPersonal": 3, "foulsTechnical": 0, "freeThrowsAttempted": 1, "freeThrowsMade": 1, "freeThrowsPercentage": 1.0, "minus": 48.0, "minutes": "PT26M31.00S", "minutesCalculated": "PT27M", "plus": 65.0, "plusMinusPoints": 17.0, "points": 17, "pointsFastBreak": 0, "pointsInThePaint": 16, "pointsSecondChance": 6, "reboundsDefensive": 5, "reboundsOffensive": 4, "reboundsTotal": 9, "steals": 1, "threePointersAttempted": 0, "threePointersMade": 0, "threePointersPercentage": 0.0, "turnovers": 0, "twoPointersAttempted": 8, "twoPointersMade": 8, "twoPointersPercentage": 1.0}, "name": "Ryan Kalkbrenner", "nameI": "R. Kalkbrenner", "firstName": "Ryan", "familyName": "Kalkbrenner"}, {"status": "ACTIVE", "order": 4, "personId": 1642883, "jerseyNum": "4", "position": "SG", "starter": "1", "oncourt": "0", "played": "1", "statistics": {"assists": 1, "blocks": 0, "blocksReceived": 1, "fieldGoalsAttempted": 5, "fieldGoalsMade": 1, "fieldGoalsPercentage": 0.2, "foulsOffensive": 0, "foulsDrawn": 2, "foulsPersonal": 1, "foulsTechnical": 0, "freeThrowsAttempted": 2, "freeThrowsMade": 2, "freeThrowsPercentage": 1.0, "minus": 59.0, "minutes": "PT29M45.00S", "minutesCalculated": "PT30M", "plus": 77.0, "plusMinusPoints": 18.0, "points": 4, "pointsFastBreak": 0, "pointsInThePaint": 2, "pointsSecondChance": 0, "reboundsDefensive": 2, "reboundsOffensive": 0, "reboundsTotal": 2, "steals": 0, "threePointersAttempted": 1, "threePointersMade": 0, "threePointersPercentage": 0.0, "turnovers": 0, "twoPointersAttempted": 4, "twoPointersMade": 1, "twoPointersPercentage": 0.25}, "name": "Sion James", "nameI": "S. James", "firstName": "Sion", "familyName": "James"}, {"status": "ACTIVE", "order": 5, "personId": 1629012, "jerseyNum": "8", "position": "PG", "starter": "1", "oncourt": "0", "played": "1", "statistics": {"assists": 8, "blocks": 0, "blocksReceived": 1, "fieldGoalsAttempted": 14, "fieldGoalsMade": 5, "fieldGoalsPercentage": 0.357142857142857, "foulsOffensive": 1, "foulsDrawn": 5, "foulsPersonal": 1, "foulsTechnical": 0, "freeThrowsAttempted": 6, "freeThrowsMade": 5, "freeThrowsPercentage": 0.833333333333334, "minus": 53.0, "minutes": "PT31M32.00S", "minutesCalculated": "PT32M", "plus": 82.0, "plusMinusPoints": 29.0, "points": 16, "pointsFastBreak": 2, "pointsInThePaint": 6, "pointsSecondChance": 2, "reboundsDefensive": 5, "reboundsOffensive": 0, "reboundsTotal": 5, "steals": 2, "threePointersAttempted": 5, "threePointersMade": 1, "threePointersPercentage": 0.2, "turnovers": 3, "twoPointersAttempted": 9, "twoPointersMade": 4, "twoPointersPercentage": 0.444444444444444}, "name": "Collin Sexton", "nameI": "C. Sexton", "firstName": "Collin", "familyName": "Sexton"}, {"status": "ACTIVE", "order": 6, "personId": 1631217, "jerseyNum": "14", "starter": "0", "oncourt": "1", "played": "1", "statistics": {"assists": 2, "blocks": 1, "blocksReceived": 2, "fieldGoalsAttempted": 3, "fieldGoalsMade": 1, "fieldGoalsPercentage": 0.333333333333333, "foulsOffensive": 0, "foulsDrawn": 5, "foulsPersonal": 2, "foulsTechnical": 0, "freeThrowsAttempted": 6, "freeThrowsMade": 5, "freeThrowsPercentage": 0.833333333333334, "minus": 55.0, "minutes": "PT23M10.00S", "minutesCalculated": "PT23M", "plus": 47.0, "plusMinusPoints": -8.0, "points": 7, "pointsFastBreak": 0, "pointsInThePaint": 2, "pointsSecondChance": 1, "reboundsDefensive": 5, "reboundsOffensive": 8, "reboundsTotal": 13, "steals": 1, "threePointersAttempted": 0, "threePointersMade": 0, "threePointersPercentage": 0.0, "turnovers": 1, "twoPointersAttempted": 3, "twoPointersMade": 1, "twoPointersPercentage": 0.333333333333333}, "name": "Moussa Diabat\u00e9", "nameI": "M. Diabat\u00e9", "firstName": "Moussa", "familyName": "Diabat\u00e9"}, {"status": "ACTIVE", "order": 7, "personId": 1642354, "jerseyNum": "25", "starter": "0", "oncourt": "0", "played": "1", "statistics": {"assists": 2, "blocks": 0, "blocksReceived": 0, "fieldGoalsAttempted": 4, "fieldGoalsMade": 1, "fieldGoalsPercentage": 0.25, "foulsOffensive": 0, "foulsDrawn": 1, "foulsPersonal": 0, "foulsTechnical": 0, "freeThrowsAttempted": 0, "freeThrowsMade": 0, "freeThrowsPercentage": 0.0, "minus": 26.0, "minutes": "PT09M01.00S", "minutesCalculated": "PT09M", "plus": 15.0, "plusMinusPoints": -11.0, "points": 2, "pointsFastBreak": 0, "pointsInThePaint": 2, "pointsSecondChance": 0, "reboundsDefensive": 2, "reboundsOffensive": 0, "reboundsTotal": 2, "steals": 0, "threePointersAttempted": 2, "threePointersMade": 0, "threePointersPercentage": 0.0, "turnovers": 0, "twoPointersAttempted": 2, "twoPointersMade": 1, "twoPointersPercentage": 0.5}, "name": "KJ Simpson", "nameI": "K. Simpson", "firstName": "KJ", "familyName": "Simpson"}, {"status": "ACTIVE", "order": 8, "personId": 1630544, "jerseyNum": "23", "starter": "0", "oncourt": "1", "played": "1", "statistics": {"assists": 3, "blocks": 1, "blocksReceived": 0, "fieldGoalsAttempted": 10, "fieldGoalsMade": 5, "fieldGoalsPercentage": 0.5, "foulsOffensive": 1, "foulsDrawn": 0, "foulsPersonal": 3, "foulsTechnical": 0, "freeThrowsAttempted": 0, "freeThrowsMade": 0, "freeThrowsPercentage": 0.0, "minus": 57.0, "minutes": "PT25M24.60S", "minutesCalculated": "PT25M", "plus": 51.0, "plusMinusPoints": -6.0, "points": 13, "pointsFastBreak": 0, "pointsInThePaint": 4, "pointsSecondChance": 6, "reboundsDefensive": 1, "reboundsOffensive": 0, "reboundsTotal": 1, "steals": 0, "threePointersAttempted": 7, "threePointersMade": 3, "threePointersPercentage": 0.428571428571429, "turnovers": 3, "twoPointersAttempted": 3, "twoPointersMade": 2, "twoPointersPercentage": 0.666666666666666}, "name": "Tre Mann", "nameI": "T. Mann", "firstName": "Tre", "familyName": "Mann"}, {"status": "ACTIVE", "order": 9, "personId": 1642862, "jerseyNum": "33", "starter": "0", "oncourt": "1", "played": "1", "statistics": {"assists": 2, "blocks": 0, "blocksReceived": 1, "fieldGoalsAttempted": 4, "fieldGoalsMade": 1, "fieldGoalsPercentage": 0.25, "foulsOffensive": 0, "foulsDrawn": 1, "foulsPersonal": 1, "foulsTechnical": 0, "freeThrowsAttempted": 2, "freeThrowsMade": 2, "freeThrowsPercentage": 1.0, "minus": 23.0, "minutes": "PT11M55.00S", "minutesCalculated": "PT12M", "plus": 28.0, "plusMinusPoints": 5.0, "points": 5, "pointsFastBreak": 0, "pointsInThePaint": 0, "pointsSecondChance": 2, "reboundsDefensive": 2, "reboundsOffensive": 1, "reboundsTotal": 3, "steals": 0, "threePointersAttempted": 3, "threePointersMade": 1, "threePointersPercentage": 0.333333333333333, "turnovers": 0, "twoPointersAttempted": 1, "twoPointersMade": 0, "twoPointersPercentage": 0.0}, "name": "Liam McNeeley", "nameI": "L. McNeeley", "firstName": "Liam", "familyName": "McNeeley"}, {"status": "ACTIVE", "order": 10, "personId": 1626192, "jerseyNum": "21", "starter": "0", "oncourt": "1", "played": "1", "statistics": {"assists": 2, "blocks": 0, "blocksReceived": 0, "fieldGoalsAttempted": 6, "fieldGoalsMade": 4, "fieldGoalsPercentage": 0.666666666666666, "foulsOffensive": 0, "foulsDrawn": 1, "foulsPersonal": 1, "foulsTechnical": 0, "freeThrowsAttempted": 2, "freeThrowsMade": 1, "freeThrowsPercentage": 0.5, "minus": 21.0, "minutes": "PT11M16.00S", "minutesCalculated": "PT11M", "plus": 22.0, "plusMinusPoints": 1.0, "points": 11, "pointsFastBreak": 5, "pointsInThePaint": 4, "pointsSecondChance": 0, "reboundsDefensive": 2, "reboundsOffensive": 0, "reboundsTotal": 2, "steals": 0, "threePointersAttempted": 4, "threePointersMade": 2, "threePointersPercentage": 0.5, "turnovers": 0, "twoPointersAttempted": 2, "twoPointersMade": 2, "twoPointersPercentage": 1.0}, "name": "Pat Connaughton", "nameI": "P. Connaughton", "firstName": "Pat", "familyName": "Connaughton"}, {"status": "ACTIVE", "order": 11, "personId": 203486, "jerseyNum": "22", "starter": "0", "oncourt": "1", "played": "1", "statistics": {"assists": 0, "blocks": 0, "blocksReceived": 0, "fieldGoalsAttempted": 0, "fieldGoalsMade": 0, "fieldGoalsPercentage": 0.0, "foulsOffensive": 0, "foulsDrawn": 0, "foulsPersonal": 0, "foulsTechnical": 0, "freeThrowsAttempted": 0, "freeThrowsMade": 0, "freeThrowsPercentage": 0.0, "minus": 16.0, "minutes": "PT04M19.00S", "minutesCalculated": "PT04M", "plus": 5.0, "plusMinusPoints": -11.0, "points": 0, "pointsFastBreak": 0, "pointsInThePaint": 0, "pointsSecondChance": 0, "reboundsDefensive": 0, "reboundsOffensive": 1, "reboundsTotal": 1, "steals": 0, "threePointersAttempted": 0, "threePointersMade": 0, "threePointersPercentage": 0.0, "turnovers": 0, "twoPointersAttempted": 0, "twoPointersMade": 0, "twoPointersPercentage": 0.0}, "name": "Mason Plumlee", "nameI": "M. Plumlee", "firstName": "Mason", "familyName": "Plumlee"}, {"status": "ACTIVE", "notPlayingReason": "DND_INJURY", "notPlayingDescription": "Right Knee; Surgery", "order": 12, "personId": 1629684, "jerseyNum": "2", "starter": "0", "oncourt": "0", "played": "0", "statistics": {"assists": 0, "blocks": 0, "blocksReceived": 0, "fieldGoalsAttempted": 0, "fieldGoalsMade": 0, "fieldGoalsPercentage": 0.0, "foulsOffensive": 0, "foulsDrawn": 0, "foulsPersonal": 0, "foulsTechnical": 0, "freeThrowsAttempted": 0, "freeThrowsMade": 0, "freeThrowsPercentage": 0.0, "minus": 0.0, "minutes": "PT00M00.00S", "minutesCalculated": "PT00M", "plus": 0.0, "plusMinusPoints": 0.0, "points": 0, "pointsFastBreak": 0, "pointsInThePaint": 0, "pointsSecondChance": 0, "reboundsDefensive": 0, "reboundsOffensive": 0, "reboundsTotal": 0, "steals": 0, "threePointersAttempted": 0, "threePointersMade": 0, "threePointersPercentage": 0.0, "turnovers": 0, "twoPointersAttempted": 0, "twoPointersMade": 0, "twoPointersPercentage": 0.0}, "name": "Grant Williams", "nameI": "G. Williams", "firstName": "Grant", "familyName": "Williams"}, {"status": "INACTIVE", "notPlayingReason": "INACTIVE_INJURY", "notPlayingDescription": "Right Ankle; Impingement", "order": 13, "personId": 1630163, "jerseyNum": "1", "starter": "0", "oncourt": "0", "played": "0", "statistics": {"assists": 0, "blocks": 0, "blocksReceived": 0, "fieldGoalsAttempted": 0, "fieldGoalsMade": 0, "fieldGoalsPercentage": 0.0, "foulsOffensive": 0, "foulsDrawn": 0, "foulsPersonal": 0, "foulsTechnical": 0, "freeThrowsAttempted": 0, "freeThrowsMade": 0, "freeThrowsPercentage": 0.0, "minus": 0.0, "minutes": "PT00M00.00S", "minutesCalculated": "PT00M", "plus": 0.0, "plusMinusPoints": 0.0, "points": 0, "pointsFastBreak": 0, "pointsInThePaint": 0, "pointsSecondChance": 0, "reboundsDefensive": 0, "reboundsOffensive": 0, "reboundsTotal": 0, "steals": 0, "threePointersAttempted": 0, "threePointersMade": 0, "threePointersPercentage": 0.0, "turnovers": 0, "twoPointersAttempted": 0, "twoPointersMade": 0, "twoPointersPercentage": 0.0}, "name": "LaMelo Ball", "nameI": "L. Ball", "firstName": "LaMelo", "familyName": "Ball"}, {"status": "INACTIVE", "notPlayingReason": "INACTIVE_INJURY", "notPlayingDescription": "Left Shoulder; Surgery", "order": 14, "personId": 1630182, "jerseyNum": "10", "starter": "0", "oncourt": "0", "played": "0", "statistics": {"assists": 0, "blocks": 0, "blocksReceived": 0, "fieldGoalsAttempted": 0, "fieldGoalsMade": 0, "fieldGoalsPercentage": 0.0, "foulsOffensive": 0, "foulsDrawn": 0, "foulsPersonal": 0, "foulsTechnical": 0, "freeThrowsAttempted": 0, "freeThrowsMade": 0, "freeThrowsPercentage": 0.0, "minus": 0.0, "minutes": "PT00M00.00S", "minutesCalculated": "PT00M", "plus": 0.0, "plusMinusPoints": 0.0, "points": 0, "pointsFastBreak": 0, "pointsInThePaint": 0, "pointsSecondChance": 0, "reboundsDefensive": 0, "reboundsOffensive": 0, "reboundsTotal": 0, "steals": 0, "threePointersAttempted": 0, "threePointersMade": 0, "threePointersPercentage": 0.0, "turnovers": 0, "twoPointersAttempted": 0, "twoPointersMade": 0, "twoPointersPercentage": 0.0}, "name": "Josh Green", "nameI": "J. Green", "firstName": "Josh", "familyName": "Green"}, {"status": "INACTIVE", "notPlayingReason": "INACTIVE_INJURY", "notPlayingDescription": "Left Shoulder; Subluxation", "order": 15, "personId": 1641706, "jerseyNum": "24", "starter": "0", "oncourt": "0", "played": "0", "statistics": {"assists": 0, "blocks": 0, "blocksReceived": 0, "fieldGoalsAttempted": 0, "fieldGoalsMade": 0, "fieldGoalsPercentage": 0.0, "foulsOffensive": 0, "foulsDrawn": 0, "foulsPersonal": 0, "foulsTechnical": 0, "freeThrowsAttempted": 0, "freeThrowsMade": 0, "freeThrowsPercentage": 0.0, "minus": 0.0, "minutes": "PT00M00.00S", "minutesCalculated": "PT00M", "plus": 0.0, "plusMinusPoints": 0.0, "points": 0, "pointsFastBreak": 0, "pointsInThePaint": 0, "pointsSecondChance": 0, "reboundsDefensive": 0, "reboundsOffensive": 0, "reboundsTotal": 0, "steals": 0, "threePointersAttempted": 0, "threePointersMade": 0, "threePointersPercentage": 0.0, "turnovers": 0, "twoPointersAttempted": 0, "twoPointersMade": 0, "twoPointersPercentage": 0.0}, "name": "Brandon Miller", "nameI": "B. Miller", "firstName": "Brandon", "familyName": "Miller"}, {"status": "INACTIVE", "notPlayingReason": "INACTIVE_GLEAGUE_TWOWAY", "order": 16, "personId": 1641809, "jerseyNum": "9", "starter": "0", "oncourt": "0", "played": "0", "statistics": {"assists": 0, "blocks": 0, "blocksReceived": 0, "fieldGoalsAttempted": 0, "fieldGoalsMade": 0, "fieldGoalsPercentage": 0.0, "foulsOffensive": 0, "foulsDrawn": 0, "foulsPersonal": 0, "foulsTechnical": 0, "freeThrowsAttempted": 0, "freeThrowsMade": 0, "freeThrowsPercentage": 0.0, "minus": 0.0, "minutes": "PT00M00.00S", "minutesCalculated": "PT00M", "plus": 0.0, "plusMinusPoints": 0.0, "points": 0, "pointsFastBreak": 0, "pointsInThePaint": 0, "pointsSecondChance": 0, "reboundsDefensive": 0, "reboundsOffensive": 0, "reboundsTotal": 0, "steals": 0, "threePointersAttempted": 0, "threePointersMade": 0, "threePointersPercentage": 0.0, "turnovers": 0, "twoPointersAttempted": 0, "twoPointersMade": 0, "twoPointersPercentage": 0.0}, "name": "Drew Peterson", "nameI": "D. Peterson", "firstName": "Drew", "familyName": "Peterson"}, {"status": "INACTIVE", "order": 17, "personId": 1641810, "jerseyNum": "12", "starter": "0", "oncourt": "0", "played": "0", "statistics": {"assists": 0, "blocks": 0, "blocksReceived": 0, "fieldGoalsAttempted": 0, "fieldGoalsMade": 0, "fieldGoalsPercentage": 0.0, "foulsOffensive": 0, "foulsDrawn": 0, "foulsPersonal": 0, "foulsTechnical": 0, "freeThrowsAttempted": 0, "freeThrowsMade": 0, "freeThrowsPercentage": 0.0, "minus": 0.0, "minutes": "PT00M00.00S", "minutesCalculated": "PT00M", "plus": 0.0, "plusMinusPoints": 0.0, "points": 0, "pointsFastBreak": 0, "pointsInThePaint": 0, "pointsSecondChance": 0, "reboundsDefensive": 0, "reboundsOffensive": 0, "reboundsTotal": 0, "steals": 0, "threePointersAttempted": 0, "threePointersMade": 0, "threePointersPercentage": 0.0, "turnovers": 0, "twoPointersAttempted": 0, "twoPointersMade": 0, "twoPointersPercentage": 0.0}, "name": "Antonio Reeves", "nameI": "A. Reeves", "firstName": "Antonio", "familyName": "Reeves"}, {"status": "INACTIVE", "notPlayingReason": "INACTIVE_GLEAGUE_ON_ASSIGNMENT", "order": 18, "personId": 1642275, "jerseyNum": "31", "starter": "0", "oncourt": "0", "played": "0", "statistics": {"assists": 0, "blocks": 0, "blocksReceived": 0, "fieldGoalsAttempted": 0, "fieldGoalsMade": 0, "fieldGoalsPercentage": 0.0, "foulsOffensive": 0, "foulsDrawn": 0, "foulsPersonal": 0, "foulsTechnical": 0, "freeThrowsAttempted": 0, "freeThrowsMade": 0, "freeThrowsPercentage": 0.0, "minus": 0.0, "minutes": "PT00M00.00S", "minutesCalculated": "PT00M", "plus": 0.0, "plusMinusPoints": 0.0, "points": 0, "pointsFastBreak": 0, "pointsInThePaint": 0, "pointsSecondChance": 0, "reboundsDefensive": 0, "reboundsOffensive": 0, "reboundsTotal": 0, "steals": 0, "threePointersAttempted": 0, "threePointersMade": 0, "threePointersPercentage": 0.0, "turnovers": 0, "twoPointersAttempted": 0, "twoPointersMade": 0, "twoPointersPercentage": 0.0}, "name": "Tidjane Sala\u00fcn", "nameI": "T. Sala\u00fcn", "firstName": "Tidjane", "familyName": "Sala\u00fcn"}], "statistics": {"assists": 27, "assistsTurnoverRatio": 1.6875, "benchPoints": 38, "biggestLead": 22, "biggestLeadScore": "84-106", "biggestScoringRun": 9, "biggestScoringRunScore": "56-75", "blocks": 5, "blocksReceived": 6, "fastBreakPointsAttempted": 11, "fastBreakPointsMade": 5, "fastBreakPointsPercentage": 0.45454545454545503, "fieldGoalsAttempted": 86, "fieldGoalsEffectiveAdjusted": 0.511627906976744, "fieldGoalsMade": 38, "fieldGoalsPercentage": 0.441860465116279, "foulsOffensive": 2, "foulsDrawn": 22, "foulsPersonal": 15, "foulsTeam": 13, "foulsTechnical": 0, "foulsTeamTechnical": 0, "freeThrowsAttempted": 27, "freeThrowsMade": 23, "freeThrowsPercentage": 0.8518518518518521, "leadChanges": 4, "minutes": "PT240M00.00S", "minutesCalculated": "PT240M", "points": 111, "pointsAgainst": 100, "pointsFastBreak": 12, "pointsFromTurnovers": 9, "pointsInThePaint": 50, "pointsInThePaintAttempted": 43, "pointsInThePaintMade": 25, "pointsInThePaintPercentage": 0.581395348837209, "pointsSecondChance": 19, "reboundsDefensive": 35, "reboundsOffensive": 15, "reboundsPersonal": 50, "reboundsTeam": 15, "reboundsTeamDefensive": 3, "reboundsTeamOffensive": 12, "reboundsTotal": 65, "secondChancePointsAttempted": 18, "secondChancePointsMade": 7, "secondChancePointsPercentage": 0.388888888888889, "steals": 5, "teamFieldGoalAttempts": 1, "threePointersAttempted": 40, "threePointersMade": 12, "threePointersPercentage": 0.3, "timeLeading": "PT44M23.00S", "timesTied": 4, "trueShootingAttempts": 97.88, "trueShootingPercentage": 0.56702084184716, "turnovers": 13, "turnoversTeam": 3, "turnoversTotal": 16, "twoPointersAttempted": 46, "twoPointersMade": 26, "twoPointersPercentage": 0.565217391304348}}, "awayTeam": {"teamId": 1610612749, "teamName": "Bucks", "teamCity": "Milwaukee", "teamTricode": "MIL", "score": 100, "inBonus": "1", "timeoutsRemaining": 1, "periods": [{"period": 1, "periodType": "REGULAR", "score": 27}, {"period": 2, "periodType": "REGULAR", "score": 23}, {"period": 3, "periodType": "REGULAR", "score": 22}, {"period": 4, "periodType": "REGULAR", "score": 28}], "players": [{"status": "ACTIVE", "order": 1, "personId": 1629018, "jerseyNum": "5", "position": "SF", "starter": "1", "oncourt": "0", "played": "1", "statistics": {"assists": 4, "blocks": 0, "blocksReceived": 0, "fieldGoalsAttempted": 5, "fieldGoalsMade": 1, "fieldGoalsPercentage": 0.2, "foulsOffensive": 0, "foulsDrawn": 0, "foulsPersonal": 1, "foulsTechnical": 0, "freeThrowsAttempted": 0, "freeThrowsMade": 0, "freeThrowsPercentage": 0.0, "minus": 77.0, "minutes": "PT29M17.00S", "minutesCalculated": "PT29M", "plus": 52.0, "plusMinusPoints": -25.0, "points": 2, "pointsFastBreak": 2, "pointsInThePaint": 2, "pointsSecondChance": 0, "reboundsDefensive": 0, "reboundsOffensive": 0, "reboundsTotal": 0, "steals": 1, "threePointersAttempted": 2, "threePointersMade": 0, "threePointersPercentage": 0.0, "turnovers": 1, "twoPointersAttempted": 3, "twoPointersMade": 1, "twoPointersPercentage": 0.333333333333333}, "name": "Gary Trent Jr.", "nameI": "G. Trent Jr.", "firstName": "Gary", "familyName": "Trent Jr."}, {"status": "ACTIVE", "order": 2, "personId": 1628398, "jerseyNum": "18", "position": "PF", "starter": "1", "oncourt": "0", "played": "1", "statistics": {"assists": 4, "blocks": 1, "blocksReceived": 1, "fieldGoalsAttempted": 12, "fieldGoalsMade": 3, "fieldGoalsPercentage": 0.25, "foulsOffensive": 0, "foulsDrawn": 2, "foulsPersonal": 2, "foulsTechnical": 0, "freeThrowsAttempted": 4, "freeThrowsMade": 2, "freeThrowsPercentage": 0.5, "minus": 76.0, "minutes": "PT29M44.00S", "minutesCalculated": "PT30M", "plus": 64.0, "plusMinusPoints": -12.0, "points": 8, "pointsFastBreak": 2, "pointsInThePaint": 6, "pointsSecondChance": 0, "reboundsDefensive": 2, "reboundsOffensive": 1, "reboundsTotal": 3, "steals": 1, "threePointersAttempted": 2, "threePointersMade": 0, "threePointersPercentage": 0.0, "turnovers": 1, "twoPointersAttempted": 10, "twoPointersMade": 3, "twoPointersPercentage": 0.3}, "name": "Kyle Kuzma", "nameI": "K. Kuzma", "firstName": "Kyle", "familyName": "Kuzma"}, {"status": "ACTIVE", "order": 3, "personId": 1626167, "jerseyNum": "3", "position": "C", "starter": "1", "oncourt": "0", "played": "1", "statistics": {"assists": 2, "blocks": 2, "blocksReceived": 2, "fieldGoalsAttempted": 14, "fieldGoalsMade": 7, "fieldGoalsPercentage": 0.5, "foulsOffensive": 1, "foulsDrawn": 4, "foulsPersonal": 3, "foulsTechnical": 0, "freeThrowsAttempted": 5, "freeThrowsMade": 4, "freeThrowsPercentage": 0.8, "minus": 73.0, "minutes": "PT28M51.00S", "minutesCalculated": "PT29M", "plus": 62.0, "plusMinusPoints": -11.0, "points": 21, "pointsFastBreak": 3, "pointsInThePaint": 8, "pointsSecondChance": 3, "reboundsDefensive": 1, "reboundsOffensive": 2, "reboundsTotal": 3, "steals": 2, "threePointersAttempted": 8, "threePointersMade": 3, "threePointersPercentage": 0.375, "turnovers": 1, "twoPointersAttempted": 6, "twoPointersMade": 4, "twoPointersPercentage": 0.666666666666666}, "name": "Myles Turner", "nameI": "M. Turner", "firstName": "Myles", "familyName": "Turner"}, {"status": "ACTIVE", "order": 4, "personId": 1631260, "jerseyNum": "20", "position": "SG", "starter": "1", "oncourt": "0", "played": "1", "statistics": {"assists": 2, "blocks": 0, "blocksReceived": 0, "fieldGoalsAttempted": 4, "fieldGoalsMade": 1, "fieldGoalsPercentage": 0.25, "foulsOffensive": 0, "foulsDrawn": 2, "foulsPersonal": 2, "foulsTechnical": 0, "freeThrowsAttempted": 0, "freeThrowsMade": 0, "freeThrowsPercentage": 0.0, "minus": 65.0, "minutes": "PT26M51.00S", "minutesCalculated": "PT27M", "plus": 56.0, "plusMinusPoints": -9.0, "points": 3, "pointsFastBreak": 0, "pointsInThePaint": 0, "pointsSecondChance": 0, "reboundsDefensive": 3, "reboundsOffensive": 0, "reboundsTotal": 3, "steals": 0, "threePointersAttempted": 3, "threePointersMade": 1, "threePointersPercentage": 0.333333333333333, "turnovers": 0, "twoPointersAttempted": 1, "twoPointersMade": 0, "twoPointersPercentage": 0.0}, "name": "AJ Green", "nameI": "A. Green", "firstName": "AJ", "familyName": "Green"}, {"status": "ACTIVE", "order": 5, "personId": 1631157, "jerseyNum": "13", "position": "PG", "starter": "1", "oncourt": "0", "played": "1", "statistics": {"assists": 6, "blocks": 0, "blocksReceived": 1, "fieldGoalsAttempted": 15, "fieldGoalsMade": 10, "fieldGoalsPercentage": 0.666666666666666, "foulsOffensive": 0, "foulsDrawn": 1, "foulsPersonal": 3, "foulsTechnical": 0, "freeThrowsAttempted": 2, "freeThrowsMade": 1, "freeThrowsPercentage": 0.5, "minus": 76.0, "minutes": "PT31M46.00S", "minutesCalculated": "PT32M", "plus": 71.0, "plusMinusPoints": -5.0, "points": 25, "pointsFastBreak": 3, "pointsInThePaint": 8, "pointsSecondChance": 0, "reboundsDefensive": 3, "reboundsOffensive": 2, "reboundsTotal": 5, "steals": 1, "threePointersAttempted": 6, "threePointersMade": 4, "threePointersPercentage": 0.666666666666666, "turnovers": 2, "twoPointersAttempted": 9, "twoPointersMade": 6, "twoPointersPercentage": 0.666666666666666}, "name": "Ryan Rollins", "nameI": "R. Rollins", "firstName": "Ryan", "familyName": "Rollins"}, {"status": "ACTIVE", "order": 6, "personId": 1626171, "jerseyNum": "9", "starter": "0", "oncourt": "0", "played": "1", "statistics": {"assists": 1, "blocks": 0, "blocksReceived": 1, "fieldGoalsAttempted": 12, "fieldGoalsMade": 7, "fieldGoalsPercentage": 0.583333333333333, "foulsOffensive": 1, "foulsDrawn": 1, "foulsPersonal": 3, "foulsTechnical": 0, "freeThrowsAttempted": 0, "freeThrowsMade": 0, "freeThrowsPercentage": 0.0, "minus": 49.0, "minutes": "PT23M11.00S", "minutesCalculated": "PT23M", "plus": 43.0, "plusMinusPoints": -6.0, "points": 14, "pointsFastBreak": 0, "pointsInThePaint": 12, "pointsSecondChance": 2, "reboundsDefensive": 5, "reboundsOffensive": 3, "reboundsTotal": 8, "steals": 0, "threePointersAttempted": 1, "threePointersMade": 0, "threePointersPercentage": 0.0, "turnovers": 2, "twoPointersAttempted": 11, "twoPointersMade": 7, "twoPointersPercentage": 0.636363636363636}, "name": "Bobby Portis", "nameI": "B. Portis", "firstName": "Bobby", "familyName": "Portis"}, {"status": "ACTIVE", "order": 7, "personId": 1630579, "jerseyNum": "00", "starter": "0", "oncourt": "0", "played": "1", "statistics": {"assists": 2, "blocks": 0, "blocksReceived": 0, "fieldGoalsAttempted": 2, "fieldGoalsMade": 1, "fieldGoalsPercentage": 0.5, "foulsOffensive": 0, "foulsDrawn": 1, "foulsPersonal": 1, "foulsTechnical": 0, "freeThrowsAttempted": 0, "freeThrowsMade": 0, "freeThrowsPercentage": 0.0, "minus": 38.0, "minutes": "PT17M59.00S", "minutesCalculated": "PT18M", "plus": 30.0, "plusMinusPoints": -8.0, "points": 2, "pointsFastBreak": 0, "pointsInThePaint": 2, "pointsSecondChance": 0, "reboundsDefensive": 5, "reboundsOffensive": 2, "reboundsTotal": 7, "steals": 0, "threePointersAttempted": 0, "threePointersMade": 0, "threePointersPercentage": 0.0, "turnovers": 1, "twoPointersAttempted": 2, "twoPointersMade": 1, "twoPointersPercentage": 0.5}, "name": "Jericho Sims", "nameI": "J. Sims", "firstName": "Jericho", "familyName": "Sims"}, {"status": "ACTIVE", "order": 8, "personId": 1630175, "jerseyNum": "50", "starter": "0", "oncourt": "0", "played": "1", "statistics": {"assists": 3, "blocks": 0, "blocksReceived": 0, "fieldGoalsAttempted": 12, "fieldGoalsMade": 2, "fieldGoalsPercentage": 0.166666666666667, "foulsOffensive": 0, "foulsDrawn": 1, "foulsPersonal": 2, "foulsTechnical": 0, "freeThrowsAttempted": 0, "freeThrowsMade": 0, "freeThrowsPercentage": 0.0, "minus": 35.0, "minutes": "PT15M00.00S", "minutesCalculated": "PT15M", "plus": 17.0, "plusMinusPoints": -18.0, "points": 4, "pointsFastBreak": 0, "pointsInThePaint": 2, "pointsSecondChance": 0, "reboundsDefensive": 2, "reboundsOffensive": 0, "reboundsTotal": 2, "steals": 0, "threePointersAttempted": 2, "threePointersMade": 0, "threePointersPercentage": 0.0, "turnovers": 0, "twoPointersAttempted": 10, "twoPointersMade": 2, "twoPointersPercentage": 0.2}, "name": "Cole Anthony", "nameI": "C. Anthony", "firstName": "Cole", "familyName": "Anthony"}, {"status": "ACTIVE", "order": 9, "personId": 1629599, "jerseyNum": "17", "starter": "0", "oncourt": "0", "played": "1", "statistics": {"assists": 0, "blocks": 0, "blocksReceived": 0, "fieldGoalsAttempted": 3, "fieldGoalsMade": 1, "fieldGoalsPercentage": 0.333333333333333, "foulsOffensive": 0, "foulsDrawn": 2, "foulsPersonal": 1, "foulsTechnical": 0, "freeThrowsAttempted": 0, "freeThrowsMade": 0, "freeThrowsPercentage": 0.0, "minus": 24.0, "minutes": "PT11M38.00S", "minutesCalculated": "PT11M", "plus": 17.0, "plusMinusPoints": -7.0, "points": 2, "pointsFastBreak": 0, "pointsInThePaint": 2, "pointsSecondChance": 0, "reboundsDefensive": 1, "reboundsOffensive": 0, "reboundsTotal": 1, "steals": 0, "threePointersAttempted": 0, "threePointersMade": 0, "threePointersPercentage": 0.0, "turnovers": 0, "twoPointersAttempted": 3, "twoPointersMade": 1, "twoPointersPercentage": 0.333333333333333}, "name": "Amir Coffey", "nameI": "A. Coffey", "firstName": "Amir", "familyName": "Coffey"}, {"status": "ACTIVE", "order": 10, "personId": 1641813, "jerseyNum": "19", "starter": "0", "oncourt": "1", "played": "1", "statistics": {"assists": 1, "blocks": 0, "blocksReceived": 0, "fieldGoalsAttempted": 3, "fieldGoalsMade": 2, "fieldGoalsPercentage": 0.666666666666666, "foulsOffensive": 0, "foulsDrawn": 1, "foulsPersonal": 1, "foulsTechnical": 0, "freeThrowsAttempted": 2, "freeThrowsMade": 1, "freeThrowsPercentage": 0.5, "minus": 12.0, "minutes": "PT05M52.00S", "minutesCalculated": "PT06M", "plus": 19.0, "plusMinusPoints": 7.0, "points": 7, "pointsFastBreak": 0, "pointsInThePaint": 0, "pointsSecondChance": 0, "reboundsDefensive": 0, "reboundsOffensive": 0, "reboundsTotal": 0, "steals": 0, "threePointersAttempted": 3, "threePointersMade": 2, "threePointersPercentage": 0.666666666666666, "turnovers": 1, "twoPointersAttempted": 0, "twoPointersMade": 0, "twoPointersPercentage": 0.0}, "name": "Mark Sears", "nameI": "M. Sears", "firstName": "Mark", "familyName": "Sears"}, {"status": "ACTIVE", "order": 11, "personId": 203914, "jerseyNum": "11", "starter": "0", "oncourt": "1", "played": "1", "statistics": {"assists": 1, "blocks": 0, "blocksReceived": 0, "fieldGoalsAttempted": 0, "fieldGoalsMade": 0, "fieldGoalsPercentage": 0.0, "foulsOffensive": 0, "foulsDrawn": 0, "foulsPersonal": 0, "foulsTechnical": 0, "freeThrowsAttempted": 0, "freeThrowsMade": 0, "freeThrowsPercentage": 0.0, "minus": 10.0, "minutes": "PT05M41.00S", "minutesCalculated": "PT06M", "plus": 19.0, "plusMinusPoints": 9.0, "points": 0, "pointsFastBreak": 0, "pointsInThePaint": 0, "pointsSecondChance": 0, "reboundsDefensive": 0, "reboundsOffensive": 0, "reboundsTotal": 0, "steals": 1, "threePointersAttempted": 0, "threePointersMade": 0, "threePointersPercentage": 0.0, "turnovers": 0, "twoPointersAttempted": 0, "twoPointersMade": 0, "twoPointersPercentage": 0.0}, "name": "Gary Harris", "nameI": "G. Harris", "firstName": "Gary", "familyName": "Harris"}, {"status": "ACTIVE", "order": 12, "personId": 1641748, "jerseyNum": "44", "starter": "0", "oncourt": "1", "played": "1", "statistics": {"assists": 3, "blocks": 1, "blocksReceived": 0, "fieldGoalsAttempted": 0, "fieldGoalsMade": 0, "fieldGoalsPercentage": 0.0, "foulsOffensive": 0, "foulsDrawn": 0, "foulsPersonal": 2, "foulsTechnical": 0, "freeThrowsAttempted": 0, "freeThrowsMade": 0, "freeThrowsPercentage": 0.0, "minus": 10.0, "minutes": "PT05M41.00S", "minutesCalculated": "PT06M", "plus": 19.0, "plusMinusPoints": 9.0, "points": 0, "pointsFastBreak": 0, "pointsInThePaint": 0, "pointsSecondChance": 0, "reboundsDefensive": 1, "reboundsOffensive": 0, "reboundsTotal": 1, "steals": 0, "threePointersAttempted": 0, "threePointersMade": 0, "threePointersPercentage": 0.0, "turnovers": 0, "twoPointersAttempted": 0, "twoPointersMade": 0, "twoPointersPercentage": 0.0}, "name": "Andre Jackson Jr.", "nameI": "A. Jackson Jr.", "firstName": "Andre", "familyName": "Jackson Jr."}, {"status": "ACTIVE", "order": 13, "personId": 1631250, "jerseyNum": "35", "starter": "0", "oncourt": "1", "played": "1", "statistics": {"assists": 0, "blocks": 0, "blocksReceived": 0, "fieldGoalsAttempted": 5, "fieldGoalsMade": 4, "fieldGoalsPercentage": 0.8, "foulsOffensive": 0, "foulsDrawn": 0, "foulsPersonal": 0, "foulsTechnical": 0, "freeThrowsAttempted": 0, "freeThrowsMade": 0, "freeThrowsPercentage": 0.0, "minus": 5.0, "minutes": "PT04M19.00S", "minutesCalculated": "PT04M", "plus": 16.0, "plusMinusPoints": 11.0, "points": 10, "pointsFastBreak": 2, "pointsInThePaint": 4, "pointsSecondChance": 0, "reboundsDefensive": 1, "reboundsOffensive": 0, "reboundsTotal": 1, "steals": 0, "threePointersAttempted": 3, "threePointersMade": 2, "threePointersPercentage": 0.666666666666666, "turnovers": 0, "twoPointersAttempted": 2, "twoPointersMade": 2, "twoPointersPercentage": 1.0}, "name": "Pete Nance", "nameI": "P. Nance", "firstName": "Pete", "familyName": "Nance"}, {"status": "ACTIVE", "order": 14, "personId": 203648, "jerseyNum": "43", "starter": "0", "oncourt": "1", "played": "1", "statistics": {"assists": 0, "blocks": 2, "blocksReceived": 0, "fieldGoalsAttempted": 1, "fieldGoalsMade": 1, "fieldGoalsPercentage": 1.0, "foulsOffensive": 0, "foulsDrawn": 0, "foulsPersonal": 1, "foulsTechnical": 0, "freeThrowsAttempted": 0, "freeThrowsMade": 0, "freeThrowsPercentage": 0.0, "minus": 5.0, "minutes": "PT04M10.00S", "minutesCalculated": "PT04M", "plus": 15.0, "plusMinusPoints": 10.0, "points": 2, "pointsFastBreak": 0, "pointsInThePaint": 2, "pointsSecondChance": 0, "reboundsDefensive": 0, "reboundsOffensive": 0, "reboundsTotal": 0, "steals": 0, "threePointersAttempted": 0, "threePointersMade": 0, "threePointersPercentage": 0.0, "turnovers": 0, "twoPointersAttempted": 1, "twoPointersMade": 1, "twoPointersPercentage": 1.0}, "name": "Thanasis Antetokounmpo", "nameI": "T. Antetokounmpo", "firstName": "Thanasis", "familyName": "Antetokounmpo"}, {"status": "INACTIVE", "notPlayingReason": "INACTIVE_GLEAGUE_TWOWAY", "order": 15, "personId": 1630828, "jerseyNum": "29", "starter": "0", "oncourt": "0", "played": "0", "statistics": {"assists": 0, "blocks": 0, "blocksReceived": 0, "fieldGoalsAttempted": 0, "fieldGoalsMade": 0, "fieldGoalsPercentage": 0.0, "foulsOffensive": 0, "foulsDrawn": 0, "foulsPersonal": 0, "foulsTechnical": 0, "freeThrowsAttempted": 0, "freeThrowsMade": 0, "freeThrowsPercentage": 0.0, "minus": 0.0, "minutes": "PT00M00.00S", "minutesCalculated": "PT00M", "plus": 0.0, "plusMinusPoints": 0.0, "points": 0, "pointsFastBreak": 0, "pointsInThePaint": 0, "pointsSecondChance": 0, "reboundsDefensive": 0, "reboundsOffensive": 0, "reboundsTotal": 0, "steals": 0, "threePointersAttempted": 0, "threePointersMade": 0, "threePointersPercentage": 0.0, "turnovers": 0, "twoPointersAttempted": 0, "twoPointersMade": 0, "twoPointersPercentage": 0.0}, "name": "Alex Antetokounmpo", "nameI": "A. Antetokounmpo", "firstName": "Alex", "familyName": "Antetokounmpo"}, {"status": "INACTIVE", "notPlayingReason": "INACTIVE_INJURY", "notPlayingDescription": "Left Knee; Patellar Tendinopathy ", "order": 16, "personId": 203507, "jerseyNum": "34", "starter": "0", "oncourt": "0", "played": "0", "statistics": {"assists": 0, "blocks": 0, "blocksReceived": 0, "fieldGoalsAttempted": 0, "fieldGoalsMade": 0, "fieldGoalsPercentage": 0.0, "foulsOffensive": 0, "foulsDrawn": 0, "foulsPersonal": 0, "foulsTechnical": 0, "freeThrowsAttempted": 0, "freeThrowsMade": 0, "freeThrowsPercentage": 0.0, "minus": 0.0, "minutes": "PT00M00.00S", "minutesCalculated": "PT00M", "plus": 0.0, "plusMinusPoints": 0.0, "points": 0, "pointsFastBreak": 0, "pointsInThePaint": 0, "pointsSecondChance": 0, "reboundsDefensive": 0, "reboundsOffensive": 0, "reboundsTotal": 0, "steals": 0, "threePointersAttempted": 0, "threePointersMade": 0, "threePointersPercentage": 0.0, "turnovers": 0, "twoPointersAttempted": 0, "twoPointersMade": 0, "twoPointersPercentage": 0.0}, "name": "Giannis Antetokounmpo", "nameI": "G. Antetokounmpo", "firstName": "Giannis", "familyName": "Antetokounmpo"}, {"status": "INACTIVE", "notPlayingReason": "INACTIVE_INJURY", "notPlayingDescription": "Right Knee; Meniscus Surgery", "order": 17, "personId": 1629645, "jerseyNum": "7", "starter": "0", "oncourt": "0", "played": "0", "statistics": {"assists": 0, "blocks": 0, "blocksReceived": 0, "fieldGoalsAttempted": 0, "fieldGoalsMade": 0, "fieldGoalsPercentage": 0.0, "foulsOffensive": 0, "foulsDrawn": 0, "foulsPersonal": 0, "foulsTechnical": 0, "freeThrowsAttempted": 0, "freeThrowsMade": 0, "freeThrowsPercentage": 0.0, "minus": 0.0, "minutes": "PT00M00.00S", "minutesCalculated": "PT00M", "plus": 0.0, "plusMinusPoints": 0.0, "points": 0, "pointsFastBreak": 0, "pointsInThePaint": 0, "pointsSecondChance": 0, "reboundsDefensive": 0, "reboundsOffensive": 0, "reboundsTotal": 0, "steals": 0, "threePointersAttempted": 0, "threePointersMade": 0, "threePointersPercentage": 0.0, "turnovers": 0, "twoPointersAttempted": 0, "twoPointersMade": 0, "twoPointersPercentage": 0.0}, "name": "Kevin Porter Jr.", "nameI": "K. Porter Jr.", "firstName": "Kevin", "familyName": "Porter Jr."}, {"status": "INACTIVE", "notPlayingReason": "INACTIVE_INJURY", "notPlayingDescription": "Neck; Herniated Disk", "order": 18, "personId": 1627752, "jerseyNum": "12", "starter": "0", "oncourt": "0", "played": "0", "statistics": {"assists": 0, "blocks": 0, "blocksReceived": 0, "fieldGoalsAttempted": 0, "fieldGoalsMade": 0, "fieldGoalsPercentage": 0.0, "foulsOffensive": 0, "foulsDrawn": 0, "foulsPersonal": 0, "foulsTechnical": 0, "freeThrowsAttempted": 0, "freeThrowsMade": 0, "freeThrowsPercentage": 0.0, "minus": 0.0, "minutes": "PT00M00.00S", "minutesCalculated": "PT00M", "plus": 0.0, "plusMinusPoints": 0.0, "points": 0, "pointsFastBreak": 0, "pointsInThePaint": 0, "pointsSecondChance": 0, "reboundsDefensive": 0, "reboundsOffensive": 0, "reboundsTotal": 0, "steals": 0, "threePointersAttempted": 0, "threePointersMade": 0, "threePointersPercentage": 0.0, "turnovers": 0, "twoPointersAttempted": 0, "twoPointersMade": 0, "twoPointersPercentage": 0.0}, "name": "Taurean Prince", "nameI": "T. Prince", "firstName": "Taurean", "familyName": "Prince"}], "statistics": {"assists": 29, "assistsTurnoverRatio": 3.22222222222222, "benchPoints": 41, "biggestLead": 3, "biggestLeadScore": "8-5", "biggestScoringRun": 9, "biggestScoringRunScore": "56-75", "blocks": 6, "blocksReceived": 5, "fastBreakPointsAttempted": 7, "fastBreakPointsMade": 4, "fastBreakPointsPercentage": 0.5714285714285711, "fieldGoalsAttempted": 88, "fieldGoalsEffectiveAdjusted": 0.522727272727273, "fieldGoalsMade": 40, "fieldGoalsPercentage": 0.45454545454545503, "foulsOffensive": 2, "foulsDrawn": 15, "foulsPersonal": 22, "foulsTeam": 20, "foulsTechnical": 0, "foulsTeamTechnical": 0, "freeThrowsAttempted": 13, "freeThrowsMade": 8, "freeThrowsPercentage": 0.615384615384615, "leadChanges": 4, "minutes": "PT240M00.00S", "minutesCalculated": "PT240M", "points": 100, "pointsAgainst": 111, "pointsFastBreak": 12, "pointsFromTurnovers": 24, "pointsInThePaint": 48, "pointsInThePaintAttempted": 47, "pointsInThePaintMade": 24, "pointsInThePaintPercentage": 0.5106382978723399, "pointsSecondChance": 5, "reboundsDefensive": 24, "reboundsOffensive": 10, "reboundsPersonal": 34, "reboundsTeam": 7, "reboundsTeamDefensive": 2, "reboundsTeamOffensive": 5, "reboundsTotal": 41, "secondChancePointsAttempted": 10, "secondChancePointsMade": 2, "secondChancePointsPercentage": 0.2, "steals": 6, "teamFieldGoalAttempts": 0, "threePointersAttempted": 30, "threePointersMade": 12, "threePointersPercentage": 0.4, "timeLeading": "PT01M54.00S", "timesTied": 4, "trueShootingAttempts": 93.72, "trueShootingPercentage": 0.533504054630815, "turnovers": 9, "turnoversTeam": 0, "turnoversTotal": 9, "twoPointersAttempted": 58, "twoPointersMade": 28, "twoPointersPercentage": 0.482758620689655}}}}